Workbook
Name sel_loc: 'Supuestos'!$B$3
Name sel_locIdx: 'Supuestos'!$C$3
Name sel_cfg: 'Supuestos'!$B$4
Name sel_cfgIdx: 'Supuestos'!$C$4
Name sel_escIdx: 'Supuestos'!$C$5
Name cfg_units: 'Supuestos'!$K$3:$K$7
Name esc_salarios: 'Supuestos'!$E$11
Name esc_retorno: 'Supuestos'!$E$12
Name esc_inflacion: 'Supuestos'!$E$13
Name esc_retraso: 'Supuestos'!$E$14
Name esc_probMatch: 'Supuestos'!$E$15
Name esc_apreciacion: 'Supuestos'!$E$16
Name esc_tasaHipoteca: 'Supuestos'!$E$17
Name esc_gastos: 'Supuestos'!$E$18
Name esc_probExamenes: 'Supuestos'!$E$19
Name general_anioInicio: 'Supuestos'!$C$54
Name general_horizonte: 'Supuestos'!$C$55
Name general_edad: 'Supuestos'!$C$56
Name general_inflacion: 'Supuestos'!$C$57
Name general_retornoInversion: 'Supuestos'!$C$58
Name general_retornoEfectivo: 'Supuestos'!$C$59
Name general_tasaAhorro: 'Supuestos'!$C$60
Name general_reservaMeses: 'Supuestos'!$C$61
Name general_tasaDeudaConsumo: 'Supuestos'!$C$62
Name personal_tarifaHora: 'Supuestos'!$C$63
Name personal_horasSemana: 'Supuestos'!$C$64
Name personal_liquidoInicial: 'Supuestos'!$C$65
Name personal_retiroInicial: 'Supuestos'!$C$66
Name personal_irsSaldo: 'Supuestos'!$C$67
Name personal_irsPagoMensual: 'Supuestos'!$C$68
Name personal_deudaEstudiantil: 'Supuestos'!$C$69
Name personal_tasaDeudaEstudiantil: 'Supuestos'!$C$70
Name personal_deudaEsFederal: 'Supuestos'!$C$71
Name personal_aporte403bPct: 'Supuestos'!$C$72
Name personal_match403bPct: 'Supuestos'!$C$73
Name personal_rothAnual: 'Supuestos'!$C$74
Name personal_bsnFin: 'Supuestos'!$C$75
Name personal_bsnCostoRestante: 'Supuestos'!$C$76
Name personal_bsnAumento: 'Supuestos'!$C$77
Name personal_llcActivo: 'Supuestos'!$C$78
Name personal_llcNeto: 'Supuestos'!$C$79
Name personal_llcCrecimiento: 'Supuestos'!$C$80
Name personal_aporteFamiliaMensual: 'Supuestos'!$C$81
Name personal_costoMudanzaInicial: 'Supuestos'!$C$82
Name impuestos_deduccionEstandar: 'Supuestos'!$C$83
Name impuestos_ssTasa: 'Supuestos'!$C$84
Name impuestos_ssTope: 'Supuestos'!$C$85
Name impuestos_medicareTasa: 'Supuestos'!$C$86
Name impuestos_medicareAdicional: 'Supuestos'!$C$87
Name impuestos_medicareUmbral: 'Supuestos'!$C$88
Name impuestos_qbiUmbral: 'Supuestos'!$C$89
Name impuestos_qbiRango: 'Supuestos'!$C$90
Name impuestos_scorpSalarioPct: 'Supuestos'!$C$91
Name impuestos_scorpCostoAnual: 'Supuestos'!$C$92
Name impuestos_nyDeduccion: 'Supuestos'!$C$93
Name impuestos_ohTasa: 'Supuestos'!$C$94
Name impuestos_ohExento: 'Supuestos'!$C$95
Name impuestos_ohMunicipal: 'Supuestos'!$C$96
Name retiro_limite403b: 'Supuestos'!$C$97
Name prestamos_tasaFederalPosgrado: 'Supuestos'!$C$98

Sheet Supuestos
A1: Supuestos del modelo (editar celdas azules)
A2: Fuente única: supuestos.json. Cambiar aquí recalcula todo el libro. Porcentajes como fracción (0.07 = 7%). Booleanos 1/0. | H2: Ubicaciones | J2: Configuraciones | K2: Unid. rentadas | L2: Escenarios
A3: Ubicación (id) | B3: dfw | C3: =MATCH(B3,$H$3:$H$7,0) | H3: miami | I3: Miami / Sur de Florida | J3: duplex | K3: 0 | L3: pesimista
A4: Configuración de vivienda | B4: duplex | C4: =MATCH(B4,$J$3:$J$7,0) | H4: dfw | I4: Dallas–Fort Worth | J4: inlaw | K4: 0 | L4: base
A5: Escenario | B5: base | C5: =MATCH(B5,$L$3:$L$5,0) | H5: houston | I5: Houston | J5: dosCasas | K5: 0 | L5: optimista
H6: nyc | I6: Nueva York (Queens/Bronx) | J6: casaAdu | K6: 0
H7: cleveland | I7: Cleveland / NE de Ohio | J7: multi | K7: 2
A9: Ajustes por escenario
A10: Ajuste | B10: pesimista | C10: base | D10: optimista | E10: Activo
A11: salarios | B11: 0.92 | C11: 1 | D11: 1.06 | E11: =CHOOSE(sel_escIdx,B11,C11,D11)
A12: retorno | B12: -0.02 | C12: 0 | D12: 0.015 | E12: =CHOOSE(sel_escIdx,B12,C12,D12)
A13: inflacion | B13: 0.01 | C13: 0 | D13: -0.005 | E13: =CHOOSE(sel_escIdx,B13,C13,D13)
A14: retraso | B14: 0.5 | C14: 0 | D14: 0 | E14: =CHOOSE(sel_escIdx,B14,C14,D14)
A15: probMatch | B15: -0.15 | C15: 0 | D15: 0.1 | E15: =CHOOSE(sel_escIdx,B15,C15,D15)
A16: apreciacion | B16: -0.02 | C16: 0 | D16: 0.01 | E16: =CHOOSE(sel_escIdx,B16,C16,D16)
A17: tasaHipoteca | B17: 0.01 | C17: 0 | D17: -0.0125 | E17: =CHOOSE(sel_escIdx,B17,C17,D17)
A18: gastos | B18: 1.08 | C18: 1 | D18: 0.96 | E18: =CHOOSE(sel_escIdx,B18,C18,D18)
A19: probExamenes | B19: -0.1 | C19: 0 | D19: 0.08 | E19: =CHOOSE(sel_escIdx,B19,C19,D19)
A21: Parámetros efectivos (escenario aplicado) | E21: Brackets federales 2026 (soltero) [hasta, tasa] | I21: Brackets estado de NY (soltero, aprox. 2026) | M21: Impuesto municipal NYC
A22: Inflación efectiva | B22: g_inf | C22: =general_inflacion+esc_inflacion | E22: Desde | F22: Tasa | G22: Δ tasa | I22: Desde | J22: Tasa | K22: Δ tasa | M22: Desde | N22: Tasa | O22: Δ tasa
A23: Retorno efectivo | B23: g_ret | C23: =general_retornoInversion+esc_retorno | E23: 0 | F23: 0.1 | G23: =F23 | I23: 0 | J23: 0.039 | K23: =J23 | M23: 0 | N23: 0.03078 | O23: =N23
A24: Retorno efectivo HYSA | B24: g_cash | C24: =general_retornoEfectivo | E24: 12400 | F24: 0.12 | G24: =F24-F23 | I24: 8500 | J24: 0.044 | K24: =J24-J23 | M24: 12000 | N24: 0.03762 | O24: =N24-N23
A25: Apreciación efectiva | B25: g_appr | C25: =vivienda_apreciacion+esc_apreciacion | E25: 50400 | F25: 0.22 | G25: =F25-F24 | I25: 11700 | J25: 0.0515 | K25: =J25-J24 | M25: 25000 | N25: 0.03819 | O25: =N25-N24
A26: Tasa hipotecaria efectiva | B26: g_mortRate | C26: =MAX(0.01,vivienda_tasaHipoteca+esc_tasaHipoteca) | E26: 105700 | F26: 0.24 | G26: =F26-F25 | I26: 13900 | J26: 0.054 | K26: =J26-J25 | M26: 50000 | N26: 0.03876 | O26: =N26-N25
A27: Multiplicador salarios | B27: g_salMult | C27: =esc_salarios | E27: 201775 | F27: 0.32 | G27: =F27-F26 | I27: 80650 | J27: 0.059 | K27: =J27-J26
A28: Multiplicador gastos | B28: g_gastos | C28: =esc_gastos | E28: 256225 | F28: 0.35 | G28: =F28-F27 | I28: 215400 | J28: 0.0685 | K28: =J28-J27
E29: 640600 | F29: 0.37 | G29: =F29-F28 | I29: 1077550 | J29: 0.0965 | K29: =J29-J28
A30: Ubicación activa | I30: 5000000 | J30: 0.103 | K30: =J30-J29
A31: factorRN | C31: =CHOOSE(sel_locIdx,ubic_miami_factorRN,ubic_dfw_factorRN,ubic_houston_factorRN,ubic_nyc_factorRN,ubic_cleveland_factorRN) | I31: 25000000 | J31: 0.109 | K31: =J31-J30
A32: factorMD | C32: =CHOOSE(sel_locIdx,ubic_miami_factorMD,ubic_dfw_factorMD,ubic_houston_factorMD,ubic_nyc_factorMD,ubic_cleveland_factorMD)
A33: residentePGY1 | C33: =CHOOSE(sel_locIdx,ubic_miami_residentePGY1,ubic_dfw_residentePGY1,ubic_houston_residentePGY1,ubic_nyc_residentePGY1,ubic_cleveland_residentePGY1)
A34: gastosVida | C34: =CHOOSE(sel_locIdx,ubic_miami_gastosVida,ubic_dfw_gastosVida,ubic_houston_gastosVida,ubic_nyc_gastosVida,ubic_cleveland_gastosVida)
A35: rentaMensual | C35: =CHOOSE(sel_locIdx,ubic_miami_rentaMensual,ubic_dfw_rentaMensual,ubic_houston_rentaMensual,ubic_nyc_rentaMensual,ubic_cleveland_rentaMensual)
A36: seguroPct | C36: =CHOOSE(sel_locIdx,ubic_miami_seguroPct,ubic_dfw_seguroPct,ubic_houston_seguroPct,ubic_nyc_seguroPct,ubic_cleveland_seguroPct)
A37: impuestoPropPct | C37: =CHOOSE(sel_locIdx,ubic_miami_impuestoPropPct,ubic_dfw_impuestoPropPct,ubic_houston_impuestoPropPct,ubic_nyc_impuestoPropPct,ubic_cleveland_impuestoPropPct)
A38: factorMatch | C38: =CHOOSE(sel_locIdx,ubic_miami_factorMatch,ubic_dfw_factorMatch,ubic_houston_factorMatch,ubic_nyc_factorMatch,ubic_cleveland_factorMatch)
A39: rentaUnidad | C39: =CHOOSE(sel_locIdx,ubic_miami_rentaUnidad,ubic_dfw_rentaUnidad,ubic_houston_rentaUnidad,ubic_nyc_rentaUnidad,ubic_cleveland_rentaUnidad)
A40: precio_duplex | C40: =CHOOSE(sel_locIdx,ubic_miami_precio_duplex,ubic_dfw_precio_duplex,ubic_houston_precio_duplex,ubic_nyc_precio_duplex,ubic_cleveland_precio_duplex)
A41: precio_inlaw | C41: =CHOOSE(sel_locIdx,ubic_miami_precio_inlaw,ubic_dfw_precio_inlaw,ubic_houston_precio_inlaw,ubic_nyc_precio_inlaw,ubic_cleveland_precio_inlaw)
A42: precio_dosCasas | C42: =CHOOSE(sel_locIdx,ubic_miami_precio_dosCasas,ubic_dfw_precio_dosCasas,ubic_houston_precio_dosCasas,ubic_nyc_precio_dosCasas,ubic_cleveland_precio_dosCasas)
A43: precio_casaAdu | C43: =CHOOSE(sel_locIdx,ubic_miami_precio_casaAdu,ubic_dfw_precio_casaAdu,ubic_houston_precio_casaAdu,ubic_nyc_precio_casaAdu,ubic_cleveland_precio_casaAdu)
A44: precio_aduCosto | C44: =CHOOSE(sel_locIdx,ubic_miami_precio_aduCosto,ubic_dfw_precio_aduCosto,ubic_houston_precio_aduCosto,ubic_nyc_precio_aduCosto,ubic_cleveland_precio_aduCosto)
A45: precio_multi | C45: =CHOOSE(sel_locIdx,ubic_miami_precio_multi,ubic_dfw_precio_multi,ubic_houston_precio_multi,ubic_nyc_precio_multi,ubic_cleveland_precio_multi)
A46: taxcode | C46: =CHOOSE(sel_locIdx,ubic_miami_taxcode,ubic_dfw_taxcode,ubic_houston_taxcode,ubic_nyc_taxcode,ubic_cleveland_taxcode)
A47: nyc | C47: =CHOOSE(sel_locIdx,ubic_miami_nyc,ubic_dfw_nyc,ubic_houston_nyc,ubic_nyc_nyc,ubic_cleveland_nyc)
A52: Todas las variables
A53: Ruta | B53: Descripción | C53: Valor | D53: Unidad | E53: Fuente | F53: URL | G53: Confianza | H53: Estimado | I53: Nota
A54: general.anioInicio | B54: Primer año simulado | C54: 2027 | D54: año | E54: Parámetro de diseño del modelo | G54: alta | I54: La simulación es anual de 2027 a 2046 (20 años). Saldo inicial = situación a oct-2026.
A55: general.horizonte | B55: Horizonte | C55: 20 | D55: años | E55: Parámetro de diseño del modelo | G55: alta
A56: general.edad | B56: Edad actual | C56: 30 | D56: años | E56: Dato proporcionado por ti (README del repositorio) | G56: alta
A57: general.inflacion | B57: Inflación anual (gastos, brackets) | C57: 0.03 | D57: % | E57: Estimación propia del modelo (sin dato publicado directo); ver nota | G57: media | H57: sí | I57: Supuesto de largo plazo; la Fed apunta a 2%, se usa 3% por prudencia.
A58: general.retornoInversion | B58: Retorno nominal de inversiones (403b/Roth/brokerage) | C58: 0.07 | D58: % | E58: Estimación propia del modelo (sin dato publicado directo); ver nota | G58: media | H58: sí | I58: Cartera mayormente en acciones; histórico S&P 500 ~10% nominal, se usa 7% conservador.
A59: general.retornoEfectivo | B59: Retorno de efectivo/HYSA (ahorro para enganche) | C59: 0.035 | D59: % | E59: Estimación propia del modelo (sin dato publicado directo); ver nota | G59: media | H59: sí
A60: general.tasaAhorro | B60: Tasa de ahorro del excedente (resto = gasto discrecional) | C60: 0.75 | D60: % | E60: Estimación propia del modelo (sin dato publicado directo); ver nota | G60: media | H60: sí | I60: De lo que sobra tras gastos básicos, vivienda, deudas y estudios, este % se ahorra/invierte.
A61: general.reservaMeses | B61: Fondo de emergencia exigido antes de comprar vivienda | C61: 3 | D61: meses | E61: Estimación propia del modelo (sin dato publicado directo); ver nota | G61: media | H61: sí
A62: general.tasaDeudaConsumo | B62: Tasa de deuda de consumo si hay déficit fuera de estudios | C62: 0.12 | D62: % | E62: Estimación propia del modelo (sin dato publicado directo); ver nota | G62: media | H62: sí
A63: personal.tarifaHora | B63: Tarifa actual Mount Sinai | C63: 40 | D63: $/h | E63: Dato proporcionado por ti (README del repositorio) | G63: alta | I63: Dato del usuario.
A64: personal.horasSemana | B64: Horas/semana actuales (~4 días) | C64: 32 | D64: h | E64: Dato proporcionado por ti (README del repositorio) | G64: alta | I64: Ingreso actual ≈ 40 × 32 × 52 = $66,560/año.
A65: personal.liquidoInicial | B65: Ahorro líquido inicial (HYSA + brokerage) | C65: 8000 | D65: $ | E65: Estimación propia del modelo (sin dato publicado directo); ver nota | G65: media | H65: sí | I65: Total declarado ~$13,000; el reparto líquido/retiro es estimado.
A66: personal.retiroInicial | B66: Retiro inicial (Roth IRA + 403b) | C66: 5000 | D66: $ | E66: Estimación propia del modelo (sin dato publicado directo); ver nota | G66: media | H66: sí
A67: personal.irsSaldo | B67: Plan de pagos IRS restante | C67: 1350 | D67: $ | E67: Dato proporcionado por ti (README del repositorio) | G67: alta
A68: personal.irsPagoMensual | B68: Pago mensual IRS | C68: 150 | D68: $ | E68: Estimación propia del modelo (sin dato publicado directo); ver nota | G68: media | H68: sí
A69: personal.deudaEstudiantil | B69: Deuda estudiantil actual | C69: 10000 | D69: $ | E69: Dato proporcionado por ti (README del repositorio) | G69: alta
A70: personal.tasaDeudaEstudiantil | B70: Tasa deuda estudiantil actual | C70: 0.06 | D70: % | E70: Dato proporcionado por ti (README del repositorio) | G70: media
A71: personal.deudaEsFederal | B71: La deuda actual es federal (elegible PSLF/RAP) | C71: 1 | D71: bool | E71: Estimación propia del modelo (sin dato publicado directo); ver nota | G71: baja | H71: sí
A72: personal.aporte403bPct | B72: Aporte propio al 403b/401k (% del salario W-2) | C72: 0.06 | D72: % | E72: Estimación propia del modelo (sin dato publicado directo); ver nota | G72: media | H72: sí
A73: personal.match403bPct | B73: Match del empleador (desde ene-2027) | C73: 0.04 | D73: % | E73: Dato proporcionado por ti (README del repositorio) | G73: alta | I73: Dato del usuario para Mount Sinai; se aplica a empleos hospitalarios con match.
A74: personal.rothAnual | B74: Aporte anual a Roth IRA (si hay excedente) | C74: 3000 | D74: $ | E74: Límites 2026 (SS wage base, 403b, IRA) – Mayer Brown | F74: https://www.mayerbrown.com/es/insights/publications/2025/12/irs-annual-limits-for-benefit-plans-2026-cost-of-living-adjustments | G74: media | I74: Límite IRA 2026 = $7,500. Con ingresos altos se asume backdoor Roth.
A75: personal.bsnFin | B75: Graduación RN-BSN (South University) | C75: 2027.5 | D75: año | E75: Dato proporcionado por ti (README del repositorio) | G75: media | I75: Default: mediados de 2027.
A76: personal.bsnCostoRestante | B76: Matrícula restante del RN-BSN | C76: 6000 | D76: $ | E76: Estimación propia del modelo (sin dato publicado directo); ver nota | G76: baja | H76: sí
A77: personal.bsnAumento | B77: Aumento salarial por BSN (case mgmt) | C77: 0.04 | D77: % | E77: Estimación propia del modelo (sin dato publicado directo); ver nota | G77: baja | H77: sí
A78: personal.llcActivo | B78: Overlay: ingreso lateral Angelmar Group LLC | C78: 0 | D78: bool | E78: Dato proporcionado por ti (README del repositorio) | G78: media
A79: personal.llcNeto | B79: Ganancia neta anual Angelmar LLC | C79: 12000 | D79: $ | E79: Estimación propia del modelo (sin dato publicado directo); ver nota | G79: baja | H79: sí | I79: Sujeta a impuesto de autoempleo (15.3%) e impuesto sobre la renta.
A80: personal.llcCrecimiento | B80: Crecimiento anual LLC | C80: 0.05 | D80: % | E80: Estimación propia del modelo (sin dato publicado directo); ver nota | G80: baja | H80: sí
A81: personal.aporteFamiliaMensual | B81: Aporte mensual de mamá/tía a la vivienda | C81: 0 | D81: $ | E81: Estimación propia del modelo (sin dato publicado directo); ver nota | G81: baja | H81: sí | I81: Si ellas aportan (p. ej. lo que hoy pagan de renta), acelera el pago.
A82: personal.costoMudanzaInicial | B82: Mudanza inicial si la ubicación no es Miami | C82: 5000 | D82: $ | E82: Estimación propia del modelo (sin dato publicado directo); ver nota | G82: media | H82: sí
A83: impuestos.deduccionEstandar | B83: Deducción estándar 2026 (soltero) | C83: 16100 | D83: $ | E83: IRS Rev. Proc. 2025-32 (brackets y deducción estándar 2026) vía Accounting Today | F83: https://www.accountingtoday.com/news/irs-announces-inflation-adjustments-for-2026 | G83: alta
A84: impuestos.ssTasa | B84: Seguro Social (empleado) | C84: 0.062 | D84: % | E84: Límites 2026 (SS wage base, 403b, IRA) – Mayer Brown | F84: https://www.mayerbrown.com/es/insights/publications/2025/12/irs-annual-limits-for-benefit-plans-2026-cost-of-living-adjustments | G84: alta
A85: impuestos.ssTope | B85: Tope salarial Seguro Social 2026 | C85: 184500 | D85: $ | E85: Límites 2026 (SS wage base, 403b, IRA) – Mayer Brown | F85: https://www.mayerbrown.com/es/insights/publications/2025/12/irs-annual-limits-for-benefit-plans-2026-cost-of-living-adjustments | G85: alta
A86: impuestos.medicareTasa | B86: Medicare (empleado) | C86: 0.0145 | D86: % | E86: Límites 2026 (SS wage base, 403b, IRA) – Mayer Brown | F86: https://www.mayerbrown.com/es/insights/publications/2025/12/irs-annual-limits-for-benefit-plans-2026-cost-of-living-adjustments | G86: alta
A87: impuestos.medicareAdicional | B87: Medicare adicional (> $200k) | C87: 0.009 | D87: % | E87: Límites 2026 (SS wage base, 403b, IRA) – Mayer Brown | F87: https://www.mayerbrown.com/es/insights/publications/2025/12/irs-annual-limits-for-benefit-plans-2026-cost-of-living-adjustments | G87: alta
A88: impuestos.medicareUmbral | B88: Umbral Medicare adicional (no indexado) | C88: 200000 | D88: $ | E88: Límites 2026 (SS wage base, 403b, IRA) – Mayer Brown | F88: https://www.mayerbrown.com/es/insights/publications/2025/12/irs-annual-limits-for-benefit-plans-2026-cost-of-living-adjustments | G88: alta
A89: impuestos.qbiUmbral | B89: Umbral QBI (SSTB) soltero 2026 | C89: 201750 | D89: $ | E89: Estimación propia del modelo (sin dato publicado directo); ver nota | G89: media | H89: sí | I89: Médicos/enfermeros son 'SSTB': la deducción 20% QBI se elimina por encima del umbral + rango.
A90: impuestos.qbiRango | B90: Rango de eliminación QBI (OBBBA) | C90: 75000 | D90: $ | E90: Estimación propia del modelo (sin dato publicado directo); ver nota | G90: media | H90: sí
A91: impuestos.scorpSalarioPct | B91: S-corp locums: % pagado como salario razonable | C91: 0.5 | D91: % | E91: Estimación propia del modelo (sin dato publicado directo); ver nota | G91: media | H91: sí | I91: El resto es distribución sin FICA. El IRS exige salario 'razonable'.
A92: impuestos.scorpCostoAnual | B92: Costo anual S-corp (contador, nómina, franchise) | C92: 3000 | D92: $ | E92: Estimación propia del modelo (sin dato publicado directo); ver nota | G92: media | H92: sí
A93: impuestos.nyDeduccion | B93: Deducción estándar NY | C93: 8000 | D93: $ | E93: NY State/NYC tasas (aprox. 2026, verificar en tax.ny.gov) | F93: https://www.countrytaxcalc.com/tax-guides/compare/new-york-vs-ohio/ | G93: media
A94: impuestos.ohTasa | B94: Ohio tasa plana 2026 | C94: 0.0275 | D94: % | E94: EY Tax News – Ohio tasa plana 2.75% desde 2026 | F94: https://taxnews.ey.com/news/2025-1744 | G94: alta
A95: impuestos.ohExento | B95: Ohio: ingreso exento | C95: 26050 | D95: $ | E95: EY Tax News – Ohio tasa plana 2.75% desde 2026 | F95: https://taxnews.ey.com/news/2025-1744 | G95: alta
A96: impuestos.ohMunicipal | B96: Impuesto municipal Cleveland (sobre salarios) | C96: 0.025 | D96: % | E96: EY Tax News – Ohio tasa plana 2.75% desde 2026 | F96: https://taxnews.ey.com/news/2025-1744 | G96: media
A97: retiro.limite403b | B97: Límite aporte 403b/401k 2026 | C97: 24500 | D97: $ | E97: Límites 2026 (SS wage base, 403b, IRA) – Mayer Brown | F97: https://www.mayerbrown.com/es/insights/publications/2025/12/irs-annual-limits-for-benefit-plans-2026-cost-of-living-adjustments | G97: alta
A98: prestamos.tasaFederalPosgrado | B98: Tasa federal posgrado 2026-27 | C98: 0.0807 | D98: % | E98: ED – tasa Direct Unsubsidized posgrado 2026-27: 8.07% | F98: https://fsapartners.ed.gov/knowledge-center/library/electronic-announcements/2026-06-04/interest-rates-federal-direct-loans-first-disbursed-between-july-1-2026-and-june-30-2027 | G98: alta
A99: prestamos.tasaPrivada | B99: Tasa préstamo privado (excedente sobre tope federal) | C99: 0.095 | D99: % | E99: Estimación propia del modelo (sin dato publicado directo); ver nota | G99: media | H99: sí
A100: prestamos.topeAnualPosgrado | B100: Tope federal anual – posgrado (NP/CRNA) | C100: 20500 | D100: $ | E100: Límites préstamos desde 1-jul-2026: posgrado $20,500/año ($100k total); profesional $50k/año ($200k) | F100: https://www.uvu.edu/financialaid/aid/graduate_professional_loan_changes_2026.html | G100: alta | I100: Grad PLUS eliminado para nuevos estudiantes desde 1-jul-2026. No está claro si el DNP-CRNA se clasificará como 'profesional' ($50k/año).
A101: prestamos.topeTotalPosgrado | B101: Tope federal acumulado – posgrado | C101: 100000 | D101: $ | E101: Límites préstamos desde 1-jul-2026: posgrado $20,500/año ($100k total); profesional $50k/año ($200k) | F101: https://www.uvu.edu/financialaid/aid/graduate_professional_loan_changes_2026.html | G101: alta
A102: prestamos.plazoAnios | B102: Plazo de repago estándar | C102: 10 | D102: años | E102: Estimación propia del modelo (sin dato publicado directo); ver nota | G102: media
A103: prestamos.pslfActivo | B103: Usar PSLF cuando el empleo es sin fines de lucro | C103: 1 | D103: bool | E103: Cambios PSLF/RAP 2026 (OBBBA): RAP califica para PSLF, 1–10% del AGI | F103: https://www.tateesq.com/learn/pslf-changes-2026 | G103: media
A104: prestamos.pslfPagos | B104: Pagos calificados requeridos para PSLF | C104: 120 | D104: meses | E104: Cambios PSLF/RAP 2026 (OBBBA): RAP califica para PSLF, 1–10% del AGI | F104: https://www.tateesq.com/learn/pslf-changes-2026 | G104: alta
A105: prestamos.rapPagoMinimoAnual | B105: Pago mínimo RAP ($10/mes) | C105: 120 | D105: $ | E105: Cambios PSLF/RAP 2026 (OBBBA): RAP califica para PSLF, 1–10% del AGI | F105: https://www.tateesq.com/learn/pslf-changes-2026 | G105: alta
A106: vivienda.configuracion | B106: Configuración de vivienda | C106: duplex | D106: opcion | E106: Parámetro de diseño del modelo | G106: alta
...

Sheet Comparativa
A1: Comparativa de caminos (ubicación, vivienda y escenario según la hoja Supuestos)
A2: =CONCATENATE("Ubicación: ",sel_loc," · Vivienda: ",sel_cfg," · Escenario: ",Supuestos!B5)
A4: Año | B4: A1 · Case mgmt → UR payer-side (remoto) | C4: A2 · Bedside ICU (residencia RN experimentado) | D4: A3 · ICU → Travel nurse | E4: A4 · CDI / informática (valora tu MD) | F4: A5 · ICU → charge → nurse manager | G4: A5b · ICU → educador clínico | H4: A6 · Nurse injector / estética | I4: A7 · ICU → CRNA | J4: A7b · ICU → Travel → CRNA | K4: A8 · NP familiar (FNP) | L4: A8b · NP psiquiátrico (PMHNP) | M4: B1 · MD: match al primer intento | N4: B2 · MD: SOAP preliminar → categórico | O4: B3 · MD: no match → match al reintento | P4: B4 · MD: nunca hace match → vuelve a CDI
A5: 2027 | B5: ='A1 cm_ur'!EG33 | C5: ='A2 icu'!EG33 | D5: ='A3 icu_travel'!EG33 | E5: ='A4 cdi'!EG33 | F5: ='A5 manager'!EG33 | G5: ='A5b educador'!EG33 | H5: ='A6 injector'!EG33 | I5: ='A7 crna'!EG33 | J5: ='A7b icu_travel_crna'!EG33 | K5: ='A8 fnp'!EG33 | L5: ='A8b pmhnp'!EG33 | M5: ='B1 md_match1'!EG33 | N5: ='B2 md_soap_prelim'!EG33 | O5: ='B3 md_reintento'!EG33 | P5: ='B4 md_fallo'!EG33
A6: 2028 | B6: ='A1 cm_ur'!EG34 | C6: ='A2 icu'!EG34 | D6: ='A3 icu_travel'!EG34 | E6: ='A4 cdi'!EG34 | F6: ='A5 manager'!EG34 | G6: ='A5b educador'!EG34 | H6: ='A6 injector'!EG34 | I6: ='A7 crna'!EG34 | J6: ='A7b icu_travel_crna'!EG34 | K6: ='A8 fnp'!EG34 | L6: ='A8b pmhnp'!EG34 | M6: ='B1 md_match1'!EG34 | N6: ='B2 md_soap_prelim'!EG34 | O6: ='B3 md_reintento'!EG34 | P6: ='B4 md_fallo'!EG34
A7: 2029 | B7: ='A1 cm_ur'!EG35 | C7: ='A2 icu'!EG35 | D7: ='A3 icu_travel'!EG35 | E7: ='A4 cdi'!EG35 | F7: ='A5 manager'!EG35 | G7: ='A5b educador'!EG35 | H7: ='A6 injector'!EG35 | I7: ='A7 crna'!EG35 | J7: ='A7b icu_travel_crna'!EG35 | K7: ='A8 fnp'!EG35 | L7: ='A8b pmhnp'!EG35 | M7: ='B1 md_match1'!EG35 | N7: ='B2 md_soap_prelim'!EG35 | O7: ='B3 md_reintento'!EG35 | P7: ='B4 md_fallo'!EG35
A8: 2030 | B8: ='A1 cm_ur'!EG36 | C8: ='A2 icu'!EG36 | D8: ='A3 icu_travel'!EG36 | E8: ='A4 cdi'!EG36 | F8: ='A5 manager'!EG36 | G8: ='A5b educador'!EG36 | H8: ='A6 injector'!EG36 | I8: ='A7 crna'!EG36 | J8: ='A7b icu_travel_crna'!EG36 | K8: ='A8 fnp'!EG36 | L8: ='A8b pmhnp'!EG36 | M8: ='B1 md_match1'!EG36 | N8: ='B2 md_soap_prelim'!EG36 | O8: ='B3 md_reintento'!EG36 | P8: ='B4 md_fallo'!EG36
A9: 2031 | B9: ='A1 cm_ur'!EG37 | C9: ='A2 icu'!EG37 | D9: ='A3 icu_travel'!EG37 | E9: ='A4 cdi'!EG37 | F9: ='A5 manager'!EG37 | G9: ='A5b educador'!EG37 | H9: ='A6 injector'!EG37 | I9: ='A7 crna'!EG37 | J9: ='A7b icu_travel_crna'!EG37 | K9: ='A8 fnp'!EG37 | L9: ='A8b pmhnp'!EG37 | M9: ='B1 md_match1'!EG37 | N9: ='B2 md_soap_prelim'!EG37 | O9: ='B3 md_reintento'!EG37 | P9: ='B4 md_fallo'!EG37
A10: 2032 | B10: ='A1 cm_ur'!EG38 | C10: ='A2 icu'!EG38 | D10: ='A3 icu_travel'!EG38 | E10: ='A4 cdi'!EG38 | F10: ='A5 manager'!EG38 | G10: ='A5b educador'!EG38 | H10: ='A6 injector'!EG38 | I10: ='A7 crna'!EG38 | J10: ='A7b icu_travel_crna'!EG38 | K10: ='A8 fnp'!EG38 | L10: ='A8b pmhnp'!EG38 | M10: ='B1 md_match1'!EG38 | N10: ='B2 md_soap_prelim'!EG38 | O10: ='B3 md_reintento'!EG38 | P10: ='B4 md_fallo'!EG38
A11: 2033 | B11: ='A1 cm_ur'!EG39 | C11: ='A2 icu'!EG39 | D11: ='A3 icu_travel'!EG39 | E11: ='A4 cdi'!EG39 | F11: ='A5 manager'!EG39 | G11: ='A5b educador'!EG39 | H11: ='A6 injector'!EG39 | I11: ='A7 crna'!EG39 | J11: ='A7b icu_travel_crna'!EG39 | K11: ='A8 fnp'!EG39 | L11: ='A8b pmhnp'!EG39 | M11: ='B1 md_match1'!EG39 | N11: ='B2 md_soap_prelim'!EG39 | O11: ='B3 md_reintento'!EG39 | P11: ='B4 md_fallo'!EG39
A12: 2034 | B12: ='A1 cm_ur'!EG40 | C12: ='A2 icu'!EG40 | D12: ='A3 icu_travel'!EG40 | E12: ='A4 cdi'!EG40 | F12: ='A5 manager'!EG40 | G12: ='A5b educador'!EG40 | H12: ='A6 injector'!EG40 | I12: ='A7 crna'!EG40 | J12: ='A7b icu_travel_crna'!EG40 | K12: ='A8 fnp'!EG40 | L12: ='A8b pmhnp'!EG40 | M12: ='B1 md_match1'!EG40 | N12: ='B2 md_soap_prelim'!EG40 | O12: ='B3 md_reintento'!EG40 | P12: ='B4 md_fallo'!EG40
A13: 2035 | B13: ='A1 cm_ur'!EG41 | C13: ='A2 icu'!EG41 | D13: ='A3 icu_travel'!EG41 | E13: ='A4 cdi'!EG41 | F13: ='A5 manager'!EG41 | G13: ='A5b educador'!EG41 | H13: ='A6 injector'!EG41 | I13: ='A7 crna'!EG41 | J13: ='A7b icu_travel_crna'!EG41 | K13: ='A8 fnp'!EG41 | L13: ='A8b pmhnp'!EG41 | M13: ='B1 md_match1'!EG41 | N13: ='B2 md_soap_prelim'!EG41 | O13: ='B3 md_reintento'!EG41 | P13: ='B4 md_fallo'!EG41
A14: 2036 | B14: ='A1 cm_ur'!EG42 | C14: ='A2 icu'!EG42 | D14: ='A3 icu_travel'!EG42 | E14: ='A4 cdi'!EG42 | F14: ='A5 manager'!EG42 | G14: ='A5b educador'!EG42 | H14: ='A6 injector'!EG42 | I14: ='A7 crna'!EG42 | J14: ='A7b icu_travel_crna'!EG42 | K14: ='A8 fnp'!EG42 | L14: ='A8b pmhnp'!EG42 | M14: ='B1 md_match1'!EG42 | N14: ='B2 md_soap_prelim'!EG42 | O14: ='B3 md_reintento'!EG42 | P14: ='B4 md_fallo'!EG42
A15: 2037 | B15: ='A1 cm_ur'!EG43 | C15: ='A2 icu'!EG43 | D15: ='A3 icu_travel'!EG43 | E15: ='A4 cdi'!EG43 | F15: ='A5 manager'!EG43 | G15: ='A5b educador'!EG43 | H15: ='A6 injector'!EG43 | I15: ='A7 crna'!EG43 | J15: ='A7b icu_travel_crna'!EG43 | K15: ='A8 fnp'!EG43 | L15: ='A8b pmhnp'!EG43 | M15: ='B1 md_match1'!EG43 | N15: ='B2 md_soap_prelim'!EG43 | O15: ='B3 md_reintento'!EG43 | P15: ='B4 md_fallo'!EG43
A16: 2038 | B16: ='A1 cm_ur'!EG44 | C16: ='A2 icu'!EG44 | D16: ='A3 icu_travel'!EG44 | E16: ='A4 cdi'!EG44 | F16: ='A5 manager'!EG44 | G16: ='A5b educador'!EG44 | H16: ='A6 injector'!EG44 | I16: ='A7 crna'!EG44 | J16: ='A7b icu_travel_crna'!EG44 | K16: ='A8 fnp'!EG44 | L16: ='A8b pmhnp'!EG44 | M16: ='B1 md_match1'!EG44 | N16: ='B2 md_soap_prelim'!EG44 | O16: ='B3 md_reintento'!EG44 | P16: ='B4 md_fallo'!EG44
... A24: 2046 | B24: ='A1 cm_ur'!EG52 | C24: ='A2 icu'!EG52 | D24: ='A3 icu_travel'!EG52 | E24: ='A4 cdi'!EG52 | F24: ='A5 manager'!EG52 | G24: ='A5b educador'!EG52 | H24: ='A6 injector'!EG52 | I24: ='A7 crna'!EG52 | J24: ='A7b icu_travel_crna'!EG52 | K24: ='A8 fnp'!EG52 | L24: ='A8b pmhnp'!EG52 | M24: ='B1 md_match1'!EG52 | N24: ='B2 md_soap_prelim'!EG52 | O24: ='B3 md_reintento'!EG52 | P24: ='B4 md_fallo'!EG52
A26: Patrimonio año 10 | B26: =B14 | C26: =C14 | D26: =D14 | E26: =E14 | F26: =F14 | G26: =G14 | H26: =H14 | I26: =I14 | ... P26: =P14
A27: Patrimonio año 20 | B27: =B24 | C27: =C24 | D27: =D24 | E27: =E24 | F27: =F24 | G27: =G24 | H27: =H24 | I27: =I24 | ... P27: =P24
A28: Año compra vivienda | B28: =IF('A1 cm_ur'!BC52="","no viable",'A1 cm_ur'!BC52) | C28: =IF('A2 icu'!BC52="","no viable",'A2 icu'!BC52) | D28: =IF('A3 icu_travel'!BC52="","no viable",'A3 icu_travel'!BC52) | E28: =IF('A4 cdi'!BC52="","no viable",'A4 cdi'!BC52) | F28: =IF('A5 manager'!BC52="","no viable",'A5 manager'!BC52) | G28: =IF('A5b educador'!BC52="","no viable",'A5b educador'!BC52) | H28: =IF('A6 injector'!BC52="","no viable",'A6 injector'!BC52) | I28: =IF('A7 crna'!BC52="","no viable",'A7 crna'!BC52) | J28: =IF('A7b icu_travel_crna'!BC52="","no viable",'A7b icu_travel_crna'!BC52) | K28: =IF('A8 fnp'!BC52="","no viable",'A8 fnp'!BC52) | L28: =IF('A8b pmhnp'!BC52="","no viable",'A8b pmhnp'!BC52) | M28: =IF('B1 md_match1'!BC52="","no viable",'B1 md_match1'!BC52) | N28: =IF('B2 md_soap_prelim'!BC52="","no viable",'B2 md_soap_prelim'!BC52) | O28: =IF('B3 md_reintento'!BC52="","no viable",'B3 md_reintento'!BC52) | P28: =IF('B4 md_fallo'!BC52="","no viable",'B4 md_fallo'!BC52)
A29: Año vivienda pagada | B29: =IF('A1 cm_ur'!EE52="","—",'A1 cm_ur'!EE52) | C29: =IF('A2 icu'!EE52="","—",'A2 icu'!EE52) | D29: =IF('A3 icu_travel'!EE52="","—",'A3 icu_travel'!EE52) | E29: =IF('A4 cdi'!EE52="","—",'A4 cdi'!EE52) | F29: =IF('A5 manager'!EE52="","—",'A5 manager'!EE52) | G29: =IF('A5b educador'!EE52="","—",'A5b educador'!EE52) | H29: =IF('A6 injector'!EE52="","—",'A6 injector'!EE52) | I29: =IF('A7 crna'!EE52="","—",'A7 crna'!EE52) | J29: =IF('A7b icu_travel_crna'!EE52="","—",'A7b icu_travel_crna'!EE52) | K29: =IF('A8 fnp'!EE52="","—",'A8 fnp'!EE52) | L29: =IF('A8b pmhnp'!EE52="","—",'A8b pmhnp'!EE52) | M29: =IF('B1 md_match1'!EE52="","—",'B1 md_match1'!EE52) | N29: =IF('B2 md_soap_prelim'!EE52="","—",'B2 md_soap_prelim'!EE52) | O29: =IF('B3 md_reintento'!EE52="","—",'B3 md_reintento'!EE52) | P29: =IF('B4 md_fallo'!EE52="","—",'B4 md_fallo'!EE52)
A30: Deuda máxima | B30: =MAX('A1 cm_ur'!EF33:EF52) | C30: =MAX('A2 icu'!EF33:EF52) | D30: =MAX('A3 icu_travel'!EF33:EF52) | E30: =MAX('A4 cdi'!EF33:EF52) | F30: =MAX('A5 manager'!EF33:EF52) | G30: =MAX('A5b educador'!EF33:EF52) | H30: =MAX('A6 injector'!EF33:EF52) | I30: =MAX('A7 crna'!EF33:EF52) | J30: =MAX('A7b icu_travel_crna'!EF33:EF52) | K30: =MAX('A8 fnp'!EF33:EF52) | L30: =MAX('A8b pmhnp'!EF33:EF52) | M30: =MAX('B1 md_match1'!EF33:EF52) | N30: =MAX('B2 md_soap_prelim'!EF33:EF52) | O30: =MAX('B3 md_reintento'!EF33:EF52) | P30: =MAX('B4 md_fallo'!EF33:EF52)
A31: Ranking (año 20) | B31: =RANK(B24,$B$24:$P$24) | C31: =RANK(C24,$B$24:$P$24) | D31: =RANK(D24,$B$24:$P$24) | E31: =RANK(E24,$B$24:$P$24) | F31: =RANK(F24,$B$24:$P$24) | G31: =RANK(G24,$B$24:$P$24) | H31: =RANK(H24,$B$24:$P$24) | I31: =RANK(I24,$B$24:$P$24) | ... P31: =RANK(P24,$B$24:$P$24)
A34: Cruces: año desde el cual el camino de la FILA supera permanentemente al de la COLUMNA
A35: Camino | B35: A1 | C35: A2 | D35: A3 | E35: A4 | F35: A5 | G35: A5b | H35: A6 | I35: A7 | J35: A7b | K35: A8 | L35: A8b | M35: B1 | N35: B2 | O35: B3 | P35: B4
A36: A1 · Case mgmt → UR payer-side (remoto) | B36: — | C36: =IF(SUMPRODUCT(--(B$5:B$24<=C$5:C$24))=0,"siempre",IF(LOOKUP(2,1/(B$5:B$24<=C$5:C$24),$A$5:$A$24)>=2046,"nunca",LOOKUP(2,1/(B$5:B$24<=C$5:C$24),$A$5:$A$24)+1)) | D36: =IF(SUMPRODUCT(--(B$5:B$24<=D$5:D$24))=0,"siempre",IF(LOOKUP(2,1/(B$5:B$24<=D$5:D$24),$A$5:$A$24)>=2046,"nunca",LOOKUP(2,1/(B$5:B$24<=D$5:D$24),$A$5:$A$24)+1)) | E36: =IF(SUMPRODUCT(--(B$5:B$24<=E$5:E$24))=0,"siempre",IF(LOOKUP(2,1/(B$5:B$24<=E$5:E$24),$A$5:$A$24)>=2046,"nunca",LOOKUP(2,1/(B$5:B$24<=E$5:E$24),$A$5:$A$24)+1)) | F36: =IF(SUMPRODUCT(--(B$5:B$24<=F$5:F$24))=0,"siempre",IF(LOOKUP(2,1/(B$5:B$24<=F$5:F$24),$A$5:$A$24)>=2046,"nunca",LOOKUP(2,1/(B$5:B$24<=F$5:F$24),$A$5:$A$24)+1)) | G36: =IF(SUMPRODUCT(--(B$5:B$24<=G$5:G$24))=0,"siempre",IF(LOOKUP(2,1/(B$5:B$24<=G$5:G$24),$A$5:$A$24)>=2046,"nunca",LOOKUP(2,1/(B$5:B$24<=G$5:G$24),$A$5:$A$24)+1)) | H36: =IF(SUMPRODUCT(--(B$5:B$24<=H$5:H$24))=0,"siempre",IF(LOOKUP(2,1/(B$5:B$24<=H$5:H$24),$A$5:$A$24)>=2046,"nunca",LOOKUP(2,1/(B$5:B$24<=H$5:H$24),$A$5:$A$24)+1)) | I36: =IF(SUMPRODUCT(--(B$5:B$24<=I$5:I$24))=0,"siempre",IF(LOOKUP(2,1/(B$5:B$24<=I$5:I$24),$A$5:$A$24)>=2046,"nunca",LOOKUP(2,1/(B$5:B$24<=I$5:I$24),$A$5:$A$24)+1)) | J36: =IF(SUMPRODUCT(--(B$5:B$24<=J$5:J$24))=0,"siempre",IF(LOOKUP(2,1/(B$5:B$24<=J$5:J$24),$A$5:$A$24)>=2046,"nunca",LOOKUP(2,1/(B$5:B$24<=J$5:J$24),$A$5:$A$24)+1)) | K36: =IF(SUMPRODUCT(--(B$5:B$24<=K$5:K$24))=0,"siempre",IF(LOOKUP(2,1/(B$5:B$24<=K$5:K$24),$A$5:$A$24)>=2046,"nunca",LOOKUP(2,1/(B$5:B$24<=K$5:K$24),$A$5:$A$24)+1)) | L36: =IF(SUMPRODUCT(--(B$5:B$24<=L$5:L$24))=0,"siempre",IF(LOOKUP(2,1/(B$5:B$24<=L$5:L$24),$A$5:$A$24)>=2046,"nunca",LOOKUP(2,1/(B$5:B$24<=L$5:L$24),$A$5:$A$24)+1)) | M36: =IF(SUMPRODUCT(--(B$5:B$24<=M$5:M$24))=0,"siempre",IF(LOOKUP(2,1/(B$5:B$24<=M$5:M$24),$A$5:$A$24)>=2046,"nunca",LOOKUP(2,1/(B$5:B$24<=M$5:M$24),$A$5:$A$24)+1)) | N36: =IF(SUMPRODUCT(--(B$5:B$24<=N$5:N$24))=0,"siempre",IF(LOOKUP(2,1/(B$5:B$24<=N$5:N$24),$A$5:$A$24)>=2046,"nunca",LOOKUP(2,1/(B$5:B$24<=N$5:N$24),$A$5:$A$24)+1)) | O36: =IF(SUMPRODUCT(--(B$5:B$24<=O$5:O$24))=0,"siempre",IF(LOOKUP(2,1/(B$5:B$24<=O$5:O$24),$A$5:$A$24)>=2046,"nunca",LOOKUP(2,1/(B$5:B$24<=O$5:O$24),$A$5:$A$24)+1)) | P36: =IF(SUMPRODUCT(--(B$5:B$24<=P$5:P$24))=0,"siempre",IF(LOOKUP(2,1/(B$5:B$24<=P$5:P$24),$A$5:$A$24)>=2046,"nunca",LOOKUP(2,1/(B$5:B$24<=P$5:P$24),$A$5:$A$24)+1))
A37: A2 · Bedside ICU (residencia RN experimentado) | B37: =IF(SUMPRODUCT(--(C$5:C$24<=B$5:B$24))=0,"siempre",IF(LOOKUP(2,1/(C$5:C$24<=B$5:B$24),$A$5:$A$24)>=2046,"nunca",LOOKUP(2,1/(C$5:C$24<=B$5:B$24),$A$5:$A$24)+1)) | C37: — | D37: =IF(SUMPRODUCT(--(C$5:C$24<=D$5:D$24))=0,"siempre",IF(LOOKUP(2,1/(C$5:C$24<=D$5:D$24),$A$5:$A$24)>=2046,"nunca",LOOKUP(2,1/(C$5:C$24<=D$5:D$24),$A$5:$A$24)+1)) | E37: =IF(SUMPRODUCT(--(C$5:C$24<=E$5:E$24))=0,"siempre",IF(LOOKUP(2,1/(C$5:C$24<=E$5:E$24),$A$5:$A$24)>=2046,"nunca",LOOKUP(2,1/(C$5:C$24<=E$5:E$24),$A$5:$A$24)+1)) | F37: =IF(SUMPRODUCT(--(C$5:C$24<=F$5:F$24))=0,"siempre",IF(LOOKUP(2,1/(C$5:C$24<=F$5:F$24),$A$5:$A$24)>=2046,"nunca",LOOKUP(2,1/(C$5:C$24<=F$5:F$24),$A$5:$A$24)+1)) | G37: =IF(SUMPRODUCT(--(C$5:C$24<=G$5:G$24))=0,"siempre",IF(LOOKUP(2,1/(C$5:C$24<=G$5:G$24),$A$5:$A$24)>=2046,"nunca",LOOKUP(2,1/(C$5:C$24<=G$5:G$24),$A$5:$A$24)+1)) | H37: =IF(SUMPRODUCT(--(C$5:C$24<=H$5:H$24))=0,"siempre",IF(LOOKUP(2,1/(C$5:C$24<=H$5:H$24),$A$5:$A$24)>=2046,"nunca",LOOKUP(2,1/(C$5:C$24<=H$5:H$24),$A$5:$A$24)+1)) | I37: =IF(SUMPRODUCT(--(C$5:C$24<=I$5:I$24))=0,"siempre",IF(LOOKUP(2,1/(C$5:C$24<=I$5:I$24),$A$5:$A$24)>=2046,"nunca",LOOKUP(2,1/(C$5:C$24<=I$5:I$24),$A$5:$A$24)+1)) | J37: =IF(SUMPRODUCT(--(C$5:C$24<=J$5:J$24))=0,"siempre",IF(LOOKUP(2,1/(C$5:C$24<=J$5:J$24),$A$5:$A$24)>=2046,"nunca",LOOKUP(2,1/(C$5:C$24<=J$5:J$24),$A$5:$A$24)+1)) | K37: =IF(SUMPRODUCT(--(C$5:C$24<=K$5:K$24))=0,"siempre",IF(LOOKUP(2,1/(C$5:C$24<=K$5:K$24),$A$5:$A$24)>=2046,"nunca",LOOKUP(2,1/(C$5:C$24<=K$5:K$24),$A$5:$A$24)+1)) | L37: =IF(SUMPRODUCT(--(C$5:C$24<=L$5:L$24))=0,"siempre",IF(LOOKUP(2,1/(C$5:C$24<=L$5:L$24),$A$5:$A$24)>=2046,"nunca",LOOKUP(2,1/(C$5:C$24<=L$5:L$24),$A$5:$A$24)+1)) | M37: =IF(SUMPRODUCT(--(C$5:C$24<=M$5:M$24))=0,"siempre",IF(LOOKUP(2,1/(C$5:C$24<=M$5:M$24),$A$5:$A$24)>=2046,"nunca",LOOKUP(2,1/(C$5:C$24<=M$5:M$24),$A$5:$A$24)+1)) | N37: =IF(SUMPRODUCT(--(C$5:C$24<=N$5:N$24))=0,"siempre",IF(LOOKUP(2,1/(C$5:C$24<=N$5:N$24),$A$5:$A$24)>=2046,"nunca",LOOKUP(2,1/(C$5:C$24<=N$5:N$24),$A$5:$A$24)+1)) | O37: =IF(SUMPRODUCT(--(C$5:C$24<=O$5:O$24))=0,"siempre",IF(LOOKUP(2,1/(C$5:C$24<=O$5:O$24),$A$5:$A$24)>=2046,"nunca",LOOKUP(2,1/(C$5:C$24<=O$5:O$24),$A$5:$A$24)+1)) | P37: =IF(SUMPRODUCT(--(C$5:C$24<=P$5:P$24))=0,"siempre",IF(LOOKUP(2,1/(C$5:C$24<=P$5:P$24),$A$5:$A$24)>=2046,"nunca",LOOKUP(2,1/(C$5:C$24<=P$5:P$24),$A$5:$A$24)+1))
A38: A3 · ICU → Travel nurse | B38: =IF(SUMPRODUCT(--(D$5:D$24<=B$5:B$24))=0,"siempre",IF(LOOKUP(2,1/(D$5:D$24<=B$5:B$24),$A$5:$A$24)>=2046,"nunca",LOOKUP(2,1/(D$5:D$24<=B$5:B$24),$A$5:$A$24)+1)) | C38: =IF(SUMPRODUCT(--(D$5:D$24<=C$5:C$24))=0,"siempre",IF(LOOKUP(2,1/(D$5:D$24<=C$5:C$24),$A$5:$A$24)>=2046,"nunca",LOOKUP(2,1/(D$5:D$24<=C$5:C$24),$A$5:$A$24)+1)) | D38: — | E38: =IF(SUMPRODUCT(--(D$5:D$24<=E$5:E$24))=0,"siempre",IF(LOOKUP(2,1/(D$5:D$24<=E$5:E$24),$A$5:$A$24)>=2046,"nunca",LOOKUP(2,1/(D$5:D$24<=E$5:E$24),$A$5:$A$24)+1)) | F38: =IF(SUMPRODUCT(--(D$5:D$24<=F$5:F$24))=0,"siempre",IF(LOOKUP(2,1/(D$5:D$24<=F$5:F$24),$A$5:$A$24)>=2046,"nunca",LOOKUP(2,1/(D$5:D$24<=F$5:F$24),$A$5:$A$24)+1)) | G38: =IF(SUMPRODUCT(--(D$5:D$24<=G$5:G$24))=0,"siempre",IF(LOOKUP(2,1/(D$5:D$24<=G$5:G$24),$A$5:$A$24)>=2046,"nunca",LOOKUP(2,1/(D$5:D$24<=G$5:G$24),$A$5:$A$24)+1)) | H38: =IF(SUMPRODUCT(--(D$5:D$24<=H$5:H$24))=0,"siempre",IF(LOOKUP(2,1/(D$5:D$24<=H$5:H$24),$A$5:$A$24)>=2046,"nunca",LOOKUP(2,1/(D$5:D$24<=H$5:H$24),$A$5:$A$24)+1)) | I38: =IF(SUMPRODUCT(--(D$5:D$24<=I$5:I$24))=0,"siempre",IF(LOOKUP(2,1/(D$5:D$24<=I$5:I$24),$A$5:$A$24)>=2046,"nunca",LOOKUP(2,1/(D$5:D$24<=I$5:I$24),$A$5:$A$24)+1)) | J38: =IF(SUMPRODUCT(--(D$5:D$24<=J$5:J$24))=0,"siempre",IF(LOOKUP(2,1/(D$5:D$24<=J$5:J$24),$A$5:$A$24)>=2046,"nunca",LOOKUP(2,1/(D$5:D$24<=J$5:J$24),$A$5:$A$24)+1)) | K38: =IF(SUMPRODUCT(--(D$5:D$24<=K$5:K$24))=0,"siempre",IF(LOOKUP(2,1/(D$5:D$24<=K$5:K$24),$A$5:$A$24)>=2046,"nunca",LOOKUP(2,1/(D$5:D$24<=K$5:K$24),$A$5:$A$24)+1)) | L38: =IF(SUMPRODUCT(--(D$5:D$24<=L$5:L$24))=0,"siempre",IF(LOOKUP(2,1/(D$5:D$24<=L$5:L$24),$A$5:$A$24)>=2046,"nunca",LOOKUP(2,1/(D$5:D$24<=L$5:L$24),$A$5:$A$24)+1)) | M38: =IF(SUMPRODUCT(--(D$5:D$24<=M$5:M$24))=0,"siempre",IF(LOOKUP(2,1/(D$5:D$24<=M$5:M$24),$A$5:$A$24)>=2046,"nunca",LOOKUP(2,1/(D$5:D$24<=M$5:M$24),$A$5:$A$24)+1)) | N38: =IF(SUMPRODUCT(--(D$5:D$24<=N$5:N$24))=0,"siempre",IF(LOOKUP(2,1/(D$5:D$24<=N$5:N$24),$A$5:$A$24)>=2046,"nunca",LOOKUP(2,1/(D$5:D$24<=N$5:N$24),$A$5:$A$24)+1)) | O38: =IF(SUMPRODUCT(--(D$5:D$24<=O$5:O$24))=0,"siempre",IF(LOOKUP(2,1/(D$5:D$24<=O$5:O$24),$A$5:$A$24)>=2046,"nunca",LOOKUP(2,1/(D$5:D$24<=O$5:O$24),$A$5:$A$24)+1)) | P38: =IF(SUMPRODUCT(--(D$5:D$24<=P$5:P$24))=0,"siempre",IF(LOOKUP(2,1/(D$5:D$24<=P$5:P$24),$A$5:$A$24)>=2046,"nunca",LOOKUP(2,1/(D$5:D$24<=P$5:P$24),$A$5:$A$24)+1))
A39: A4 · CDI / informática (valora tu MD) | B39: =IF(SUMPRODUCT(--(E$5:E$24<=B$5:B$24))=0,"siempre",IF(LOOKUP(2,1/(E$5:E$24<=B$5:B$24),$A$5:$A$24)>=2046,"nunca",LOOKUP(2,1/(E$5:E$24<=B$5:B$24),$A$5:$A$24)+1)) | C39: =IF(SUMPRODUCT(--(E$5:E$24<=C$5:C$24))=0,"siempre",IF(LOOKUP(2,1/(E$5:E$24<=C$5:C$24),$A$5:$A$24)>=2046,"nunca",LOOKUP(2,1/(E$5:E$24<=C$5:C$24),$A$5:$A$24)+1)) | D39: =IF(SUMPRODUCT(--(E$5:E$24<=D$5:D$24))=0,"siempre",IF(LOOKUP(2,1/(E$5:E$24<=D$5:D$24),$A$5:$A$24)>=2046,"nunca",LOOKUP(2,1/(E$5:E$24<=D$5:D$24),$A$5:$A$24)+1)) | E39: — | F39: =IF(SUMPRODUCT(--(E$5:E$24<=F$5:F$24))=0,"siempre",IF(LOOKUP(2,1/(E$5:E$24<=F$5:F$24),$A$5:$A$24)>=2046,"nunca",LOOKUP(2,1/(E$5:E$24<=F$5:F$24),$A$5:$A$24)+1)) | G39: =IF(SUMPRODUCT(--(E$5:E$24<=G$5:G$24))=0,"siempre",IF(LOOKUP(2,1/(E$5:E$24<=G$5:G$24),$A$5:$A$24)>=2046,"nunca",LOOKUP(2,1/(E$5:E$24<=G$5:G$24),$A$5:$A$24)+1)) | H39: =IF(SUMPRODUCT(--(E$5:E$24<=H$5:H$24))=0,"siempre",IF(LOOKUP(2,1/(E$5:E$24<=H$5:H$24),$A$5:$A$24)>=2046,"nunca",LOOKUP(2,1/(E$5:E$24<=H$5:H$24),$A$5:$A$24)+1)) | I39: =IF(SUMPRODUCT(--(E$5:E$24<=I$5:I$24))=0,"siempre",IF(LOOKUP(2,1/(E$5:E$24<=I$5:I$24),$A$5:$A$24)>=2046,"nunca",LOOKUP(2,1/(E$5:E$24<=I$5:I$24),$A$5:$A$24)+1)) | J39: =IF(SUMPRODUCT(--(E$5:E$24<=J$5:J$24))=0,"siempre",IF(LOOKUP(2,1/(E$5:E$24<=J$5:J$24),$A$5:$A$24)>=2046,"nunca",LOOKUP(2,1/(E$5:E$24<=J$5:J$24),$A$5:$A$24)+1)) | K39: =IF(SUMPRODUCT(--(E$5:E$24<=K$5:K$24))=0,"siempre",IF(LOOKUP(2,1/(E$5:E$24<=K$5:K$24),$A$5:$A$24)>=2046,"nunca",LOOKUP(2,1/(E$5:E$24<=K$5:K$24),$A$5:$A$24)+1)) | L39: =IF(SUMPRODUCT(--(E$5:E$24<=L$5:L$24))=0,"siempre",IF(LOOKUP(2,1/(E$5:E$24<=L$5:L$24),$A$5:$A$24)>=2046,"nunca",LOOKUP(2,1/(E$5:E$24<=L$5:L$24),$A$5:$A$24)+1)) | M39: =IF(SUMPRODUCT(--(E$5:E$24<=M$5:M$24))=0,"siempre",IF(LOOKUP(2,1/(E$5:E$24<=M$5:M$24),$A$5:$A$24)>=2046,"nunca",LOOKUP(2,1/(E$5:E$24<=M$5:M$24),$A$5:$A$24)+1)) | N39: =IF(SUMPRODUCT(--(E$5:E$24<=N$5:N$24))=0,"siempre",IF(LOOKUP(2,1/(E$5:E$24<=N$5:N$24),$A$5:$A$24)>=2046,"nunca",LOOKUP(2,1/(E$5:E$24<=N$5:N$24),$A$5:$A$24)+1)) | O39: =IF(SUMPRODUCT(--(E$5:E$24<=O$5:O$24))=0,"siempre",IF(LOOKUP(2,1/(E$5:E$24<=O$5:O$24),$A$5:$A$24)>=2046,"nunca",LOOKUP(2,1/(E$5:E$24<=O$5:O$24),$A$5:$A$24)+1)) | P39: =IF(SUMPRODUCT(--(E$5:E$24<=P$5:P$24))=0,"siempre",IF(LOOKUP(2,1/(E$5:E$24<=P$5:P$24),$A$5:$A$24)>=2046,"nunca",LOOKUP(2,1/(E$5:E$24<=P$5:P$24),$A$5:$A$24)+1))
A40: A5 · ICU → charge → nurse manager | B40: =IF(SUMPRODUCT(--(F$5:F$24<=B$5:B$24))=0,"siempre",IF(LOOKUP(2,1/(F$5:F$24<=B$5:B$24),$A$5:$A$24)>=2046,"nunca",LOOKUP(2,1/(F$5:F$24<=B$5:B$24),$A$5:$A$24)+1)) | C40: =IF(SUMPRODUCT(--(F$5:F$24<=C$5:C$24))=0,"siempre",IF(LOOKUP(2,1/(F$5:F$24<=C$5:C$24),$A$5:$A$24)>=2046,"nunca",LOOKUP(2,1/(F$5:F$24<=C$5:C$24),$A$5:$A$24)+1)) | D40: =IF(SUMPRODUCT(--(F$5:F$24<=D$5:D$24))=0,"siempre",IF(LOOKUP(2,1/(F$5:F$24<=D$5:D$24),$A$5:$A$24)>=2046,"nunca",LOOKUP(2,1/(F$5:F$24<=D$5:D$24),$A$5:$A$24)+1)) | E40: =IF(SUMPRODUCT(--(F$5:F$24<=E$5:E$24))=0,"siempre",IF(LOOKUP(2,1/(F$5:F$24<=E$5:E$24),$A$5:$A$24)>=2046,"nunca",LOOKUP(2,1/(F$5:F$24<=E$5:E$24),$A$5:$A$24)+1)) | F40: — | G40: =IF(SUMPRODUCT(--(F$5:F$24<=G$5:G$24))=0,"siempre",IF(LOOKUP(2,1/(F$5:F$24<=G$5:G$24),$A$5:$A$24)>=2046,"nunca",LOOKUP(2,1/(F$5:F$24<=G$5:G$24),$A$5:$A$24)+1)) | H40: =IF(SUMPRODUCT(--(F$5:F$24<=H$5:H$24))=0,"siempre",IF(LOOKUP(2,1/(F$5:F$24<=H$5:H$24),$A$5:$A$24)>=2046,"nunca",LOOKUP(2,1/(F$5:F$24<=H$5:H$24),$A$5:$A$24)+1)) | I40: =IF(SUMPRODUCT(--(F$5:F$24<=I$5:I$24))=0,"siempre",IF(LOOKUP(2,1/(F$5:F$24<=I$5:I$24),$A$5:$A$24)>=2046,"nunca",LOOKUP(2,1/(F$5:F$24<=I$5:I$24),$A$5:$A$24)+1)) | J40: =IF(SUMPRODUCT(--(F$5:F$24<=J$5:J$24))=0,"siempre",IF(LOOKUP(2,1/(F$5:F$24<=J$5:J$24),$A$5:$A$24)>=2046,"nunca",LOOKUP(2,1/(F$5:F$24<=J$5:J$24),$A$5:$A$24)+1)) | K40: =IF(SUMPRODUCT(--(F$5:F$24<=K$5:K$24))=0,"siempre",IF(LOOKUP(2,1/(F$5:F$24<=K$5:K$24),$A$5:$A$24)>=2046,"nunca",LOOKUP(2,1/(F$5:F$24<=K$5:K$24),$A$5:$A$24)+1)) | L40: =IF(SUMPRODUCT(--(F$5:F$24<=L$5:L$24))=0,"siempre",IF(LOOKUP(2,1/(F$5:F$24<=L$5:L$24),$A$5:$A$24)>=2046,"nunca",LOOKUP(2,1/(F$5:F$24<=L$5:L$24),$A$5:$A$24)+1)) | M40: =IF(SUMPRODUCT(--(F$5:F$24<=M$5:M$24))=0,"siempre",IF(LOOKUP(2,1/(F$5:F$24<=M$5:M$24),$A$5:$A$24)>=2046,"nunca",LOOKUP(2,1/(F$5:F$24<=M$5:M$24),$A$5:$A$24)+1)) | N40: =IF(SUMPRODUCT(--(F$5:F$24<=N$5:N$24))=0,"siempre",IF(LOOKUP(2,1/(F$5:F$24<=N$5:N$24),$A$5:$A$24)>=2046,"nunca",LOOKUP(2,1/(F$5:F$24<=N$5:N$24),$A$5:$A$24)+1)) | O40: =IF(SUMPRODUCT(--(F$5:F$24<=O$5:O$24))=0,"siempre",IF(LOOKUP(2,1/(F$5:F$24<=O$5:O$24),$A$5:$A$24)>=2046,"nunca",LOOKUP(2,1/(F$5:F$24<=O$5:O$24),$A$5:$A$24)+1)) | P40: =IF(SUMPRODUCT(--(F$5:F$24<=P$5:P$24))=0,"siempre",IF(LOOKUP(2,1/(F$5:F$24<=P$5:P$24),$A$5:$A$24)>=2046,"nunca",LOOKUP(2,1/(F$5:F$24<=P$5:P$24),$A$5:$A$24)+1))
A41: A5b · ICU → educador clínico | B41: =IF(SUMPRODUCT(--(G$5:G$24<=B$5:B$24))=0,"siempre",IF(LOOKUP(2,1/(G$5:G$24<=B$5:B$24),$A$5:$A$24)>=2046,"nunca",LOOKUP(2,1/(G$5:G$24<=B$5:B$24),$A$5:$A$24)+1)) | C41: =IF(SUMPRODUCT(--(G$5:G$24<=C$5:C$24))=0,"siempre",IF(LOOKUP(2,1/(G$5:G$24<=C$5:C$24),$A$5:$A$24)>=2046,"nunca",LOOKUP(2,1/(G$5:G$24<=C$5:C$24),$A$5:$A$24)+1)) | D41: =IF(SUMPRODUCT(--(G$5:G$24<=D$5:D$24))=0,"siempre",IF(LOOKUP(2,1/(G$5:G$24<=D$5:D$24),$A$5:$A$24)>=2046,"nunca",LOOKUP(2,1/(G$5:G$24<=D$5:D$24),$A$5:$A$24)+1)) | E41: =IF(SUMPRODUCT(--(G$5:G$24<=E$5:E$24))=0,"siempre",IF(LOOKUP(2,1/(G$5:G$24<=E$5:E$24),$A$5:$A$24)>=2046,"nunca",LOOKUP(2,1/(G$5:G$24<=E$5:E$24),$A$5:$A$24)+1)) | F41: =IF(SUMPRODUCT(--(G$5:G$24<=F$5:F$24))=0,"siempre",IF(LOOKUP(2,1/(G$5:G$24<=F$5:F$24),$A$5:$A$24)>=2046,"nunca",LOOKUP(2,1/(G$5:G$24<=F$5:F$24),$A$5:$A$24)+1)) | G41: — | H41: =IF(SUMPRODUCT(--(G$5:G$24<=H$5:H$24))=0,"siempre",IF(LOOKUP(2,1/(G$5:G$24<=H$5:H$24),$A$5:$A$24)>=2046,"nunca",LOOKUP(2,1/(G$5:G$24<=H$5:H$24),$A$5:$A$24)+1)) | I41: =IF(SUMPRODUCT(--(G$5:G$24<=I$5:I$24))=0,"siempre",IF(LOOKUP(2,1/(G$5:G$24<=I$5:I$24),$A$5:$A$24)>=2046,"nunca",LOOKUP(2,1/(G$5:G$24<=I$5:I$24),$A$5:$A$24)+1)) | J41: =IF(SUMPRODUCT(--(G$5:G$24<=J$5:J$24))=0,"siempre",IF(LOOKUP(2,1/(G$5:G$24<=J$5:J$24),$A$5:$A$24)>=2046,"nunca",LOOKUP(2,1/(G$5:G$24<=J$5:J$24),$A$5:$A$24)+1)) | K41: =IF(SUMPRODUCT(--(G$5:G$24<=K$5:K$24))=0,"siempre",IF(LOOKUP(2,1/(G$5:G$24<=K$5:K$24),$A$5:$A$24)>=2046,"nunca",LOOKUP(2,1/(G$5:G$24<=K$5:K$24),$A$5:$A$24)+1)) | L41: =IF(SUMPRODUCT(--(G$5:G$24<=L$5:L$24))=0,"siempre",IF(LOOKUP(2,1/(G$5:G$24<=L$5:L$24),$A$5:$A$24)>=2046,"nunca",LOOKUP(2,1/(G$5:G$24<=L$5:L$24),$A$5:$A$24)+1)) | M41: =IF(SUMPRODUCT(--(G$5:G$24<=M$5:M$24))=0,"siempre",IF(LOOKUP(2,1/(G$5:G$24<=M$5:M$24),$A$5:$A$24)>=2046,"nunca",LOOKUP(2,1/(G$5:G$24<=M$5:M$24),$A$5:$A$24)+1)) | N41: =IF(SUMPRODUCT(--(G$5:G$24<=N$5:N$24))=0,"siempre",IF(LOOKUP(2,1/(G$5:G$24<=N$5:N$24),$A$5:$A$24)>=2046,"nunca",LOOKUP(2,1/(G$5:G$24<=N$5:N$24),$A$5:$A$24)+1)) | O41: =IF(SUMPRODUCT(--(G$5:G$24<=O$5:O$24))=0,"siempre",IF(LOOKUP(2,1/(G$5:G$24<=O$5:O$24),$A$5:$A$24)>=2046,"nunca",LOOKUP(2,1/(G$5:G$24<=O$5:O$24),$A$5:$A$24)+1)) | P41: =IF(SUMPRODUCT(--(G$5:G$24<=P$5:P$24))=0,"siempre",IF(LOOKUP(2,1/(G$5:G$24<=P$5:P$24),$A$5:$A$24)>=2046,"nunca",LOOKUP(2,1/(G$5:G$24<=P$5:P$24),$A$5:$A$24)+1))
A42: A6 · Nurse injector / estética | B42: =IF(SUMPRODUCT(--(H$5:H$24<=B$5:B$24))=0,"siempre",IF(LOOKUP(2,1/(H$5:H$24<=B$5:B$24),$A$5:$A$24)>=2046,"nunca",LOOKUP(2,1/(H$5:H$24<=B$5:B$24),$A$5:$A$24)+1)) | C42: =IF(SUMPRODUCT(--(H$5:H$24<=C$5:C$24))=0,"siempre",IF(LOOKUP(2,1/(H$5:H$24<=C$5:C$24),$A$5:$A$24)>=2046,"nunca",LOOKUP(2,1/(H$5:H$24<=C$5:C$24),$A$5:$A$24)+1)) | D42: =IF(SUMPRODUCT(--(H$5:H$24<=D$5:D$24))=0,"siempre",IF(LOOKUP(2,1/(H$5:H$24<=D$5:D$24),$A$5:$A$24)>=2046,"nunca",LOOKUP(2,1/(H$5:H$24<=D$5:D$24),$A$5:$A$24)+1)) | E42: =IF(SUMPRODUCT(--(H$5:H$24<=E$5:E$24))=0,"siempre",IF(LOOKUP(2,1/(H$5:H$24<=E$5:E$24),$A$5:$A$24)>=2046,"nunca",LOOKUP(2,1/(H$5:H$24<=E$5:E$24),$A$5:$A$24)+1)) | F42: =IF(SUMPRODUCT(--(H$5:H$24<=F$5:F$24))=0,"siempre",IF(LOOKUP(2,1/(H$5:H$24<=F$5:F$24),$A$5:$A$24)>=2046,"nunca",LOOKUP(2,1/(H$5:H$24<=F$5:F$24),$A$5:$A$24)+1)) | G42: =IF(SUMPRODUCT(--(H$5:H$24<=G$5:G$24))=0,"siempre",IF(LOOKUP(2,1/(H$5:H$24<=G$5:G$24),$A$5:$A$24)>=2046,"nunca",LOOKUP(2,1/(H$5:H$24<=G$5:G$24),$A$5:$A$24)+1)) | H42: — | I42: =IF(SUMPRODUCT(--(H$5:H$24<=I$5:I$24))=0,"siempre",IF(LOOKUP(2,1/(H$5:H$24<=I$5:I$24),$A$5:$A$24)>=2046,"nunca",LOOKUP(2,1/(H$5:H$24<=I$5:I$24),$A$5:$A$24)+1)) | J42: =IF(SUMPRODUCT(--(H$5:H$24<=J$5:J$24))=0,"siempre",IF(LOOKUP(2,1/(H$5:H$24<=J$5:J$24),$A$5:$A$24)>=2046,"nunca",LOOKUP(2,1/(H$5:H$24<=J$5:J$24),$A$5:$A$24)+1)) | K42: =IF(SUMPRODUCT(--(H$5:H$24<=K$5:K$24))=0,"siempre",IF(LOOKUP(2,1/(H$5:H$24<=K$5:K$24),$A$5:$A$24)>=2046,"nunca",LOOKUP(2,1/(H$5:H$24<=K$5:K$24),$A$5:$A$24)+1)) | L42: =IF(SUMPRODUCT(--(H$5:H$24<=L$5:L$24))=0,"siempre",IF(LOOKUP(2,1/(H$5:H$24<=L$5:L$24),$A$5:$A$24)>=2046,"nunca",LOOKUP(2,1/(H$5:H$24<=L$5:L$24),$A$5:$A$24)+1)) | M42: =IF(SUMPRODUCT(--(H$5:H$24<=M$5:M$24))=0,"siempre",IF(LOOKUP(2,1/(H$5:H$24<=M$5:M$24),$A$5:$A$24)>=2046,"nunca",LOOKUP(2,1/(H$5:H$24<=M$5:M$24),$A$5:$A$24)+1)) | N42: =IF(SUMPRODUCT(--(H$5:H$24<=N$5:N$24))=0,"siempre",IF(LOOKUP(2,1/(H$5:H$24<=N$5:N$24),$A$5:$A$24)>=2046,"nunca",LOOKUP(2,1/(H$5:H$24<=N$5:N$24),$A$5:$A$24)+1)) | O42: =IF(SUMPRODUCT(--(H$5:H$24<=O$5:O$24))=0,"siempre",IF(LOOKUP(2,1/(H$5:H$24<=O$5:O$24),$A$5:$A$24)>=2046,"nunca",LOOKUP(2,1/(H$5:H$24<=O$5:O$24),$A$5:$A$24)+1)) | P42: =IF(SUMPRODUCT(--(H$5:H$24<=P$5:P$24))=0,"siempre",IF(LOOKUP(2,1/(H$5:H$24<=P$5:P$24),$A$5:$A$24)>=2046,"nunca",LOOKUP(2,1/(H$5:H$24<=P$5:P$24),$A$5:$A$24)+1))
A43: A7 · ICU → CRNA | B43: =IF(SUMPRODUCT(--(I$5:I$24<=B$5:B$24))=0,"siempre",IF(LOOKUP(2,1/(I$5:I$24<=B$5:B$24),$A$5:$A$24)>=2046,"nunca",LOOKUP(2,1/(I$5:I$24<=B$5:B$24),$A$5:$A$24)+1)) | C43: =IF(SUMPRODUCT(--(I$5:I$24<=C$5:C$24))=0,"siempre",IF(LOOKUP(2,1/(I$5:I$24<=C$5:C$24),$A$5:$A$24)>=2046,"nunca",LOOKUP(2,1/(I$5:I$24<=C$5:C$24),$A$5:$A$24)+1)) | D43: =IF(SUMPRODUCT(--(I$5:I$24<=D$5:D$24))=0,"siempre",IF(LOOKUP(2,1/(I$5:I$24<=D$5:D$24),$A$5:$A$24)>=2046,"nunca",LOOKUP(2,1/(I$5:I$24<=D$5:D$24),$A$5:$A$24)+1)) | E43: =IF(SUMPRODUCT(--(I$5:I$24<=E$5:E$24))=0,"siempre",IF(LOOKUP(2,1/(I$5:I$24<=E$5:E$24),$A$5:$A$24)>=2046,"nunca",LOOKUP(2,1/(I$5:I$24<=E$5:E$24),$A$5:$A$24)+1)) | F43: =IF(SUMPRODUCT(--(I$5:I$24<=F$5:F$24))=0,"siempre",IF(LOOKUP(2,1/(I$5:I$24<=F$5:F$24),$A$5:$A$24)>=2046,"nunca",LOOKUP(2,1/(I$5:I$24<=F$5:F$24),$A$5:$A$24)+1)) | G43: =IF(SUMPRODUCT(--(I$5:I$24<=G$5:G$24))=0,"siempre",IF(LOOKUP(2,1/(I$5:I$24<=G$5:G$24),$A$5:$A$24)>=2046,"nunca",LOOKUP(2,1/(I$5:I$24<=G$5:G$24),$A$5:$A$24)+1)) | H43: =IF(SUMPRODUCT(--(I$5:I$24<=H$5:H$24))=0,"siempre",IF(LOOKUP(2,1/(I$5:I$24<=H$5:H$24),$A$5:$A$24)>=2046,"nunca",LOOKUP(2,1/(I$5:I$24<=H$5:H$24),$A$5:$A$24)+1)) | I43: — | J43: =IF(SUMPRODUCT(--(I$5:I$24<=J$5:J$24))=0,"siempre",IF(LOOKUP(2,1/(I$5:I$24<=J$5:J$24),$A$5:$A$24)>=2046,"nunca",LOOKUP(2,1/(I$5:I$24<=J$5:J$24),$A$5:$A$24)+1)) | K43: =IF(SUMPRODUCT(--(I$5:I$24<=K$5:K$24))=0,"siempre",IF(LOOKUP(2,1/(I$5:I$24<=K$5:K$24),$A$5:$A$24)>=2046,"nunca",LOOKUP(2,1/(I$5:I$24<=K$5:K$24),$A$5:$A$24)+1)) | L43: =IF(SUMPRODUCT(--(I$5:I$24<=L$5:L$24))=0,"siempre",IF(LOOKUP(2,1/(I$5:I$24<=L$5:L$24),$A$5:$A$24)>=2046,"nunca",LOOKUP(2,1/(I$5:I$24<=L$5:L$24),$A$5:$A$24)+1)) | M43: =IF(SUMPRODUCT(--(I$5:I$24<=M$5:M$24))=0,"siempre",IF(LOOKUP(2,1/(I$5:I$24<=M$5:M$24),$A$5:$A$24)>=2046,"nunca",LOOKUP(2,1/(I$5:I$24<=M$5:M$24),$A$5:$A$24)+1)) | N43: =IF(SUMPRODUCT(--(I$5:I$24<=N$5:N$24))=0,"siempre",IF(LOOKUP(2,1/(I$5:I$24<=N$5:N$24),$A$5:$A$24)>=2046,"nunca",LOOKUP(2,1/(I$5:I$24<=N$5:N$24),$A$5:$A$24)+1)) | O43: =IF(SUMPRODUCT(--(I$5:I$24<=O$5:O$24))=0,"siempre",IF(LOOKUP(2,1/(I$5:I$24<=O$5:O$24),$A$5:$A$24)>=2046,"nunca",LOOKUP(2,1/(I$5:I$24<=O$5:O$24),$A$5:$A$24)+1)) | P43: =IF(SUMPRODUCT(--(I$5:I$24<=P$5:P$24))=0,"siempre",IF(LOOKUP(2,1/(I$5:I$24<=P$5:P$24),$A$5:$A$24)>=2046,"nunca",LOOKUP(2,1/(I$5:I$24<=P$5:P$24),$A$5:$A$24)+1))
A44: A7b · ICU → Travel → CRNA | B44: =IF(SUMPRODUCT(--(J$5:J$24<=B$5:B$24))=0,"siempre",IF(LOOKUP(2,1/(J$5:J$24<=B$5:B$24),$A$5:$A$24)>=2046,"nunca",LOOKUP(2,1/(J$5:J$24<=B$5:B$24),$A$5:$A$24)+1)) | C44: =IF(SUMPRODUCT(--(J$5:J$24<=C$5:C$24))=0,"siempre",IF(LOOKUP(2,1/(J$5:J$24<=C$5:C$24),$A$5:$A$24)>=2046,"nunca",LOOKUP(2,1/(J$5:J$24<=C$5:C$24),$A$5:$A$24)+1)) | D44: =IF(SUMPRODUCT(--(J$5:J$24<=D$5:D$24))=0,"siempre",IF(LOOKUP(2,1/(J$5:J$24<=D$5:D$24),$A$5:$A$24)>=2046,"nunca",LOOKUP(2,1/(J$5:J$24<=D$5:D$24),$A$5:$A$24)+1)) | E44: =IF(SUMPRODUCT(--(J$5:J$24<=E$5:E$24))=0,"siempre",IF(LOOKUP(2,1/(J$5:J$24<=E$5:E$24),$A$5:$A$24)>=2046,"nunca",LOOKUP(2,1/(J$5:J$24<=E$5:E$24),$A$5:$A$24)+1)) | F44: =IF(SUMPRODUCT(--(J$5:J$24<=F$5:F$24))=0,"siempre",IF(LOOKUP(2,1/(J$5:J$24<=F$5:F$24),$A$5:$A$24)>=2046,"nunca",LOOKUP(2,1/(J$5:J$24<=F$5:F$24),$A$5:$A$24)+1)) | G44: =IF(SUMPRODUCT(--(J$5:J$24<=G$5:G$24))=0,"siempre",IF(LOOKUP(2,1/(J$5:J$24<=G$5:G$24),$A$5:$A$24)>=2046,"nunca",LOOKUP(2,1/(J$5:J$24<=G$5:G$24),$A$5:$A$24)+1)) | H44: =IF(SUMPRODUCT(--(J$5:J$24<=H$5:H$24))=0,"siempre",IF(LOOKUP(2,1/(J$5:J$24<=H$5:H$24),$A$5:$A$24)>=2046,"nunca",LOOKUP(2,1/(J$5:J$24<=H$5:H$24),$A$5:$A$24)+1)) | I44: =IF(SUMPRODUCT(--(J$5:J$24<=I$5:I$24))=0,"siempre",IF(LOOKUP(2,1/(J$5:J$24<=I$5:I$24),$A$5:$A$24)>=2046,"nunca",LOOKUP(2,1/(J$5:J$24<=I$5:I$24),$A$5:$A$24)+1)) | J44: — | K44: =IF(SUMPRODUCT(--(J$5:J$24<=K$5:K$24))=0,"siempre",IF(LOOKUP(2,1/(J$5:J$24<=K$5:K$24),$A$5:$A$24)>=2046,"nunca",LOOKUP(2,1/(J$5:J$24<=K$5:K$24),$A$5:$A$24)+1)) | L44: =IF(SUMPRODUCT(--(J$5:J$24<=L$5:L$24))=0,"siempre",IF(LOOKUP(2,1/(J$5:J$24<=L$5:L$24),$A$5:$A$24)>=2046,"nunca",LOOKUP(2,1/(J$5:J$24<=L$5:L$24),$A$5:$A$24)+1)) | M44: =IF(SUMPRODUCT(--(J$5:J$24<=M$5:M$24))=0,"siempre",IF(LOOKUP(2,1/(J$5:J$24<=M$5:M$24),$A$5:$A$24)>=2046,"nunca",LOOKUP(2,1/(J$5:J$24<=M$5:M$24),$A$5:$A$24)+1)) | N44: =IF(SUMPRODUCT(--(J$5:J$24<=N$5:N$24))=0,"siempre",IF(LOOKUP(2,1/(J$5:J$24<=N$5:N$24),$A$5:$A$24)>=2046,"nunca",LOOKUP(2,1/(J$5:J$24<=N$5:N$24),$A$5:$A$24)+1)) | O44: =IF(SUMPRODUCT(--(J$5:J$24<=O$5:O$24))=0,"siempre",IF(LOOKUP(2,1/(J$5:J$24<=O$5:O$24),$A$5:$A$24)>=2046,"nunca",LOOKUP(2,1/(J$5:J$24<=O$5:O$24),$A$5:$A$24)+1)) | P44: =IF(SUMPRODUCT(--(J$5:J$24<=P$5:P$24))=0,"siempre",IF(LOOKUP(2,1/(J$5:J$24<=P$5:P$24),$A$5:$A$24)>=2046,"nunca",LOOKUP(2,1/(J$5:J$24<=P$5:P$24),$A$5:$A$24)+1))
A45: A8 · NP familiar (FNP) | B45: =IF(SUMPRODUCT(--(K$5:K$24<=B$5:B$24))=0,"siempre",IF(LOOKUP(2,1/(K$5:K$24<=B$5:B$24),$A$5:$A$24)>=2046,"nunca",LOOKUP(2,1/(K$5:K$24<=B$5:B$24),$A$5:$A$24)+1)) | C45: =IF(SUMPRODUCT(--(K$5:K$24<=C$5:C$24))=0,"siempre",IF(LOOKUP(2,1/(K$5:K$24<=C$5:C$24),$A$5:$A$24)>=2046,"nunca",LOOKUP(2,1/(K$5:K$24<=C$5:C$24),$A$5:$A$24)+1)) | D45: =IF(SUMPRODUCT(--(K$5:K$24<=D$5:D$24))=0,"siempre",IF(LOOKUP(2,1/(K$5:K$24<=D$5:D$24),$A$5:$A$24)>=2046,"nunca",LOOKUP(2,1/(K$5:K$24<=D$5:D$24),$A$5:$A$24)+1)) | E45: =IF(SUMPRODUCT(--(K$5:K$24<=E$5:E$24))=0,"siempre",IF(LOOKUP(2,1/(K$5:K$24<=E$5:E$24),$A$5:$A$24)>=2046,"nunca",LOOKUP(2,1/(K$5:K$24<=E$5:E$24),$A$5:$A$24)+1)) | F45: =IF(SUMPRODUCT(--(K$5:K$24<=F$5:F$24))=0,"siempre",IF(LOOKUP(2,1/(K$5:K$24<=F$5:F$24),$A$5:$A$24)>=2046,"nunca",LOOKUP(2,1/(K$5:K$24<=F$5:F$24),$A$5:$A$24)+1)) | G45: =IF(SUMPRODUCT(--(K$5:K$24<=G$5:G$24))=0,"siempre",IF(LOOKUP(2,1/(K$5:K$24<=G$5:G$24),$A$5:$A$24)>=2046,"nunca",LOOKUP(2,1/(K$5:K$24<=G$5:G$24),$A$5:$A$24)+1)) | H45: =IF(SUMPRODUCT(--(K$5:K$24<=H$5:H$24))=0,"siempre",IF(LOOKUP(2,1/(K$5:K$24<=H$5:H$24),$A$5:$A$24)>=2046,"nunca",LOOKUP(2,1/(K$5:K$24<=H$5:H$24),$A$5:$A$24)+1)) | I45: =IF(SUMPRODUCT(--(K$5:K$24<=I$5:I$24))=0,"siempre",IF(LOOKUP(2,1/(K$5:K$24<=I$5:I$24),$A$5:$A$24)>=2046,"nunca",LOOKUP(2,1/(K$5:K$24<=I$5:I$24),$A$5:$A$24)+1)) | J45: =IF(SUMPRODUCT(--(K$5:K$24<=J$5:J$24))=0,"siempre",IF(LOOKUP(2,1/(K$5:K$24<=J$5:J$24),$A$5:$A$24)>=2046,"nunca",LOOKUP(2,1/(K$5:K$24<=J$5:J$24),$A$5:$A$24)+1)) | K45: — | L45: =IF(SUMPRODUCT(--(K$5:K$24<=L$5:L$24))=0,"siempre",IF(LOOKUP(2,1/(K$5:K$24<=L$5:L$24),$A$5:$A$24)>=2046,"nunca",LOOKUP(2,1/(K$5:K$24<=L$5:L$24),$A$5:$A$24)+1)) | M45: =IF(SUMPRODUCT(--(K$5:K$24<=M$5:M$24))=0,"siempre",IF(LOOKUP(2,1/(K$5:K$24<=M$5:M$24),$A$5:$A$24)>=2046,"nunca",LOOKUP(2,1/(K$5:K$24<=M$5:M$24),$A$5:$A$24)+1)) | N45: =IF(SUMPRODUCT(--(K$5:K$24<=N$5:N$24))=0,"siempre",IF(LOOKUP(2,1/(K$5:K$24<=N$5:N$24),$A$5:$A$24)>=2046,"nunca",LOOKUP(2,1/(K$5:K$24<=N$5:N$24),$A$5:$A$24)+1)) | O45: =IF(SUMPRODUCT(--(K$5:K$24<=O$5:O$24))=0,"siempre",IF(LOOKUP(2,1/(K$5:K$24<=O$5:O$24),$A$5:$A$24)>=2046,"nunca",LOOKUP(2,1/(K$5:K$24<=O$5:O$24),$A$5:$A$24)+1)) | P45: =IF(SUMPRODUCT(--(K$5:K$24<=P$5:P$24))=0,"siempre",IF(LOOKUP(2,1/(K$5:K$24<=P$5:P$24),$A$5:$A$24)>=2046,"nunca",LOOKUP(2,1/(K$5:K$24<=P$5:P$24),$A$5:$A$24)+1))
A46: A8b · NP psiquiátrico (PMHNP) | B46: =IF(SUMPRODUCT(--(L$5:L$24<=B$5:B$24))=0,"siempre",IF(LOOKUP(2,1/(L$5:L$24<=B$5:B$24),$A$5:$A$24)>=2046,"nunca",LOOKUP(2,1/(L$5:L$24<=B$5:B$24),$A$5:$A$24)+1)) | C46: =IF(SUMPRODUCT(--(L$5:L$24<=C$5:C$24))=0,"siempre",IF(LOOKUP(2,1/(L$5:L$24<=C$5:C$24),$A$5:$A$24)>=2046,"nunca",LOOKUP(2,1/(L$5:L$24<=C$5:C$24),$A$5:$A$24)+1)) | D46: =IF(SUMPRODUCT(--(L$5:L$24<=D$5:D$24))=0,"siempre",IF(LOOKUP(2,1/(L$5:L$24<=D$5:D$24),$A$5:$A$24)>=2046,"nunca",LOOKUP(2,1/(L$5:L$24<=D$5:D$24),$A$5:$A$24)+1)) | E46: =IF(SUMPRODUCT(--(L$5:L$24<=E$5:E$24))=0,"siempre",IF(LOOKUP(2,1/(L$5:L$24<=E$5:E$24),$A$5:$A$24)>=2046,"nunca",LOOKUP(2,1/(L$5:L$24<=E$5:E$24),$A$5:$A$24)+1)) | F46: =IF(SUMPRODUCT(--(L$5:L$24<=F$5:F$24))=0,"siempre",IF(LOOKUP(2,1/(L$5:L$24<=F$5:F$24),$A$5:$A$24)>=2046,"nunca",LOOKUP(2,1/(L$5:L$24<=F$5:F$24),$A$5:$A$24)+1)) | G46: =IF(SUMPRODUCT(--(L$5:L$24<=G$5:G$24))=0,"siempre",IF(LOOKUP(2,1/(L$5:L$24<=G$5:G$24),$A$5:$A$24)>=2046,"nunca",LOOKUP(2,1/(L$5:L$24<=G$5:G$24),$A$5:$A$24)+1)) | H46: =IF(SUMPRODUCT(--(L$5:L$24<=H$5:H$24))=0,"siempre",IF(LOOKUP(2,1/(L$5:L$24<=H$5:H$24),$A$5:$A$24)>=2046,"nunca",LOOKUP(2,1/(L$5:L$24<=H$5:H$24),$A$5:$A$24)+1)) | I46: =IF(SUMPRODUCT(--(L$5:L$24<=I$5:I$24))=0,"siempre",IF(LOOKUP(2,1/(L$5:L$24<=I$5:I$24),$A$5:$A$24)>=2046,"nunca",LOOKUP(2,1/(L$5:L$24<=I$5:I$24),$A$5:$A$24)+1)) | J46: =IF(SUMPRODUCT(--(L$5:L$24<=J$5:J$24))=0,"siempre",IF(LOOKUP(2,1/(L$5:L$24<=J$5:J$24),$A$5:$A$24)>=2046,"nunca",LOOKUP(2,1/(L$5:L$24<=J$5:J$24),$A$5:$A$24)+1)) | K46: =IF(SUMPRODUCT(--(L$5:L$24<=K$5:K$24))=0,"siempre",IF(LOOKUP(2,1/(L$5:L$24<=K$5:K$24),$A$5:$A$24)>=2046,"nunca",LOOKUP(2,1/(L$5:L$24<=K$5:K$24),$A$5:$A$24)+1)) | L46: — | M46: =IF(SUMPRODUCT(--(L$5:L$24<=M$5:M$24))=0,"siempre",IF(LOOKUP(2,1/(L$5:L$24<=M$5:M$24),$A$5:$A$24)>=2046,"nunca",LOOKUP(2,1/(L$5:L$24<=M$5:M$24),$A$5:$A$24)+1)) | N46: =IF(SUMPRODUCT(--(L$5:L$24<=N$5:N$24))=0,"siempre",IF(LOOKUP(2,1/(L$5:L$24<=N$5:N$24),$A$5:$A$24)>=2046,"nunca",LOOKUP(2,1/(L$5:L$24<=N$5:N$24),$A$5:$A$24)+1)) | O46: =IF(SUMPRODUCT(--(L$5:L$24<=O$5:O$24))=0,"siempre",IF(LOOKUP(2,1/(L$5:L$24<=O$5:O$24),$A$5:$A$24)>=2046,"nunca",LOOKUP(2,1/(L$5:L$24<=O$5:O$24),$A$5:$A$24)+1)) | P46: =IF(SUMPRODUCT(--(L$5:L$24<=P$5:P$24))=0,"siempre",IF(LOOKUP(2,1/(L$5:L$24<=P$5:P$24),$A$5:$A$24)>=2046,"nunca",LOOKUP(2,1/(L$5:L$24<=P$5:P$24),$A$5:$A$24)+1))
A47: B1 · MD: match al primer intento | B47: =IF(SUMPRODUCT(--(M$5:M$24<=B$5:B$24))=0,"siempre",IF(LOOKUP(2,1/(M$5:M$24<=B$5:B$24),$A$5:$A$24)>=2046,"nunca",LOOKUP(2,1/(M$5:M$24<=B$5:B$24),$A$5:$A$24)+1)) | C47: =IF(SUMPRODUCT(--(M$5:M$24<=C$5:C$24))=0,"siempre",IF(LOOKUP(2,1/(M$5:M$24<=C$5:C$24),$A$5:$A$24)>=2046,"nunca",LOOKUP(2,1/(M$5:M$24<=C$5:C$24),$A$5:$A$24)+1)) | D47: =IF(SUMPRODUCT(--(M$5:M$24<=D$5:D$24))=0,"siempre",IF(LOOKUP(2,1/(M$5:M$24<=D$5:D$24),$A$5:$A$24)>=2046,"nunca",LOOKUP(2,1/(M$5:M$24<=D$5:D$24),$A$5:$A$24)+1)) | E47: =IF(SUMPRODUCT(--(M$5:M$24<=E$5:E$24))=0,"siempre",IF(LOOKUP(2,1/(M$5:M$24<=E$5:E$24),$A$5:$A$24)>=2046,"nunca",LOOKUP(2,1/(M$5:M$24<=E$5:E$24),$A$5:$A$24)+1)) | F47: =IF(SUMPRODUCT(--(M$5:M$24<=F$5:F$24))=0,"siempre",IF(LOOKUP(2,1/(M$5:M$24<=F$5:F$24),$A$5:$A$24)>=2046,"nunca",LOOKUP(2,1/(M$5:M$24<=F$5:F$24),$A$5:$A$24)+1)) | G47: =IF(SUMPRODUCT(--(M$5:M$24<=G$5:G$24))=0,"siempre",IF(LOOKUP(2,1/(M$5:M$24<=G$5:G$24),$A$5:$A$24)>=2046,"nunca",LOOKUP(2,1/(M$5:M$24<=G$5:G$24),$A$5:$A$24)+1)) | H47: =IF(SUMPRODUCT(--(M$5:M$24<=H$5:H$24))=0,"siempre",IF(LOOKUP(2,1/(M$5:M$24<=H$5:H$24),$A$5:$A$24)>=2046,"nunca",LOOKUP(2,1/(M$5:M$24<=H$5:H$24),$A$5:$A$24)+1)) | I47: =IF(SUMPRODUCT(--(M$5:M$24<=I$5:I$24))=0,"siempre",IF(LOOKUP(2,1/(M$5:M$24<=I$5:I$24),$A$5:$A$24)>=2046,"nunca",LOOKUP(2,1/(M$5:M$24<=I$5:I$24),$A$5:$A$24)+1)) | J47: =IF(SUMPRODUCT(--(M$5:M$24<=J$5:J$24))=0,"siempre",IF(LOOKUP(2,1/(M$5:M$24<=J$5:J$24),$A$5:$A$24)>=2046,"nunca",LOOKUP(2,1/(M$5:M$24<=J$5:J$24),$A$5:$A$24)+1)) | K47: =IF(SUMPRODUCT(--(M$5:M$24<=K$5:K$24))=0,"siempre",IF(LOOKUP(2,1/(M$5:M$24<=K$5:K$24),$A$5:$A$24)>=2046,"nunca",LOOKUP(2,1/(M$5:M$24<=K$5:K$24),$A$5:$A$24)+1)) | L47: =IF(SUMPRODUCT(--(M$5:M$24<=L$5:L$24))=0,"siempre",IF(LOOKUP(2,1/(M$5:M$24<=L$5:L$24),$A$5:$A$24)>=2046,"nunca",LOOKUP(2,1/(M$5:M$24<=L$5:L$24),$A$5:$A$24)+1)) | M47: — | N47: =IF(SUMPRODUCT(--(M$5:M$24<=N$5:N$24))=0,"siempre",IF(LOOKUP(2,1/(M$5:M$24<=N$5:N$24),$A$5:$A$24)>=2046,"nunca",LOOKUP(2,1/(M$5:M$24<=N$5:N$24),$A$5:$A$24)+1)) | O47: =IF(SUMPRODUCT(--(M$5:M$24<=O$5:O$24))=0,"siempre",IF(LOOKUP(2,1/(M$5:M$24<=O$5:O$24),$A$5:$A$24)>=2046,"nunca",LOOKUP(2,1/(M$5:M$24<=O$5:O$24),$A$5:$A$24)+1)) | P47: =IF(SUMPRODUCT(--(M$5:M$24<=P$5:P$24))=0,"siempre",IF(LOOKUP(2,1/(M$5:M$24<=P$5:P$24),$A$5:$A$24)>=2046,"nunca",LOOKUP(2,1/(M$5:M$24<=P$5:P$24),$A$5:$A$24)+1))
A48: B2 · MD: SOAP preliminar → categórico | B48: =IF(SUMPRODUCT(--(N$5:N$24<=B$5:B$24))=0,"siempre",IF(LOOKUP(2,1/(N$5:N$24<=B$5:B$24),$A$5:$A$24)>=2046,"nunca",LOOKUP(2,1/(N$5:N$24<=B$5:B$24),$A$5:$A$24)+1)) | C48: =IF(SUMPRODUCT(--(N$5:N$24<=C$5:C$24))=0,"siempre",IF(LOOKUP(2,1/(N$5:N$24<=C$5:C$24),$A$5:$A$24)>=2046,"nunca",LOOKUP(2,1/(N$5:N$24<=C$5:C$24),$A$5:$A$24)+1)) | D48: =IF(SUMPRODUCT(--(N$5:N$24<=D$5:D$24))=0,"siempre",IF(LOOKUP(2,1/(N$5:N$24<=D$5:D$24),$A$5:$A$24)>=2046,"nunca",LOOKUP(2,1/(N$5:N$24<=D$5:D$24),$A$5:$A$24)+1)) | E48: =IF(SUMPRODUCT(--(N$5:N$24<=E$5:E$24))=0,"siempre",IF(LOOKUP(2,1/(N$5:N$24<=E$5:E$24),$A$5:$A$24)>=2046,"nunca",LOOKUP(2,1/(N$5:N$24<=E$5:E$24),$A$5:$A$24)+1)) | F48: =IF(SUMPRODUCT(--(N$5:N$24<=F$5:F$24))=0,"siempre",IF(LOOKUP(2,1/(N$5:N$24<=F$5:F$24),$A$5:$A$24)>=2046,"nunca",LOOKUP(2,1/(N$5:N$24<=F$5:F$24),$A$5:$A$24)+1)) | G48: =IF(SUMPRODUCT(--(N$5:N$24<=G$5:G$24))=0,"siempre",IF(LOOKUP(2,1/(N$5:N$24<=G$5:G$24),$A$5:$A$24)>=2046,"nunca",LOOKUP(2,1/(N$5:N$24<=G$5:G$24),$A$5:$A$24)+1)) | H48: =IF(SUMPRODUCT(--(N$5:N$24<=H$5:H$24))=0,"siempre",IF(LOOKUP(2,1/(N$5:N$24<=H$5:H$24),$A$5:$A$24)>=2046,"nunca",LOOKUP(2,1/(N$5:N$24<=H$5:H$24),$A$5:$A$24)+1)) | I48: =IF(SUMPRODUCT(--(N$5:N$24<=I$5:I$24))=0,"siempre",IF(LOOKUP(2,1/(N$5:N$24<=I$5:I$24),$A$5:$A$24)>=2046,"nunca",LOOKUP(2,1/(N$5:N$24<=I$5:I$24),$A$5:$A$24)+1)) | J48: =IF(SUMPRODUCT(--(N$5:N$24<=J$5:J$24))=0,"siempre",IF(LOOKUP(2,1/(N$5:N$24<=J$5:J$24),$A$5:$A$24)>=2046,"nunca",LOOKUP(2,1/(N$5:N$24<=J$5:J$24),$A$5:$A$24)+1)) | K48: =IF(SUMPRODUCT(--(N$5:N$24<=K$5:K$24))=0,"siempre",IF(LOOKUP(2,1/(N$5:N$24<=K$5:K$24),$A$5:$A$24)>=2046,"nunca",LOOKUP(2,1/(N$5:N$24<=K$5:K$24),$A$5:$A$24)+1)) | L48: =IF(SUMPRODUCT(--(N$5:N$24<=L$5:L$24))=0,"siempre",IF(LOOKUP(2,1/(N$5:N$24<=L$5:L$24),$A$5:$A$24)>=2046,"nunca",LOOKUP(2,1/(N$5:N$24<=L$5:L$24),$A$5:$A$24)+1)) | M48: =IF(SUMPRODUCT(--(N$5:N$24<=M$5:M$24))=0,"siempre",IF(LOOKUP(2,1/(N$5:N$24<=M$5:M$24),$A$5:$A$24)>=2046,"nunca",LOOKUP(2,1/(N$5:N$24<=M$5:M$24),$A$5:$A$24)+1)) | N48: — | O48: =IF(SUMPRODUCT(--(N$5:N$24<=O$5:O$24))=0,"siempre",IF(LOOKUP(2,1/(N$5:N$24<=O$5:O$24),$A$5:$A$24)>=2046,"nunca",LOOKUP(2,1/(N$5:N$24<=O$5:O$24),$A$5:$A$24)+1)) | P48: =IF(SUMPRODUCT(--(N$5:N$24<=P$5:P$24))=0,"siempre",IF(LOOKUP(2,1/(N$5:N$24<=P$5:P$24),$A$5:$A$24)>=2046,"nunca",LOOKUP(2,1/(N$5:N$24<=P$5:P$24),$A$5:$A$24)+1))
A49: B3 · MD: no match → match al reintento | B49: =IF(SUMPRODUCT(--(O$5:O$24<=B$5:B$24))=0,"siempre",IF(LOOKUP(2,1/(O$5:O$24<=B$5:B$24),$A$5:$A$24)>=2046,"nunca",LOOKUP(2,1/(O$5:O$24<=B$5:B$24),$A$5:$A$24)+1)) | C49: =IF(SUMPRODUCT(--(O$5:O$24<=C$5:C$24))=0,"siempre",IF(LOOKUP(2,1/(O$5:O$24<=C$5:C$24),$A$5:$A$24)>=2046,"nunca",LOOKUP(2,1/(O$5:O$24<=C$5:C$24),$A$5:$A$24)+1)) | D49: =IF(SUMPRODUCT(--(O$5:O$24<=D$5:D$24))=0,"siempre",IF(LOOKUP(2,1/(O$5:O$24<=D$5:D$24),$A$5:$A$24)>=2046,"nunca",LOOKUP(2,1/(O$5:O$24<=D$5:D$24),$A$5:$A$24)+1)) | E49: =IF(SUMPRODUCT(--(O$5:O$24<=E$5:E$24))=0,"siempre",IF(LOOKUP(2,1/(O$5:O$24<=E$5:E$24),$A$5:$A$24)>=2046,"nunca",LOOKUP(2,1/(O$5:O$24<=E$5:E$24),$A$5:$A$24)+1)) | F49: =IF(SUMPRODUCT(--(O$5:O$24<=F$5:F$24))=0,"siempre",IF(LOOKUP(2,1/(O$5:O$24<=F$5:F$24),$A$5:$A$24)>=2046,"nunca",LOOKUP(2,1/(O$5:O$24<=F$5:F$24),$A$5:$A$24)+1)) | G49: =IF(SUMPRODUCT(--(O$5:O$24<=G$5:G$24))=0,"siempre",IF(LOOKUP(2,1/(O$5:O$24<=G$5:G$24),$A$5:$A$24)>=2046,"nunca",LOOKUP(2,1/(O$5:O$24<=G$5:G$24),$A$5:$A$24)+1)) | H49: =IF(SUMPRODUCT(--(O$5:O$24<=H$5:H$24))=0,"siempre",IF(LOOKUP(2,1/(O$5:O$24<=H$5:H$24),$A$5:$A$24)>=2046,"nunca",LOOKUP(2,1/(O$5:O$24<=H$5:H$24),$A$5:$A$24)+1)) | I49: =IF(SUMPRODUCT(--(O$5:O$24<=I$5:I$24))=0,"siempre",IF(LOOKUP(2,1/(O$5:O$24<=I$5:I$24),$A$5:$A$24)>=2046,"nunca",LOOKUP(2,1/(O$5:O$24<=I$5:I$24),$A$5:$A$24)+1)) | J49: =IF(SUMPRODUCT(--(O$5:O$24<=J$5:J$24))=0,"siempre",IF(LOOKUP(2,1/(O$5:O$24<=J$5:J$24),$A$5:$A$24)>=2046,"nunca",LOOKUP(2,1/(O$5:O$24<=J$5:J$24),$A$5:$A$24)+1)) | K49: =IF(SUMPRODUCT(--(O$5:O$24<=K$5:K$24))=0,"siempre",IF(LOOKUP(2,1/(O$5:O$24<=K$5:K$24),$A$5:$A$24)>=2046,"nunca",LOOKUP(2,1/(O$5:O$24<=K$5:K$24),$A$5:$A$24)+1)) | L49: =IF(SUMPRODUCT(--(O$5:O$24<=L$5:L$24))=0,"siempre",IF(LOOKUP(2,1/(O$5:O$24<=L$5:L$24),$A$5:$A$24)>=2046,"nunca",LOOKUP(2,1/(O$5:O$24<=L$5:L$24),$A$5:$A$24)+1)) | M49: =IF(SUMPRODUCT(--(O$5:O$24<=M$5:M$24))=0,"siempre",IF(LOOKUP(2,1/(O$5:O$24<=M$5:M$24),$A$5:$A$24)>=2046,"nunca",LOOKUP(2,1/(O$5:O$24<=M$5:M$24),$A$5:$A$24)+1)) | N49: =IF(SUMPRODUCT(--(O$5:O$24<=N$5:N$24))=0,"siempre",IF(LOOKUP(2,1/(O$5:O$24<=N$5:N$24),$A$5:$A$24)>=2046,"nunca",LOOKUP(2,1/(O$5:O$24<=N$5:N$24),$A$5:$A$24)+1)) | O49: — | P49: =IF(SUMPRODUCT(--(O$5:O$24<=P$5:P$24))=0,"siempre",IF(LOOKUP(2,1/(O$5:O$24<=P$5:P$24),$A$5:$A$24)>=2046,"nunca",LOOKUP(2,1/(O$5:O$24<=P$5:P$24),$A$5:$A$24)+1))
A50: B4 · MD: nunca hace match → vuelve a CDI | B50: =IF(SUMPRODUCT(--(P$5:P$24<=B$5:B$24))=0,"siempre",IF(LOOKUP(2,1/(P$5:P$24<=B$5:B$24),$A$5:$A$24)>=2046,"nunca",LOOKUP(2,1/(P$5:P$24<=B$5:B$24),$A$5:$A$24)+1)) | C50: =IF(SUMPRODUCT(--(P$5:P$24<=C$5:C$24))=0,"siempre",IF(LOOKUP(2,1/(P$5:P$24<=C$5:C$24),$A$5:$A$24)>=2046,"nunca",LOOKUP(2,1/(P$5:P$24<=C$5:C$24),$A$5:$A$24)+1)) | D50: =IF(SUMPRODUCT(--(P$5:P$24<=D$5:D$24))=0,"siempre",IF(LOOKUP(2,1/(P$5:P$24<=D$5:D$24),$A$5:$A$24)>=2046,"nunca",LOOKUP(2,1/(P$5:P$24<=D$5:D$24),$A$5:$A$24)+1)) | E50: =IF(SUMPRODUCT(--(P$5:P$24<=E$5:E$24))=0,"siempre",IF(LOOKUP(2,1/(P$5:P$24<=E$5:E$24),$A$5:$A$24)>=2046,"nunca",LOOKUP(2,1/(P$5:P$24<=E$5:E$24),$A$5:$A$24)+1)) | F50: =IF(SUMPRODUCT(--(P$5:P$24<=F$5:F$24))=0,"siempre",IF(LOOKUP(2,1/(P$5:P$24<=F$5:F$24),$A$5:$A$24)>=2046,"nunca",LOOKUP(2,1/(P$5:P$24<=F$5:F$24),$A$5:$A$24)+1)) | G50: =IF(SUMPRODUCT(--(P$5:P$24<=G$5:G$24))=0,"siempre",IF(LOOKUP(2,1/(P$5:P$24<=G$5:G$24),$A$5:$A$24)>=2046,"nunca",LOOKUP(2,1/(P$5:P$24<=G$5:G$24),$A$5:$A$24)+1)) | H50: =IF(SUMPRODUCT(--(P$5:P$24<=H$5:H$24))=0,"siempre",IF(LOOKUP(2,1/(P$5:P$24<=H$5:H$24),$A$5:$A$24)>=2046,"nunca",LOOKUP(2,1/(P$5:P$24<=H$5:H$24),$A$5:$A$24)+1)) | I50: =IF(SUMPRODUCT(--(P$5:P$24<=I$5:I$24))=0,"siempre",IF(LOOKUP(2,1/(P$5:P$24<=I$5:I$24),$A$5:$A$24)>=2046,"nunca",LOOKUP(2,1/(P$5:P$24<=I$5:I$24),$A$5:$A$24)+1)) | J50: =IF(SUMPRODUCT(--(P$5:P$24<=J$5:J$24))=0,"siempre",IF(LOOKUP(2,1/(P$5:P$24<=J$5:J$24),$A$5:$A$24)>=2046,"nunca",LOOKUP(2,1/(P$5:P$24<=J$5:J$24),$A$5:$A$24)+1)) | K50: =IF(SUMPRODUCT(--(P$5:P$24<=K$5:K$24))=0,"siempre",IF(LOOKUP(2,1/(P$5:P$24<=K$5:K$24),$A$5:$A$24)>=2046,"nunca",LOOKUP(2,1/(P$5:P$24<=K$5:K$24),$A$5:$A$24)+1)) | L50: =IF(SUMPRODUCT(--(P$5:P$24<=L$5:L$24))=0,"siempre",IF(LOOKUP(2,1/(P$5:P$24<=L$5:L$24),$A$5:$A$24)>=2046,"nunca",LOOKUP(2,1/(P$5:P$24<=L$5:L$24),$A$5:$A$24)+1)) | M50: =IF(SUMPRODUCT(--(P$5:P$24<=M$5:M$24))=0,"siempre",IF(LOOKUP(2,1/(P$5:P$24<=M$5:M$24),$A$5:$A$24)>=2046,"nunca",LOOKUP(2,1/(P$5:P$24<=M$5:M$24),$A$5:$A$24)+1)) | N50: =IF(SUMPRODUCT(--(P$5:P$24<=N$5:N$24))=0,"siempre",IF(LOOKUP(2,1/(P$5:P$24<=N$5:N$24),$A$5:$A$24)>=2046,"nunca",LOOKUP(2,1/(P$5:P$24<=N$5:N$24),$A$5:$A$24)+1)) | O50: =IF(SUMPRODUCT(--(P$5:P$24<=O$5:O$24))=0,"siempre",IF(LOOKUP(2,1/(P$5:P$24<=O$5:O$24),$A$5:$A$24)>=2046,"nunca",LOOKUP(2,1/(P$5:P$24<=O$5:O$24),$A$5:$A$24)+1)) | P50: —
A52: Notas
A53: El Excel replica la lógica del dashboard (src/engine.cjs). El test tests/test_excel.py recalcula este libro con LibreOffice y compara el patrimonio con el motor.
A54: Las fechas de las etapas (hojas de cada camino) son valores; el escenario "retraso" del dashboard no las mueve. El Monte Carlo del camino MD solo está en el dashboard.
A55: Para cambiar ubicación, vivienda o escenario usa los selectores en Supuestos!B3:B5.

Sheet Ubic_miami
A1: Miami / Sur de Florida
A2: Seguros muy caros; dúplex escasos y caros; mamá y tía tendrían que mudarse desde DFW.
A3: Licencia compacta: Válida: FL es estado NLC. Ojo: viviendo en FL tu licencia multiestado debería ser de FL (estado de residencia primaria), no la de TX.
A5: Parámetro | B5: Valor | C5: Unidad | D5: Fuente | E5: Confianza | F5: Estimado
A6: Factor salarial RN vs nacional | B6: 0.937 | C6: x | D6: RN Miami-Fort Lauderdale (BLS OEWS 2025 vía Hyring: media $94,990) | E6: media
A7: Factor salarial médico vs nacional | B7: 0.97 | C7: x | D7: Doximity Physician Compensation Report 2026 | E7: baja | F7: sí
A8: Salario PGY-1 2026 | B8: 67400 | C8: $ | D8: Encuesta AAMC 2025 de salarios de residentes por región (vía MedSchoolCoach) | E8: media
A9: Gastos de vida anuales (sin vivienda) | B9: 31000 | C9: $ | D9: Estimación propia del modelo (sin dato publicado directo); ver nota | E9: baja | F9: sí
A10: Renta propia mensual antes de comprar (1 hab.) | B10: 2250 | C10: $ | D10: Estimación propia del modelo (sin dato publicado directo); ver nota | E10: baja | F10: sí
A11: Seguro de vivienda (% del valor/año) | B11: 0.013 | C11: % | D11: Insurance.com 2026: prima promedio FL $8,471; TX $4,582; nacional $2,872 | E11: media | F11: sí
A12: Impuesto a la propiedad efectivo | B12: 0.016 | C12: % | D12: Estimación propia del modelo (sin dato publicado directo); ver nota | E12: baja | F12: sí
A13: Facilidad de match IMG si te limitas a la región | B13: 0.85 | C13: x | D13: Estimación propia del modelo (sin dato publicado directo); ver nota | E13: baja | F13: sí
A14: Renta mensual por unidad rentada (multifamiliar) | B14: 2300 | C14: $ | D14: Estimación propia del modelo (sin dato publicado directo); ver nota | E14: baja | F14: sí
A15: Precio dúplex | B15: 850000 | C15: $ | D15: Miami-Dade unifamiliar mediana $692k (sep-2026, Echo Fine Properties) | E15: baja | F15: sí
A16: Precio casa con in-law suite | B16: 950000 | C16: $ | D16: Miami-Dade unifamiliar mediana $692k (sep-2026, Echo Fine Properties) | E16: baja | F16: sí
A17: Precio dos casas pequeñas (total) | B17: 1150000 | C17: $ | D17: Miami-Dade unifamiliar mediana $692k (sep-2026, Echo Fine Properties) | E17: baja | F17: sí
A18: Precio casa (sin ADU) | B18: 700000 | C18: $ | D18: Miami-Dade unifamiliar mediana $692k (sep-2026, Echo Fine Properties) | E18: media | F18: sí
A19: Costo de construir ADU | B19: 180000 | C19: $ | D19: Estimación propia del modelo (sin dato publicado directo); ver nota | E19: baja | F19: sí
A20: Precio fourplex | B20: 1500000 | C20: $ | D20: Estimación propia del modelo (sin dato publicado directo); ver nota | E20: baja | F20: sí
A21: Impuesto estatal (1=ninguno, 2=Ohio, 3=Nueva York) | B21: 1
A22: Impuesto municipal NYC (1/0) | B22: 0
A24: Cotización de vivienda (precios 2026, escenario activo)
A25: Configuración | B25: Precio | C25: Enganche | D25: Cierre | E25: Préstamo | F25: P&I mensual | G25: Impuesto/mes | H25: Seguro/mes | I25: PMI/mes | J25: Mantenimiento/mes | K25: Renta recibida/mes | L25: PITI | M25: Costo neto/mes | N25: Ingreso bruto anual necesario
A26: Dúplex (yo en una unidad, ellas en la otra) | B26: =ubic_miami_precio_duplex | C26: =B26*vivienda_enganchePct | D26: =B26*vivienda_cierrePct | E26: =B26-C26 | F26: =PMT(g_mortRate/12,vivienda_plazoHipoteca*12,-E26) | G26: =B26*ubic_miami_impuestoPropPct/12 | H26: =B26*ubic_miami_seguroPct/12 | I26: =IF(vivienda_enganchePct<0.2,E26*vivienda_pmiTasa/12,0) | J26: =B26*vivienda_mantenimientoPct/12 | K26: =0*ubic_miami_rentaUnidad*(1-vivienda_vacancia) | L26: =F26+G26+H26+I26 | M26: =L26+J26-K26*(1-vivienda_gestionPct) | N26: =12*MAX(0,L26-0.75*K26)/vivienda_dtiMax
A27: Casa grande con in-law suite | B27: =ubic_miami_precio_inlaw | C27: =B27*vivienda_enganchePct | D27: =B27*vivienda_cierrePct | E27: =B27-C27 | F27: =PMT(g_mortRate/12,vivienda_plazoHipoteca*12,-E27) | G27: =B27*ubic_miami_impuestoPropPct/12 | H27: =B27*ubic_miami_seguroPct/12 | I27: =IF(vivienda_enganchePct<0.2,E27*vivienda_pmiTasa/12,0) | J27: =B27*vivienda_mantenimientoPct/12 | K27: =0*ubic_miami_rentaUnidad*(1-vivienda_vacancia) | L27: =F27+G27+H27+I27 | M27: =L27+J27-K27*(1-vivienda_gestionPct) | N27: =12*MAX(0,L27-0.75*K27)/vivienda_dtiMax
A28: Dos casas pequeñas cercanas | B28: =ubic_miami_precio_dosCasas | C28: =B28*vivienda_enganchePct | D28: =B28*vivienda_cierrePct | E28: =B28-C28 | F28: =PMT(g_mortRate/12,vivienda_plazoHipoteca*12,-E28) | G28: =B28*ubic_miami_impuestoPropPct/12 | H28: =B28*ubic_miami_seguroPct/12 | I28: =IF(vivienda_enganchePct<0.2,E28*vivienda_pmiTasa/12,0) | J28: =B28*vivienda_mantenimientoPct/12 | K28: =0*ubic_miami_rentaUnidad*(1-vivienda_vacancia) | L28: =F28+G28+H28+I28 | M28: =L28+J28-K28*(1-vivienda_gestionPct) | N28: =12*MAX(0,L28-0.75*K28)/vivienda_dtiMax
A29: Casa + ADU construido después | B29: =ubic_miami_precio_casaAdu | C29: =B29*vivienda_enganchePct | D29: =B29*vivienda_cierrePct | E29: =B29-C29 | F29: =PMT(g_mortRate/12,vivienda_plazoHipoteca*12,-E29) | G29: =B29*ubic_miami_impuestoPropPct/12 | H29: =B29*ubic_miami_seguroPct/12 | I29: =IF(vivienda_enganchePct<0.2,E29*vivienda_pmiTasa/12,0) | J29: =B29*vivienda_mantenimientoPct/12 | K29: =0*ubic_miami_rentaUnidad*(1-vivienda_vacancia) | L29: =F29+G29+H29+I29 | M29: =L29+J29-K29*(1-vivienda_gestionPct) | N29: =12*MAX(0,L29-0.75*K29)/vivienda_dtiMax
A30: Multifamiliar 3-4 unidades (rentar 1-2) | B30: =ubic_miami_precio_multi | C30: =B30*vivienda_enganchePct | D30: =B30*vivienda_cierrePct | E30: =B30-C30 | F30: =PMT(g_mortRate/12,vivienda_plazoHipoteca*12,-E30) | G30: =B30*ubic_miami_impuestoPropPct/12 | H30: =B30*ubic_miami_seguroPct/12 | I30: =IF(vivienda_enganchePct<0.2,E30*vivienda_pmiTasa/12,0) | J30: =B30*vivienda_mantenimientoPct/12 | K30: =2*ubic_miami_rentaUnidad*(1-vivienda_vacancia) | L30: =F30+G30+H30+I30 | M30: =L30+J30-K30*(1-vivienda_gestionPct) | N30: =12*MAX(0,L30-0.75*K30)/vivienda_dtiMax

Sheet Ubic_dfw
A1: Dallas–Fort Worth
A2: Donde viven mamá y tía. Sin impuesto estatal; impuesto predial alto (~1.8–2.2%).
A3: Licencia compacta: Válida: tu licencia compacta es de TX; al mudarte TX sería tu estado de residencia (lo ideal).
A5: Parámetro | B5: Valor | C5: Unidad | D5: Fuente | E5: Confianza | F5: Estimado
A6: Factor salarial RN vs nacional | B6: 0.976 | C6: x | D6: RN DFW $101,420 / Houston $99,830 (allnurses, año BLS no claro); DFW 2024 mediana $98,740 | E6: media
A7: Factor salarial médico vs nacional | B7: 1.02 | C7: x | D7: Doximity Physician Compensation Report 2026 | E7: baja | F7: sí
A8: Salario PGY-1 2026 | B8: 67400 | C8: $ | D8: Encuesta AAMC 2025 de salarios de residentes por región (vía MedSchoolCoach) | E8: media
A9: Gastos de vida anuales (sin vivienda) | B9: 28500 | C9: $ | D9: Estimación propia del modelo (sin dato publicado directo); ver nota | E9: baja | F9: sí
A10: Renta propia mensual antes de comprar (1 hab.) | B10: 1400 | C10: $ | D10: Estimación propia del modelo (sin dato publicado directo); ver nota | E10: baja | F10: sí
A11: Seguro de vivienda (% del valor/año) | B11: 0.011 | C11: % | D11: Insurance.com 2026: prima promedio FL $8,471; TX $4,582; nacional $2,872 | E11: media | F11: sí
A12: Impuesto a la propiedad efectivo | B12: 0.019 | C12: % | D12: Impuesto predial efectivo Dallas 1.44–1.85%, Tarrant 1.54–1.80% | E12: media
A13: Facilidad de match IMG si te limitas a la región | B13: 0.9 | C13: x | D13: Estimación propia del modelo (sin dato publicado directo); ver nota | E13: baja | F13: sí
A14: Renta mensual por unidad rentada (multifamiliar) | B14: 1750 | C14: $ | D14: Dúplex DFW: nuevos Midlothian $699k; Fort Worth 2009 $525k (listados) | E14: media | F14: sí
A15: Precio dúplex | B15: 520000 | C15: $ | D15: Dúplex DFW: nuevos Midlothian $699k; Fort Worth 2009 $525k (listados) | E15: media | F15: sí
A16: Precio casa con in-law suite | B16: 560000 | C16: $ | D16: DFW mediana ~$395k (Opendoor, may-2026); $439,990 (Follow Up Ace, jul-2026) | E16: baja | F16: sí
A17: Precio dos casas pequeñas (total) | B17: 640000 | C17: $ | D17: DFW mediana ~$395k (Opendoor, may-2026); $439,990 (Follow Up Ace, jul-2026) | E17: media | F17: sí
A18: Precio casa (sin ADU) | B18: 420000 | C18: $ | D18: DFW mediana ~$395k (Opendoor, may-2026); $439,990 (Follow Up Ace, jul-2026) | E18: media | F18: sí
A19: Costo de construir ADU | B19: 140000 | C19: $ | D19: Estimación propia del modelo (sin dato publicado directo); ver nota | E19: baja | F19: sí
A20: Precio fourplex | B20: 900000 | C20: $ | D20: Estimación propia del modelo (sin dato publicado directo); ver nota | E20: baja | F20: sí
A21: Impuesto estatal (1=ninguno, 2=Ohio, 3=Nueva York) | B21: 1
A22: Impuesto municipal NYC (1/0) | B22: 0
A24: Cotización de vivienda (precios 2026, escenario activo)
A25: Configuración | B25: Precio | C25: Enganche | D25: Cierre | E25: Préstamo | F25: P&I mensual | G25: Impuesto/mes | H25: Seguro/mes | I25: PMI/mes | J25: Mantenimiento/mes | K25: Renta recibida/mes | L25: PITI | M25: Costo neto/mes | N25: Ingreso bruto anual necesario
A26: Dúplex (yo en una unidad, ellas en la otra) | B26: =ubic_dfw_precio_duplex | C26: =B26*vivienda_enganchePct | D26: =B26*vivienda_cierrePct | E26: =B26-C26 | F26: =PMT(g_mortRate/12,vivienda_plazoHipoteca*12,-E26) | G26: =B26*ubic_dfw_impuestoPropPct/12 | H26: =B26*ubic_dfw_seguroPct/12 | I26: =IF(vivienda_enganchePct<0.2,E26*vivienda_pmiTasa/12,0) | J26: =B26*vivienda_mantenimientoPct/12 | K26: =0*ubic_dfw_rentaUnidad*(1-vivienda_vacancia) | L26: =F26+G26+H26+I26 | M26: =L26+J26-K26*(1-vivienda_gestionPct) | N26: =12*MAX(0,L26-0.75*K26)/vivienda_dtiMax
A27: Casa grande con in-law suite | B27: =ubic_dfw_precio_inlaw | C27: =B27*vivienda_enganchePct | D27: =B27*vivienda_cierrePct | E27: =B27-C27 | F27: =PMT(g_mortRate/12,vivienda_plazoHipoteca*12,-E27) | G27: =B27*ubic_dfw_impuestoPropPct/12 | H27: =B27*ubic_dfw_seguroPct/12 | I27: =IF(vivienda_enganchePct<0.2,E27*vivienda_pmiTasa/12,0) | J27: =B27*vivienda_mantenimientoPct/12 | K27: =0*ubic_dfw_rentaUnidad*(1-vivienda_vacancia) | L27: =F27+G27+H27+I27 | M27: =L27+J27-K27*(1-vivienda_gestionPct) | N27: =12*MAX(0,L27-0.75*K27)/vivienda_dtiMax
A28: Dos casas pequeñas cercanas | B28: =ubic_dfw_precio_dosCasas | C28: =B28*vivienda_enganchePct | D28: =B28*vivienda_cierrePct | E28: =B28-C28 | F28: =PMT(g_mortRate/12,vivienda_plazoHipoteca*12,-E28) | G28: =B28*ubic_dfw_impuestoPropPct/12 | H28: =B28*ubic_dfw_seguroPct/12 | I28: =IF(vivienda_enganchePct<0.2,E28*vivienda_pmiTasa/12,0) | J28: =B28*vivienda_mantenimientoPct/12 | K28: =0*ubic_dfw_rentaUnidad*(1-vivienda_vacancia) | L28: =F28+G28+H28+I28 | M28: =L28+J28-K28*(1-vivienda_gestionPct) | N28: =12*MAX(0,L28-0.75*K28)/vivienda_dtiMax
A29: Casa + ADU construido después | B29: =ubic_dfw_precio_casaAdu | C29: =B29*vivienda_enganchePct | D29: =B29*vivienda_cierrePct | E29: =B29-C29 | F29: =PMT(g_mortRate/12,vivienda_plazoHipoteca*12,-E29) | G29: =B29*ubic_dfw_impuestoPropPct/12 | H29: =B29*ubic_dfw_seguroPct/12 | I29: =IF(vivienda_enganchePct<0.2,E29*vivienda_pmiTasa/12,0) | J29: =B29*vivienda_mantenimientoPct/12 | K29: =0*ubic_dfw_rentaUnidad*(1-vivienda_vacancia) | L29: =F29+G29+H29+I29 | M29: =L29+J29-K29*(1-vivienda_gestionPct) | N29: =12*MAX(0,L29-0.75*K29)/vivienda_dtiMax
A30: Multifamiliar 3-4 unidades (rentar 1-2) | B30: =ubic_dfw_precio_multi | C30: =B30*vivienda_enganchePct | D30: =B30*vivienda_cierrePct | E30: =B30-C30 | F30: =PMT(g_mortRate/12,vivienda_plazoHipoteca*12,-E30) | G30: =B30*ubic_dfw_impuestoPropPct/12 | H30: =B30*ubic_dfw_seguroPct/12 | I30: =IF(vivienda_enganchePct<0.2,E30*vivienda_pmiTasa/12,0) | J30: =B30*vivienda_mantenimientoPct/12 | K30: =2*ubic_dfw_rentaUnidad*(1-vivienda_vacancia) | L30: =F30+G30+H30+I30 | M30: =L30+J30-K30*(1-vivienda_gestionPct) | N30: =12*MAX(0,L30-0.75*K30)/vivienda_dtiMax

Sheet Ubic_houston
A1: Houston
A2: TX sin impuesto estatal, Texas Medical Center (muchos programas y empleos RN), vivienda más barata que DFW; ~4 h de mamá y tía. Riesgo de huracán/inundación.
A3: Licencia compacta: Válida: licencia compacta TX.
A5: Parámetro | B5: Valor | C5: Unidad | D5: Fuente | E5: Confianza | F5: Estimado
A6: Factor salarial RN vs nacional | B6: 0.984 | C6: x | D6: RN DFW $101,420 / Houston $99,830 (allnurses, año BLS no claro); DFW 2024 mediana $98,740 | E6: media
A7: Factor salarial médico vs nacional | B7: 1.02 | C7: x | D7: Doximity Physician Compensation Report 2026 | E7: baja | F7: sí
A8: Salario PGY-1 2026 | B8: 67400 | C8: $ | D8: Encuesta AAMC 2025 de salarios de residentes por región (vía MedSchoolCoach) | E8: media
A9: Gastos de vida anuales (sin vivienda) | B9: 28000 | C9: $ | D9: Estimación propia del modelo (sin dato publicado directo); ver nota | E9: baja | F9: sí
A10: Renta propia mensual antes de comprar (1 hab.) | B10: 1300 | C10: $ | D10: Estimación propia del modelo (sin dato publicado directo); ver nota | E10: baja | F10: sí
A11: Seguro de vivienda (% del valor/año) | B11: 0.012 | C11: % | D11: Insurance.com 2026: prima promedio FL $8,471; TX $4,582; nacional $2,872 | E11: media | F11: sí
A12: Impuesto a la propiedad efectivo | B12: 0.02 | C12: % | D12: Estimación propia del modelo (sin dato publicado directo); ver nota | E12: media | F12: sí
A13: Facilidad de match IMG si te limitas a la región | B13: 0.95 | C13: x | D13: Estimación propia del modelo (sin dato publicado directo); ver nota | E13: baja | F13: sí
A14: Renta mensual por unidad rentada (multifamiliar) | B14: 1600 | C14: $ | D14: Estimación propia del modelo (sin dato publicado directo); ver nota | E14: baja | F14: sí
A15: Precio dúplex | B15: 460000 | C15: $ | D15: Houston (HAR) mediana unifamiliar ~$345k (jun-2026) | E15: baja | F15: sí
A16: Precio casa con in-law suite | B16: 500000 | C16: $ | D16: Houston (HAR) mediana unifamiliar ~$345k (jun-2026) | E16: baja | F16: sí
A17: Precio dos casas pequeñas (total) | B17: 580000 | C17: $ | D17: Houston (HAR) mediana unifamiliar ~$345k (jun-2026) | E17: media | F17: sí
A18: Precio casa (sin ADU) | B18: 380000 | C18: $ | D18: Houston (HAR) mediana unifamiliar ~$345k (jun-2026) | E18: media | F18: sí
A19: Costo de construir ADU | B19: 130000 | C19: $ | D19: Estimación propia del modelo (sin dato publicado directo); ver nota | E19: baja | F19: sí
A20: Precio fourplex | B20: 800000 | C20: $ | D20: Estimación propia del modelo (sin dato publicado directo); ver nota | E20: baja | F20: sí
A21: Impuesto estatal (1=ninguno, 2=Ohio, 3=Nueva York) | B21: 1
A22: Impuesto municipal NYC (1/0) | B22: 0
A24: Cotización de vivienda (precios 2026, escenario activo)
A25: Configuración | B25: Precio | C25: Enganche | D25: Cierre | E25: Préstamo | F25: P&I mensual | G25: Impuesto/mes | H25: Seguro/mes | I25: PMI/mes | J25: Mantenimiento/mes | K25: Renta recibida/mes | L25: PITI | M25: Costo neto/mes | N25: Ingreso bruto anual necesario
A26: Dúplex (yo en una unidad, ellas en la otra) | B26: =ubic_houston_precio_duplex | C26: =B26*vivienda_enganchePct | D26: =B26*vivienda_cierrePct | E26: =B26-C26 | F26: =PMT(g_mortRate/12,vivienda_plazoHipoteca*12,-E26) | G26: =B26*ubic_houston_impuestoPropPct/12 | H26: =B26*ubic_houston_seguroPct/12 | I26: =IF(vivienda_enganchePct<0.2,E26*vivienda_pmiTasa/12,0) | J26: =B26*vivienda_mantenimientoPct/12 | K26: =0*ubic_houston_rentaUnidad*(1-vivienda_vacancia) | L26: =F26+G26+H26+I26 | M26: =L26+J26-K26*(1-vivienda_gestionPct) | N26: =12*MAX(0,L26-0.75*K26)/vivienda_dtiMax
A27: Casa grande con in-law suite | B27: =ubic_houston_precio_inlaw | C27: =B27*vivienda_enganchePct | D27: =B27*vivienda_cierrePct | E27: =B27-C27 | F27: =PMT(g_mortRate/12,vivienda_plazoHipoteca*12,-E27) | G27: =B27*ubic_houston_impuestoPropPct/12 | H27: =B27*ubic_houston_seguroPct/12 | I27: =IF(vivienda_enganchePct<0.2,E27*vivienda_pmiTasa/12,0) | J27: =B27*vivienda_mantenimientoPct/12 | K27: =0*ubic_houston_rentaUnidad*(1-vivienda_vacancia) | L27: =F27+G27+H27+I27 | M27: =L27+J27-K27*(1-vivienda_gestionPct) | N27: =12*MAX(0,L27-0.75*K27)/vivienda_dtiMax
A28: Dos casas pequeñas cercanas | B28: =ubic_houston_precio_dosCasas | C28: =B28*vivienda_enganchePct | D28: =B28*vivienda_cierrePct | E28: =B28-C28 | F28: =PMT(g_mortRate/12,vivienda_plazoHipoteca*12,-E28) | G28: =B28*ubic_houston_impuestoPropPct/12 | H28: =B28*ubic_houston_seguroPct/12 | I28: =IF(vivienda_enganchePct<0.2,E28*vivienda_pmiTasa/12,0) | J28: =B28*vivienda_mantenimientoPct/12 | K28: =0*ubic_houston_rentaUnidad*(1-vivienda_vacancia) | L28: =F28+G28+H28+I28 | M28: =L28+J28-K28*(1-vivienda_gestionPct) | N28: =12*MAX(0,L28-0.75*K28)/vivienda_dtiMax
A29: Casa + ADU construido después | B29: =ubic_houston_precio_casaAdu | C29: =B29*vivienda_enganchePct | D29: =B29*vivienda_cierrePct | E29: =B29-C29 | F29: =PMT(g_mortRate/12,vivienda_plazoHipoteca*12,-E29) | G29: =B29*ubic_houston_impuestoPropPct/12 | H29: =B29*ubic_houston_seguroPct/12 | I29: =IF(vivienda_enganchePct<0.2,E29*vivienda_pmiTasa/12,0) | J29: =B29*vivienda_mantenimientoPct/12 | K29: =0*ubic_houston_rentaUnidad*(1-vivienda_vacancia) | L29: =F29+G29+H29+I29 | M29: =L29+J29-K29*(1-vivienda_gestionPct) | N29: =12*MAX(0,L29-0.75*K29)/vivienda_dtiMax
A30: Multifamiliar 3-4 unidades (rentar 1-2) | B30: =ubic_houston_precio_multi | C30: =B30*vivienda_enganchePct | D30: =B30*vivienda_cierrePct | E30: =B30-C30 | F30: =PMT(g_mortRate/12,vivienda_plazoHipoteca*12,-E30) | G30: =B30*ubic_houston_impuestoPropPct/12 | H30: =B30*ubic_houston_seguroPct/12 | I30: =IF(vivienda_enganchePct<0.2,E30*vivienda_pmiTasa/12,0) | J30: =B30*vivienda_mantenimientoPct/12 | K30: =2*ubic_houston_rentaUnidad*(1-vivienda_vacancia) | L30: =F30+G30+H30+I30 | M30: =L30+J30-K30*(1-vivienda_gestionPct) | N30: =12*MAX(0,L30-0.75*K30)/vivienda_dtiMax

Sheet Ubic_nyc
A1: Nueva York (Queens/Bronx)
A2: El estado con más puestos de IM para IMGs (37% non-US IMG). Salarios RN altos pero impuestos estatal+municipal y vivienda muy caros.
A3: Licencia compacta: NO válida: NY no pertenece al NLC. Necesitas licencia RN de NY por endoso (trámite de semanas).
A5: Parámetro | B5: Valor | C5: Unidad | D5: Fuente | E5: Confianza | F5: Estimado
A6: Factor salarial RN vs nacional | B6: 1.179 | C6: x | D6: RN New York-Newark-Jersey City (OEWS mayo 2025 vía Wagedex/Hyring: ~$119,600) | E6: media
A7: Factor salarial médico vs nacional | B7: 0.93 | C7: x | D7: Doximity Physician Compensation Report 2026 | E7: baja | F7: sí
A8: Salario PGY-1 2026 | B8: 80000 | C8: $ | D8: Encuesta AAMC 2025 de salarios de residentes por región (vía MedSchoolCoach) | E8: media
A9: Gastos de vida anuales (sin vivienda) | B9: 30000 | C9: $ | D9: Estimación propia del modelo (sin dato publicado directo); ver nota | E9: baja | F9: sí
A10: Renta propia mensual antes de comprar (1 hab.) | B10: 2600 | C10: $ | D10: Estimación propia del modelo (sin dato publicado directo); ver nota | E10: baja | F10: sí
A11: Seguro de vivienda (% del valor/año) | B11: 0.003 | C11: % | D11: Insurance.com 2026: prima promedio FL $8,471; TX $4,582; nacional $2,872 | E11: baja | F11: sí
A12: Impuesto a la propiedad efectivo | B12: 0.009 | C12: % | D12: Estimación propia del modelo (sin dato publicado directo); ver nota | E12: baja | F12: sí
A13: Facilidad de match IMG si te limitas a la región | B13: 1.25 | C13: x | D13: % de puestos IM PGY-1 2026 ocupados por non-US IMG por estado (NY 37.4%, NJ 42.4%, PA 33.4%) | E13: media | F13: sí
A14: Renta mensual por unidad rentada (multifamiliar) | B14: 2600 | C14: $ | D14: Estimación propia del modelo (sin dato publicado directo); ver nota | E14: baja | F14: sí
A15: Precio casa bifamiliar | B15: 1250000 | C15: $ | D15: Estimación propia del modelo (sin dato publicado directo); ver nota | E15: baja | F15: sí
A16: Precio casa con in-law suite | B16: 1150000 | C16: $ | D16: Estimación propia del modelo (sin dato publicado directo); ver nota | E16: baja | F16: sí
A17: Precio dos casas pequeñas (total) | B17: 1900000 | C17: $ | D17: Estimación propia del modelo (sin dato publicado directo); ver nota | E17: baja | F17: sí
A18: Precio casa (sin ADU) | B18: 950000 | C18: $ | D18: Estimación propia del modelo (sin dato publicado directo); ver nota | E18: baja | F18: sí
A19: Costo de construir ADU | B19: 250000 | C19: $ | D19: Estimación propia del modelo (sin dato publicado directo); ver nota | E19: baja | F19: sí
A20: Precio 3-4 familias | B20: 1800000 | C20: $ | D20: Estimación propia del modelo (sin dato publicado directo); ver nota | E20: baja | F20: sí
A21: Impuesto estatal (1=ninguno, 2=Ohio, 3=Nueva York) | B21: 3
A22: Impuesto municipal NYC (1/0) | B22: 1
A24: Cotización de vivienda (precios 2026, escenario activo)
A25: Configuración | B25: Precio | C25: Enganche | D25: Cierre | E25: Préstamo | F25: P&I mensual | G25: Impuesto/mes | H25: Seguro/mes | I25: PMI/mes | J25: Mantenimiento/mes | K25: Renta recibida/mes | L25: PITI | M25: Costo neto/mes | N25: Ingreso bruto anual necesario
A26: Dúplex (yo en una unidad, ellas en la otra) | B26: =ubic_nyc_precio_duplex | C26: =B26*vivienda_enganchePct | D26: =B26*vivienda_cierrePct | E26: =B26-C26 | F26: =PMT(g_mortRate/12,vivienda_plazoHipoteca*12,-E26) | G26: =B26*ubic_nyc_impuestoPropPct/12 | H26: =B26*ubic_nyc_seguroPct/12 | I26: =IF(vivienda_enganchePct<0.2,E26*vivienda_pmiTasa/12,0) | J26: =B26*vivienda_mantenimientoPct/12 | K26: =0*ubic_nyc_rentaUnidad*(1-vivienda_vacancia) | L26: =F26+G26+H26+I26 | M26: =L26+J26-K26*(1-vivienda_gestionPct) | N26: =12*MAX(0,L26-0.75*K26)/vivienda_dtiMax
A27: Casa grande con in-law suite | B27: =ubic_nyc_precio_inlaw | C27: =B27*vivienda_enganchePct | D27: =B27*vivienda_cierrePct | E27: =B27-C27 | F27: =PMT(g_mortRate/12,vivienda_plazoHipoteca*12,-E27) | G27: =B27*ubic_nyc_impuestoPropPct/12 | H27: =B27*ubic_nyc_seguroPct/12 | I27: =IF(vivienda_enganchePct<0.2,E27*vivienda_pmiTasa/12,0) | J27: =B27*vivienda_mantenimientoPct/12 | K27: =0*ubic_nyc_rentaUnidad*(1-vivienda_vacancia) | L27: =F27+G27+H27+I27 | M27: =L27+J27-K27*(1-vivienda_gestionPct) | N27: =12*MAX(0,L27-0.75*K27)/vivienda_dtiMax
A28: Dos casas pequeñas cercanas | B28: =ubic_nyc_precio_dosCasas | C28: =B28*vivienda_enganchePct | D28: =B28*vivienda_cierrePct | E28: =B28-C28 | F28: =PMT(g_mortRate/12,vivienda_plazoHipoteca*12,-E28) | G28: =B28*ubic_nyc_impuestoPropPct/12 | H28: =B28*ubic_nyc_seguroPct/12 | I28: =IF(vivienda_enganchePct<0.2,E28*vivienda_pmiTasa/12,0) | J28: =B28*vivienda_mantenimientoPct/12 | K28: =0*ubic_nyc_rentaUnidad*(1-vivienda_vacancia) | L28: =F28+G28+H28+I28 | M28: =L28+J28-K28*(1-vivienda_gestionPct) | N28: =12*MAX(0,L28-0.75*K28)/vivienda_dtiMax
A29: Casa + ADU construido después | B29: =ubic_nyc_precio_casaAdu | C29: =B29*vivienda_enganchePct | D29: =B29*vivienda_cierrePct | E29: =B29-C29 | F29: =PMT(g_mortRate/12,vivienda_plazoHipoteca*12,-E29) | G29: =B29*ubic_nyc_impuestoPropPct/12 | H29: =B29*ubic_nyc_seguroPct/12 | I29: =IF(vivienda_enganchePct<0.2,E29*vivienda_pmiTasa/12,0) | J29: =B29*vivienda_mantenimientoPct/12 | K29: =0*ubic_nyc_rentaUnidad*(1-vivienda_vacancia) | L29: =F29+G29+H29+I29 | M29: =L29+J29-K29*(1-vivienda_gestionPct) | N29: =12*MAX(0,L29-0.75*K29)/vivienda_dtiMax
A30: Multifamiliar 3-4 unidades (rentar 1-2) | B30: =ubic_nyc_precio_multi | C30: =B30*vivienda_enganchePct | D30: =B30*vivienda_cierrePct | E30: =B30-C30 | F30: =PMT(g_mortRate/12,vivienda_plazoHipoteca*12,-E30) | G30: =B30*ubic_nyc_impuestoPropPct/12 | H30: =B30*ubic_nyc_seguroPct/12 | I30: =IF(vivienda_enganchePct<0.2,E30*vivienda_pmiTasa/12,0) | J30: =B30*vivienda_mantenimientoPct/12 | K30: =2*ubic_nyc_rentaUnidad*(1-vivienda_vacancia) | L30: =F30+G30+H30+I30 | M30: =L30+J30-K30*(1-vivienda_gestionPct) | N30: =12*MAX(0,L30-0.75*K30)/vivienda_dtiMax

Sheet Ubic_cleveland
A1: Cleveland / NE de Ohio
A2: Vivienda muy barata, Cleveland Clinic/UH/MetroHealth, muchos programas comunitarios de IM amigables con IMGs en OH/MI/PA. Invierno duro, lejos de la familia.
A3: Licencia compacta: Válida: Ohio es miembro del NLC (implementado 2023). Al mudarte, Ohio sería tu estado de residencia.
A5: Parámetro | B5: Valor | C5: Unidad | D5: Fuente | E5: Confianza | F5: Estimado
A6: Factor salarial RN vs nacional | B6: 0.868 | C6: x | D6: RN Cleveland (OEWS mayo 2025 vía DegreeCalc: mediana $83,940) | E6: media | F6: sí
A7: Factor salarial médico vs nacional | B7: 1.03 | C7: x | D7: Doximity Physician Compensation Report 2026 | E7: baja | F7: sí
A8: Salario PGY-1 2026 | B8: 71000 | C8: $ | D8: Encuesta AAMC 2025 de salarios de residentes por región (vía MedSchoolCoach) | E8: media
A9: Gastos de vida anuales (sin vivienda) | B9: 25500 | C9: $ | D9: Estimación propia del modelo (sin dato publicado directo); ver nota | E9: baja | F9: sí
A10: Renta propia mensual antes de comprar (1 hab.) | B10: 1100 | C10: $ | D10: Estimación propia del modelo (sin dato publicado directo); ver nota | E10: baja | F10: sí
A11: Seguro de vivienda (% del valor/año) | B11: 0.006 | C11: % | D11: Insurance.com 2026: prima promedio FL $8,471; TX $4,582; nacional $2,872 | E11: baja | F11: sí
A12: Impuesto a la propiedad efectivo | B12: 0.0172 | C12: % | D12: Cuyahoga County mediana venta ~$225k (Zillow jun-2026); ATTOM impuesto efectivo 1.72% | E12: media
A13: Facilidad de match IMG si te limitas a la región | B13: 1.15 | C13: x | D13: Estimación propia del modelo (sin dato publicado directo); ver nota | E13: baja | F13: sí
A14: Renta mensual por unidad rentada (multifamiliar) | B14: 1100 | C14: $ | D14: Estimación propia del modelo (sin dato publicado directo); ver nota | E14: baja | F14: sí
A15: Precio dúplex ('up-down double') | B15: 260000 | C15: $ | D15: Cuyahoga County mediana venta ~$225k (Zillow jun-2026); ATTOM impuesto efectivo 1.72% | E15: baja | F15: sí
A16: Precio casa con in-law suite | B16: 340000 | C16: $ | D16: Cuyahoga County mediana venta ~$225k (Zillow jun-2026); ATTOM impuesto efectivo 1.72% | E16: baja | F16: sí
A17: Precio dos casas pequeñas (total) | B17: 400000 | C17: $ | D17: Cuyahoga County mediana venta ~$225k (Zillow jun-2026); ATTOM impuesto efectivo 1.72% | E17: media | F17: sí
A18: Precio casa (sin ADU) | B18: 240000 | C18: $ | D18: Cuyahoga County mediana venta ~$225k (Zillow jun-2026); ATTOM impuesto efectivo 1.72% | E18: media | F18: sí
A19: Costo de construir ADU | B19: 120000 | C19: $ | D19: Estimación propia del modelo (sin dato publicado directo); ver nota | E19: baja | F19: sí
A20: Precio fourplex | B20: 420000 | C20: $ | D20: Estimación propia del modelo (sin dato publicado directo); ver nota | E20: baja | F20: sí
A21: Impuesto estatal (1=ninguno, 2=Ohio, 3=Nueva York) | B21: 2
A22: Impuesto municipal NYC (1/0) | B22: 0
A24: Cotización de vivienda (precios 2026, escenario activo)
A25: Configuración | B25: Precio | C25: Enganche | D25: Cierre | E25: Préstamo | F25: P&I mensual | G25: Impuesto/mes | H25: Seguro/mes | I25: PMI/mes | J25: Mantenimiento/mes | K25: Renta recibida/mes | L25: PITI | M25: Costo neto/mes | N25: Ingreso bruto anual necesario
A26: Dúplex (yo en una unidad, ellas en la otra) | B26: =ubic_cleveland_precio_duplex | C26: =B26*vivienda_enganchePct | D26: =B26*vivienda_cierrePct | E26: =B26-C26 | F26: =PMT(g_mortRate/12,vivienda_plazoHipoteca*12,-E26) | G26: =B26*ubic_cleveland_impuestoPropPct/12 | H26: =B26*ubic_cleveland_seguroPct/12 | I26: =IF(vivienda_enganchePct<0.2,E26*vivienda_pmiTasa/12,0) | J26: =B26*vivienda_mantenimientoPct/12 | K26: =0*ubic_cleveland_rentaUnidad*(1-vivienda_vacancia) | L26: =F26+G26+H26+I26 | M26: =L26+J26-K26*(1-vivienda_gestionPct) | N26: =12*MAX(0,L26-0.75*K26)/vivienda_dtiMax
A27: Casa grande con in-law suite | B27: =ubic_cleveland_precio_inlaw | C27: =B27*vivienda_enganchePct | D27: =B27*vivienda_cierrePct | E27: =B27-C27 | F27: =PMT(g_mortRate/12,vivienda_plazoHipoteca*12,-E27) | G27: =B27*ubic_cleveland_impuestoPropPct/12 | H27: =B27*ubic_cleveland_seguroPct/12 | I27: =IF(vivienda_enganchePct<0.2,E27*vivienda_pmiTasa/12,0) | J27: =B27*vivienda_mantenimientoPct/12 | K27: =0*ubic_cleveland_rentaUnidad*(1-vivienda_vacancia) | L27: =F27+G27+H27+I27 | M27: =L27+J27-K27*(1-vivienda_gestionPct) | N27: =12*MAX(0,L27-0.75*K27)/vivienda_dtiMax
A28: Dos casas pequeñas cercanas | B28: =ubic_cleveland_precio_dosCasas | C28: =B28*vivienda_enganchePct | D28: =B28*vivienda_cierrePct | E28: =B28-C28 | F28: =PMT(g_mortRate/12,vivienda_plazoHipoteca*12,-E28) | G28: =B28*ubic_cleveland_impuestoPropPct/12 | H28: =B28*ubic_cleveland_seguroPct/12 | I28: =IF(vivienda_enganchePct<0.2,E28*vivienda_pmiTasa/12,0) | J28: =B28*vivienda_mantenimientoPct/12 | K28: =0*ubic_cleveland_rentaUnidad*(1-vivienda_vacancia) | L28: =F28+G28+H28+I28 | M28: =L28+J28-K28*(1-vivienda_gestionPct) | N28: =12*MAX(0,L28-0.75*K28)/vivienda_dtiMax
A29: Casa + ADU construido después | B29: =ubic_cleveland_precio_casaAdu | C29: =B29*vivienda_enganchePct | D29: =B29*vivienda_cierrePct | E29: =B29-C29 | F29: =PMT(g_mortRate/12,vivienda_plazoHipoteca*12,-E29) | G29: =B29*ubic_cleveland_impuestoPropPct/12 | H29: =B29*ubic_cleveland_seguroPct/12 | I29: =IF(vivienda_enganchePct<0.2,E29*vivienda_pmiTasa/12,0) | J29: =B29*vivienda_mantenimientoPct/12 | K29: =0*ubic_cleveland_rentaUnidad*(1-vivienda_vacancia) | L29: =F29+G29+H29+I29 | M29: =L29+J29-K29*(1-vivienda_gestionPct) | N29: =12*MAX(0,L29-0.75*K29)/vivienda_dtiMax
A30: Multifamiliar 3-4 unidades (rentar 1-2) | B30: =ubic_cleveland_precio_multi | C30: =B30*vivienda_enganchePct | D30: =B30*vivienda_cierrePct | E30: =B30-C30 | F30: =PMT(g_mortRate/12,vivienda_plazoHipoteca*12,-E30) | G30: =B30*ubic_cleveland_impuestoPropPct/12 | H30: =B30*ubic_cleveland_seguroPct/12 | I30: =IF(vivienda_enganchePct<0.2,E30*vivienda_pmiTasa/12,0) | J30: =B30*vivienda_mantenimientoPct/12 | K30: =2*ubic_cleveland_rentaUnidad*(1-vivienda_vacancia) | L30: =F30+G30+H30+I30 | M30: =L30+J30-K30*(1-vivienda_gestionPct) | N30: =12*MAX(0,L30-0.75*K30)/vivienda_dtiMax

Sheet A1 cm_ur
A1: A1 · Case mgmt → UR payer-side (remoto)
A2: Etapas (celdas azules editables; fechas decimales: 2027.67 = sep-2027). Traslape por año en columnas T→AM. Hitos con costo en AN→AP.
A4: Etapa | B4: Inicio | C4: Fin | D4: Rol | E4: Salario base FT 2026 ($) | F4: Aumento anual | G4: Horas (FTE) | H4: Multiplicador | I4: Bono al inicio | J4: Matrícula total (2026$) | K4: Estudio (1/0) | L4: PSLF (1/0) | M4: Match 403b (1/0) | N4: Travel (1/0) | O4: % stipend libre | P4: S-corp anual base | Q4: Autoempleo anual base | R4: Attending (1/0) | T4: 2027 | U4: 2028 | V4: 2029 | W4: 2030 | X4: 2031 | Y4: 2032 | Z4: 2033 | AA4: 2034 | AB4: 2035 | AC4: 2036 | AD4: 2037 | AE4: 2038 | AF4: 2039 | AG4: 2040 | AH4: 2041 | AI4: 2042 | AJ4: 2043 | AK4: 2044 | AL4: 2045 | AM4: 2046 | AN4: Hito | AO4: Fecha | AP4: Costo (2026$)
A5: Case manager RN (cursando BSN) | B5: 2027 | C5: 2027.5 | D5: cm | E5: =personal_tarifaHora*2080*loc_factorRN/ubic_miami_factorRN | F5: =roles_cm_aumento | G5: =personal_horasSemana/40 | H5: 1 | I5: 0 | J5: 0 | K5: 0 | L5: 1 | M5: 1 | N5: 0 | O5: 0 | P5: 0 | Q5: 0 | R5: 0 | T5: =MAX(0,MIN($C5,T$4+1)-MAX($B5,T$4)) | U5: =MAX(0,MIN($C5,U$4+1)-MAX($B5,U$4)) | V5: =MAX(0,MIN($C5,V$4+1)-MAX($B5,V$4)) | W5: =MAX(0,MIN($C5,W$4+1)-MAX($B5,W$4)) | X5: =MAX(0,MIN($C5,X$4+1)-MAX($B5,X$4)) | Y5: =MAX(0,MIN($C5,Y$4+1)-MAX($B5,Y$4)) | Z5: =MAX(0,MIN($C5,Z$4+1)-MAX($B5,Z$4)) | AA5: =MAX(0,MIN($C5,AA$4+1)-MAX($B5,AA$4)) | ... AM5: =MAX(0,MIN($C5,AM$4+1)-MAX($B5,AM$4)) | AN5: Graduación RN-BSN | AO5: 2027.5 | AP5: 0
A6: Case manager RN (BSN) | B6: 2027.5 | C6: 2028 | D6: cm | E6: =personal_tarifaHora*2080*loc_factorRN/ubic_miami_factorRN | F6: =roles_cm_aumento | G6: =personal_horasSemana/40 | H6: =1+personal_bsnAumento | I6: 0 | J6: 0 | K6: 0 | L6: 1 | M6: 1 | N6: 0 | O6: 0 | P6: 0 | Q6: 0 | R6: 0 | T6: =MAX(0,MIN($C6,T$4+1)-MAX($B6,T$4)) | U6: =MAX(0,MIN($C6,U$4+1)-MAX($B6,U$4)) | V6: =MAX(0,MIN($C6,V$4+1)-MAX($B6,V$4)) | W6: =MAX(0,MIN($C6,W$4+1)-MAX($B6,W$4)) | X6: =MAX(0,MIN($C6,X$4+1)-MAX($B6,X$4)) | Y6: =MAX(0,MIN($C6,Y$4+1)-MAX($B6,Y$4)) | Z6: =MAX(0,MIN($C6,Z$4+1)-MAX($B6,Z$4)) | AA6: =MAX(0,MIN($C6,AA$4+1)-MAX($B6,AA$4)) | ... AM6: =MAX(0,MIN($C6,AM$4+1)-MAX($B6,AM$4)) | AN6: Matrícula restante BSN | AO6: 2027 | AP6: =personal_bsnCostoRestante
A7: Utilization review / payer-side (CVS/Aetna) | B7: 2028 | C7: 2048 | D7: ur | E7: =roles_ur_base*(1+(loc_factorRN-1)*0.5) | F7: =roles_ur_aumento | G7: 1 | H7: 1 | I7: 0 | J7: 0 | K7: 0 | L7: 0 | M7: 1 | N7: 0 | O7: 0 | P7: 0 | Q7: 0 | R7: 0 | T7: =MAX(0,MIN($C7,T$4+1)-MAX($B7,T$4)) | U7: =MAX(0,MIN($C7,U$4+1)-MAX($B7,U$4)) | V7: =MAX(0,MIN($C7,V$4+1)-MAX($B7,V$4)) | W7: =MAX(0,MIN($C7,W$4+1)-MAX($B7,W$4)) | X7: =MAX(0,MIN($C7,X$4+1)-MAX($B7,X$4)) | Y7: =MAX(0,MIN($C7,Y$4+1)-MAX($B7,Y$4)) | Z7: =MAX(0,MIN($C7,Z$4+1)-MAX($B7,Z$4)) | AA7: =MAX(0,MIN($C7,AA$4+1)-MAX($B7,AA$4)) | ... AM7: =MAX(0,MIN($C7,AM$4+1)-MAX($B7,AM$4)) | AN7: Empieza UR payer-side | AO7: 2028 | AP7: 0
B8: 0 | C8: 0 | E8: 0 | F8: 0 | G8: 0 | H8: 0 | I8: 0 | J8: 0 | K8: 0 | L8: 0 | M8: 0 | N8: 0 | O8: 0 | P8: 0 | Q8: 0 | R8: 0 | T8: =MAX(0,MIN($C8,T$4+1)-MAX($B8,T$4)) | U8: =MAX(0,MIN($C8,U$4+1)-MAX($B8,U$4)) | V8: =MAX(0,MIN($C8,V$4+1)-MAX($B8,V$4)) | W8: =MAX(0,MIN($C8,W$4+1)-MAX($B8,W$4)) | X8: =MAX(0,MIN($C8,X$4+1)-MAX($B8,X$4)) | Y8: =MAX(0,MIN($C8,Y$4+1)-MAX($B8,Y$4)) | Z8: =MAX(0,MIN($C8,Z$4+1)-MAX($B8,Z$4)) | AA8: =MAX(0,MIN($C8,AA$4+1)-MAX($B8,AA$4)) | ... AM8: =MAX(0,MIN($C8,AM$4+1)-MAX($B8,AM$4)) | AO8: 0 | AP8: 0
B9: 0 | C9: 0 | E9: 0 | F9: 0 | G9: 0 | H9: 0 | I9: 0 | J9: 0 | K9: 0 | L9: 0 | M9: 0 | N9: 0 | O9: 0 | P9: 0 | Q9: 0 | R9: 0 | T9: =MAX(0,MIN($C9,T$4+1)-MAX($B9,T$4)) | U9: =MAX(0,MIN($C9,U$4+1)-MAX($B9,U$4)) | V9: =MAX(0,MIN($C9,V$4+1)-MAX($B9,V$4)) | W9: =MAX(0,MIN($C9,W$4+1)-MAX($B9,W$4)) | X9: =MAX(0,MIN($C9,X$4+1)-MAX($B9,X$4)) | Y9: =MAX(0,MIN($C9,Y$4+1)-MAX($B9,Y$4)) | Z9: =MAX(0,MIN($C9,Z$4+1)-MAX($B9,Z$4)) | AA9: =MAX(0,MIN($C9,AA$4+1)-MAX($B9,AA$4)) | ... AM9: =MAX(0,MIN($C9,AM$4+1)-MAX($B9,AM$4)) | AO9: 0 | AP9: 0
B10: 0 | C10: 0 | E10: 0 | F10: 0 | G10: 0 | H10: 0 | I10: 0 | J10: 0 | K10: 0 | L10: 0 | M10: 0 | N10: 0 | O10: 0 | P10: 0 | Q10: 0 | R10: 0 | T10: =MAX(0,MIN($C10,T$4+1)-MAX($B10,T$4)) | U10: =MAX(0,MIN($C10,U$4+1)-MAX($B10,U$4)) | V10: =MAX(0,MIN($C10,V$4+1)-MAX($B10,V$4)) | W10: =MAX(0,MIN($C10,W$4+1)-MAX($B10,W$4)) | X10: =MAX(0,MIN($C10,X$4+1)-MAX($B10,X$4)) | Y10: =MAX(0,MIN($C10,Y$4+1)-MAX($B10,Y$4)) | Z10: =MAX(0,MIN($C10,Z$4+1)-MAX($B10,Z$4)) | AA10: =MAX(0,MIN($C10,AA$4+1)-MAX($B10,AA$4)) | ... AM10: =MAX(0,MIN($C10,AM$4+1)-MAX($B10,AM$4)) | AO10: 0 | AP10: 0
B11: 0 | C11: 0 | E11: 0 | F11: 0 | G11: 0 | H11: 0 | I11: 0 | J11: 0 | K11: 0 | L11: 0 | M11: 0 | N11: 0 | O11: 0 | P11: 0 | Q11: 0 | R11: 0 | T11: =MAX(0,MIN($C11,T$4+1)-MAX($B11,T$4)) | U11: =MAX(0,MIN($C11,U$4+1)-MAX($B11,U$4)) | V11: =MAX(0,MIN($C11,V$4+1)-MAX($B11,V$4)) | W11: =MAX(0,MIN($C11,W$4+1)-MAX($B11,W$4)) | X11: =MAX(0,MIN($C11,X$4+1)-MAX($B11,X$4)) | Y11: =MAX(0,MIN($C11,Y$4+1)-MAX($B11,Y$4)) | Z11: =MAX(0,MIN($C11,Z$4+1)-MAX($B11,Z$4)) | AA11: =MAX(0,MIN($C11,AA$4+1)-MAX($B11,AA$4)) | ... AM11: =MAX(0,MIN($C11,AM$4+1)-MAX($B11,AM$4)) | AO11: 0 | AP11: 0
B12: 0 | C12: 0 | E12: 0 | F12: 0 | G12: 0 | H12: 0 | I12: 0 | J12: 0 | K12: 0 | L12: 0 | M12: 0 | N12: 0 | O12: 0 | P12: 0 | Q12: 0 | R12: 0 | T12: =MAX(0,MIN($C12,T$4+1)-MAX($B12,T$4)) | U12: =MAX(0,MIN($C12,U$4+1)-MAX($B12,U$4)) | V12: =MAX(0,MIN($C12,V$4+1)-MAX($B12,V$4)) | W12: =MAX(0,MIN($C12,W$4+1)-MAX($B12,W$4)) | X12: =MAX(0,MIN($C12,X$4+1)-MAX($B12,X$4)) | Y12: =MAX(0,MIN($C12,Y$4+1)-MAX($B12,Y$4)) | Z12: =MAX(0,MIN($C12,Z$4+1)-MAX($B12,Z$4)) | AA12: =MAX(0,MIN($C12,AA$4+1)-MAX($B12,AA$4)) | ... AM12: =MAX(0,MIN($C12,AM$4+1)-MAX($B12,AM$4)) | AO12: 0 | AP12: 0
B13: 0 | C13: 0 | E13: 0 | F13: 0 | G13: 0 | H13: 0 | I13: 0 | J13: 0 | K13: 0 | L13: 0 | M13: 0 | N13: 0 | O13: 0 | P13: 0 | Q13: 0 | R13: 0 | T13: =MAX(0,MIN($C13,T$4+1)-MAX($B13,T$4)) | U13: =MAX(0,MIN($C13,U$4+1)-MAX($B13,U$4)) | V13: =MAX(0,MIN($C13,V$4+1)-MAX($B13,V$4)) | W13: =MAX(0,MIN($C13,W$4+1)-MAX($B13,W$4)) | X13: =MAX(0,MIN($C13,X$4+1)-MAX($B13,X$4)) | Y13: =MAX(0,MIN($C13,Y$4+1)-MAX($B13,Y$4)) | Z13: =MAX(0,MIN($C13,Z$4+1)-MAX($B13,Z$4)) | AA13: =MAX(0,MIN($C13,AA$4+1)-MAX($B13,AA$4)) | ... AM13: =MAX(0,MIN($C13,AM$4+1)-MAX($B13,AM$4)) | AO13: 0 | AP13: 0
B14: 0 | C14: 0 | E14: 0 | F14: 0 | G14: 0 | H14: 0 | I14: 0 | J14: 0 | K14: 0 | L14: 0 | M14: 0 | N14: 0 | O14: 0 | P14: 0 | Q14: 0 | R14: 0 | T14: =MAX(0,MIN($C14,T$4+1)-MAX($B14,T$4)) | U14: =MAX(0,MIN($C14,U$4+1)-MAX($B14,U$4)) | V14: =MAX(0,MIN($C14,V$4+1)-MAX($B14,V$4)) | W14: =MAX(0,MIN($C14,W$4+1)-MAX($B14,W$4)) | X14: =MAX(0,MIN($C14,X$4+1)-MAX($B14,X$4)) | Y14: =MAX(0,MIN($C14,Y$4+1)-MAX($B14,Y$4)) | Z14: =MAX(0,MIN($C14,Z$4+1)-MAX($B14,Z$4)) | AA14: =MAX(0,MIN($C14,AA$4+1)-MAX($B14,AA$4)) | ... AM14: =MAX(0,MIN($C14,AM$4+1)-MAX($B14,AM$4)) | AO14: 0 | AP14: 0
B15: 0 | C15: 0 | E15: 0 | F15: 0 | G15: 0 | H15: 0 | I15: 0 | J15: 0 | K15: 0 | L15: 0 | M15: 0 | N15: 0 | O15: 0 | P15: 0 | Q15: 0 | R15: 0 | T15: =MAX(0,MIN($C15,T$4+1)-MAX($B15,T$4)) | U15: =MAX(0,MIN($C15,U$4+1)-MAX($B15,U$4)) | V15: =MAX(0,MIN($C15,V$4+1)-MAX($B15,V$4)) | W15: =MAX(0,MIN($C15,W$4+1)-MAX($B15,W$4)) | X15: =MAX(0,MIN($C15,X$4+1)-MAX($B15,X$4)) | Y15: =MAX(0,MIN($C15,Y$4+1)-MAX($B15,Y$4)) | Z15: =MAX(0,MIN($C15,Z$4+1)-MAX($B15,Z$4)) | AA15: =MAX(0,MIN($C15,AA$4+1)-MAX($B15,AA$4)) | ... AM15: =MAX(0,MIN($C15,AM$4+1)-MAX($B15,AM$4)) | AO15: 0 | AP15: 0
B16: 0 | C16: 0 | E16: 0 | F16: 0 | G16: 0 | H16: 0 | I16: 0 | J16: 0 | K16: 0 | L16: 0 | M16: 0 | N16: 0 | O16: 0 | P16: 0 | Q16: 0 | R16: 0 | T16: =MAX(0,MIN($C16,T$4+1)-MAX($B16,T$4)) | U16: =MAX(0,MIN($C16,U$4+1)-MAX($B16,U$4)) | V16: =MAX(0,MIN($C16,V$4+1)-MAX($B16,V$4)) | W16: =MAX(0,MIN($C16,W$4+1)-MAX($B16,W$4)) | X16: =MAX(0,MIN($C16,X$4+1)-MAX($B16,X$4)) | Y16: =MAX(0,MIN($C16,Y$4+1)-MAX($B16,Y$4)) | Z16: =MAX(0,MIN($C16,Z$4+1)-MAX($B16,Z$4)) | AA16: =MAX(0,MIN($C16,AA$4+1)-MAX($B16,AA$4)) | ... AM16: =MAX(0,MIN($C16,AM$4+1)-MAX($B16,AM$4)) | AO16: 0 | AP16: 0
B17: 0 | C17: 0 | E17: 0 | F17: 0 | G17: 0 | H17: 0 | I17: 0 | J17: 0 | K17: 0 | L17: 0 | M17: 0 | N17: 0 | O17: 0 | P17: 0 | Q17: 0 | R17: 0 | T17: =MAX(0,MIN($C17,T$4+1)-MAX($B17,T$4)) | U17: =MAX(0,MIN($C17,U$4+1)-MAX($B17,U$4)) | V17: =MAX(0,MIN($C17,V$4+1)-MAX($B17,V$4)) | W17: =MAX(0,MIN($C17,W$4+1)-MAX($B17,W$4)) | X17: =MAX(0,MIN($C17,X$4+1)-MAX($B17,X$4)) | Y17: =MAX(0,MIN($C17,Y$4+1)-MAX($B17,Y$4)) | Z17: =MAX(0,MIN($C17,Z$4+1)-MAX($B17,Z$4)) | AA17: =MAX(0,MIN($C17,AA$4+1)-MAX($B17,AA$4)) | ... AM17: =MAX(0,MIN($C17,AM$4+1)-MAX($B17,AM$4)) | AO17: 0 | AP17: 0
B18: 0 | C18: 0 | E18: 0 | F18: 0 | G18: 0 | H18: 0 | I18: 0 | J18: 0 | K18: 0 | L18: 0 | M18: 0 | N18: 0 | O18: 0 | P18: 0 | Q18: 0 | R18: 0 | T18: =MAX(0,MIN($C18,T$4+1)-MAX($B18,T$4)) | U18: =MAX(0,MIN($C18,U$4+1)-MAX($B18,U$4)) | V18: =MAX(0,MIN($C18,V$4+1)-MAX($B18,V$4)) | W18: =MAX(0,MIN($C18,W$4+1)-MAX($B18,W$4)) | X18: =MAX(0,MIN($C18,X$4+1)-MAX($B18,X$4)) | Y18: =MAX(0,MIN($C18,Y$4+1)-MAX($B18,Y$4)) | Z18: =MAX(0,MIN($C18,Z$4+1)-MAX($B18,Z$4)) | AA18: =MAX(0,MIN($C18,AA$4+1)-MAX($B18,AA$4)) | ... AM18: =MAX(0,MIN($C18,AM$4+1)-MAX($B18,AM$4)) | AO18: 0 | AP18: 0
B19: 0 | C19: 0 | E19: 0 | F19: 0 | G19: 0 | H19: 0 | I19: 0 | J19: 0 | K19: 0 | L19: 0 | M19: 0 | N19: 0 | O19: 0 | P19: 0 | Q19: 0 | R19: 0 | T19: =MAX(0,MIN($C19,T$4+1)-MAX($B19,T$4)) | U19: =MAX(0,MIN($C19,U$4+1)-MAX($B19,U$4)) | V19: =MAX(0,MIN($C19,V$4+1)-MAX($B19,V$4)) | W19: =MAX(0,MIN($C19,W$4+1)-MAX($B19,W$4)) | X19: =MAX(0,MIN($C19,X$4+1)-MAX($B19,X$4)) | Y19: =MAX(0,MIN($C19,Y$4+1)-MAX($B19,Y$4)) | Z19: =MAX(0,MIN($C19,Z$4+1)-MAX($B19,Z$4)) | AA19: =MAX(0,MIN($C19,AA$4+1)-MAX($B19,AA$4)) | ... AM19: =MAX(0,MIN($C19,AM$4+1)-MAX($B19,AM$4)) | AO19: 0 | AP19: 0
... B24: 0 | C24: 0 | E24: 0 | F24: 0 | G24: 0 | H24: 0 | I24: 0 | J24: 0 | K24: 0 | L24: 0 | M24: 0 | N24: 0 | O24: 0 | P24: 0 | Q24: 0 | R24: 0 | T24: =MAX(0,MIN($C24,T$4+1)-MAX($B24,T$4)) | U24: =MAX(0,MIN($C24,U$4+1)-MAX($B24,U$4)) | V24: =MAX(0,MIN($C24,V$4+1)-MAX($B24,V$4)) | W24: =MAX(0,MIN($C24,W$4+1)-MAX($B24,W$4)) | X24: =MAX(0,MIN($C24,X$4+1)-MAX($B24,X$4)) | Y24: =MAX(0,MIN($C24,Y$4+1)-MAX($B24,Y$4)) | Z24: =MAX(0,MIN($C24,Z$4+1)-MAX($B24,Z$4)) | AA24: =MAX(0,MIN($C24,AA$4+1)-MAX($B24,AA$4)) | ... AM24: =MAX(0,MIN($C24,AM$4+1)-MAX($B24,AM$4)) | AO24: 0 | AP24: 0
B25: 0 | C25: 0 | E25: 0 | F25: 0 | G25: 0 | H25: 0 | I25: 0 | J25: 0 | K25: 0 | L25: 0 | M25: 0 | N25: 0 | O25: 0 | P25: 0 | Q25: 0 | R25: 0 | T25: =MAX(0,MIN($C25,T$4+1)-MAX($B25,T$4)) | U25: =MAX(0,MIN($C25,U$4+1)-MAX($B25,U$4)) | V25: =MAX(0,MIN($C25,V$4+1)-MAX($B25,V$4)) | W25: =MAX(0,MIN($C25,W$4+1)-MAX($B25,W$4)) | X25: =MAX(0,MIN($C25,X$4+1)-MAX($B25,X$4)) | Y25: =MAX(0,MIN($C25,Y$4+1)-MAX($B25,Y$4)) | Z25: =MAX(0,MIN($C25,Z$4+1)-MAX($B25,Z$4)) | AA25: =MAX(0,MIN($C25,AA$4+1)-MAX($B25,AA$4)) | ... AM25: =MAX(0,MIN($C25,AM$4+1)-MAX($B25,AM$4))
B26: 0 | C26: 0 | E26: 0 | F26: 0 | G26: 0 | H26: 0 | I26: 0 | J26: 0 | K26: 0 | L26: 0 | M26: 0 | N26: 0 | O26: 0 | P26: 0 | Q26: 0 | R26: 0 | T26: =MAX(0,MIN($C26,T$4+1)-MAX($B26,T$4)) | U26: =MAX(0,MIN($C26,U$4+1)-MAX($B26,U$4)) | V26: =MAX(0,MIN($C26,V$4+1)-MAX($B26,V$4)) | W26: =MAX(0,MIN($C26,W$4+1)-MAX($B26,W$4)) | X26: =MAX(0,MIN($C26,X$4+1)-MAX($B26,X$4)) | Y26: =MAX(0,MIN($C26,Y$4+1)-MAX($B26,Y$4)) | Z26: =MAX(0,MIN($C26,Z$4+1)-MAX($B26,Z$4)) | AA26: =MAX(0,MIN($C26,AA$4+1)-MAX($B26,AA$4)) | ... AM26: =MAX(0,MIN($C26,AM$4+1)-MAX($B26,AM$4))
B27: 0 | C27: 0 | E27: 0 | F27: 0 | G27: 0 | H27: 0 | I27: 0 | J27: 0 | K27: 0 | L27: 0 | M27: 0 | N27: 0 | O27: 0 | P27: 0 | Q27: 0 | R27: 0 | T27: =MAX(0,MIN($C27,T$4+1)-MAX($B27,T$4)) | U27: =MAX(0,MIN($C27,U$4+1)-MAX($B27,U$4)) | V27: =MAX(0,MIN($C27,V$4+1)-MAX($B27,V$4)) | W27: =MAX(0,MIN($C27,W$4+1)-MAX($B27,W$4)) | X27: =MAX(0,MIN($C27,X$4+1)-MAX($B27,X$4)) | Y27: =MAX(0,MIN($C27,Y$4+1)-MAX($B27,Y$4)) | Z27: =MAX(0,MIN($C27,Z$4+1)-MAX($B27,Z$4)) | AA27: =MAX(0,MIN($C27,AA$4+1)-MAX($B27,AA$4)) | ... AM27: =MAX(0,MIN($C27,AM$4+1)-MAX($B27,AM$4))
B28: 0 | C28: 0 | E28: 0 | F28: 0 | G28: 0 | H28: 0 | I28: 0 | J28: 0 | K28: 0 | L28: 0 | M28: 0 | N28: 0 | O28: 0 | P28: 0 | Q28: 0 | R28: 0 | T28: =MAX(0,MIN($C28,T$4+1)-MAX($B28,T$4)) | U28: =MAX(0,MIN($C28,U$4+1)-MAX($B28,U$4)) | V28: =MAX(0,MIN($C28,V$4+1)-MAX($B28,V$4)) | W28: =MAX(0,MIN($C28,W$4+1)-MAX($B28,W$4)) | X28: =MAX(0,MIN($C28,X$4+1)-MAX($B28,X$4)) | Y28: =MAX(0,MIN($C28,Y$4+1)-MAX($B28,Y$4)) | Z28: =MAX(0,MIN($C28,Z$4+1)-MAX($B28,Z$4)) | AA28: =MAX(0,MIN($C28,AA$4+1)-MAX($B28,AA$4)) | ... AM28: =MAX(0,MIN($C28,AM$4+1)-MAX($B28,AM$4))
B29: 0 | C29: 0 | E29: 0 | F29: 0 | G29: 0 | H29: 0 | I29: 0 | J29: 0 | K29: 0 | L29: 0 | M29: 0 | N29: 0 | O29: 0 | P29: 0 | Q29: 0 | R29: 0 | T29: =MAX(0,MIN($C29,T$4+1)-MAX($B29,T$4)) | U29: =MAX(0,MIN($C29,U$4+1)-MAX($B29,U$4)) | V29: =MAX(0,MIN($C29,V$4+1)-MAX($B29,V$4)) | W29: =MAX(0,MIN($C29,W$4+1)-MAX($B29,W$4)) | X29: =MAX(0,MIN($C29,X$4+1)-MAX($B29,X$4)) | Y29: =MAX(0,MIN($C29,Y$4+1)-MAX($B29,Y$4)) | Z29: =MAX(0,MIN($C29,Z$4+1)-MAX($B29,Z$4)) | AA29: =MAX(0,MIN($C29,AA$4+1)-MAX($B29,AA$4)) | ... AM29: =MAX(0,MIN($C29,AM$4+1)-MAX($B29,AM$4))
A31: Simulación anual (todas las celdas son fórmulas)
A32: Año | B32: k | C32: Índice inflación | D32: Salarios W-2 | E32: W-2 con match | F32: Stipends libres | G32: Ingreso S-corp | H32: Autoempleo (LLC/tutoría) | I32: Matrícula | J32: Fracción estudio | K32: Fracción PSLF | L32: Fracción travel | M32: Attending | N32: Hitos (costos) | O32: Aporte 403b | P32: Match empleador | Q32: S-corp neto | R32: Salario S-corp | S32: FICA patronal S-corp | T32: Distribución S-corp | U32: Salarios totales | V32: Base autoempleo | W32: Impuesto autoempleo | X32: FICA empleado | Y32: AGI | Z32: Ingreso gravable antes QBI | AA32: Deducción QBI | AB32: Ingreso gravable | AC32: Impuesto federal | AD32: Gravable NY | AE32: Impuesto estatal/local | AF32: Impuestos totales | AG32: Ingreso personal bruto en efectivo | AH32: Efectivo neto (tras impuestos y 403b) | AI32: Ingreso bruto | AJ32: Gastos de vida | AK32: Ahorro líquido inicio | AL32: Ya era dueño | AM32: Precio base 2026 | AN32: Precio en el año | AO32: Physician loan | AP32: % enganche | AQ32: Préstamo | AR32: Cuota P&I mensual | AS32: Unidades rentadas | AT32: Renta mensual (cotización) | AU32: PITI mensual | AV32: Efectivo requerido | AW32: Otras deudas mensuales | AX32: Crédito aporte familiar | AY32: Carga mensual para DTI | AZ32: Ingreso mensual para DTI | BA32: Compra este año | BB32: Dueño | BC32: Año de compra | BD32: Ahorro tras enganche | BE32: Precio de compra | BF32: Cuota hipoteca | BG32: PMI activo (antes) | BH32: Config. con ADU | BI32: Construye ADU | BJ32: ADU construido | BK32: Cuota ADU | BL32: Valor vivienda inicio | BM32: Hipoteca inicio | BN32: Hipoteca tras 12 pagos | BO32: Pagado hipoteca | BP32: Hipoteca tras pagos | BQ32: ADU inicio | BR32: ADU tras 12 pagos | BS32: Pagado ADU | BT32: ADU tras pagos | BU32: Seguro | BV32: Impuesto predial | BW32: Mantenimiento | BX32: PMI | BY32: PMI activo (después) | BZ32: Renta recibida | CA32: Costo de vivienda | CB32: Aporte familiar | CC32: IRS pagado | CD32: IRS saldo | CE32: Federal inicio | CF32: Tasa federal | CG32: Años repago fed. | CH32: En estudios (≥50%) | CI32: Usa RAP/PSLF | CJ32: Interés federal | CK32: Pago RAP | CL32: Pago federal | CM32: Federal tras pago | CN32: Meses PSLF | CO32: Condonado PSLF | CP32: Federal tras PSLF | CQ32: Años repago (tras pago) | CR32: Privado inicio | CS32: Tasa privada | CT32: Años repago priv. | CU32: Pago privado | CV32: Privado tras pago | CW32: Años repago priv. (tras) | CX32: Consumo tras interés | CY32: Gasto extra travel | CZ32: Salidas | DA32: Excedente (déficit) | DB32: Flujo acumulado | DC32: Meta enganche | DD32: Retorno del ahorro líquido | DE32: Pago deuda consumo | DF32: Gasto discrecional | DG32: Ahorro | DH32: Roth | DI32: Prepago | DJ32: Prepago a hipoteca | DK32: Retiro del ahorro | DL32: Déficit por financiar | DM32: Federal acumulado (antes) | DN32: Nuevo préstamo federal | DO32: Nuevo préstamo privado | DP32: Nueva deuda consumo | DQ32: Flujo al ahorro líquido | DR32: Ahorro líquido fin | DS32: Retiro fin | DT32: Valor vivienda fin | DU32: Hipoteca fin | DV32: ADU fin | DW32: Federal fin | DX32: Tasa federal fin | DY32: Años repago fed. fin | DZ32: Federal acumulado | EA32: Privado fin | EB32: Tasa privada fin | EC32: Años repago priv. fin | ED32: Deuda consumo fin | EE32: Año vivienda pagada | EF32: Deuda total | EG32: PATRIMONIO NETO | EH32: Patrimonio (dólares 2026)
A33: 2027 | B33: 0 | C33: =(1+g_inf)^(A33-2026) | D33: =SUMPRODUCT($T$5:$T$29,$E$5:$E$29*(1+$F$5:$F$29)^(A33-2026)*$G$5:$G$29*$H$5:$H$29*(1-$N$5:$N$29*$O$5:$O$29))*g_salMult+SUMPRODUCT(($B$5:$B$29>=A33)*($B$5:$B$29<A33+1)*$I$5:$I$29)*g_salMult | E33: =SUMPRODUCT($T$5:$T$29,$E$5:$E$29*(1+$F$5:$F$29)^(A33-2026)*$G$5:$G$29*$H$5:$H$29*$M$5:$M$29)*g_salMult | F33: =SUMPRODUCT($T$5:$T$29,$E$5:$E$29*(1+$F$5:$F$29)^(A33-2026)*$G$5:$G$29*$H$5:$H$29*$N$5:$N$29*$O$5:$O$29)*g_salMult | G33: =SUMPRODUCT($T$5:$T$29,$P$5:$P$29*(1+$F$5:$F$29)^(A33-2026)) | H33: =SUMPRODUCT($T$5:$T$29,$Q$5:$Q$29*(1+$F$5:$F$29)^(A33-2026))+IF(personal_llcActivo=1,personal_llcNeto*(1+personal_llcCrecimiento)^0,0) | I33: =SUMPRODUCT($T$5:$T$29,$J$5:$J$29/($C$5:$C$29-$B$5:$B$29+($C$5:$C$29=$B$5:$B$29)))*C33 | J33: =SUMPRODUCT($T$5:$T$29,$K$5:$K$29) | K33: =SUMPRODUCT($T$5:$T$29,$L$5:$L$29) | L33: =SUMPRODUCT($T$5:$T$29,$N$5:$N$29) | M33: =IF(SUMPRODUCT($T$5:$T$29,$R$5:$R$29)>0,1,0) | N33: =SUMPRODUCT(($AO$5:$AO$24>=A33)*($AO$5:$AO$24<A33+1)*$AP$5:$AP$24)*C33+IF(0=0,IF(sel_loc<>"miami",personal_costoMudanzaInicial,0),0) | O33: =MIN(personal_aporte403bPct*D33,retiro_limite403b*C33) | P33: =MIN(personal_aporte403bPct,personal_match403bPct)*E33 | Q33: =IF(G33>0,MAX(0,G33-impuestos_scorpCostoAnual*C33),0) | R33: =Q33*impuestos_scorpSalarioPct/(1+impuestos_ssTasa+impuestos_medicareTasa) | S33: =impuestos_ssTasa*MIN(R33,MAX(0,impuestos_ssTope*C33-D33))+impuestos_medicareTasa*R33 | T33: =Q33-R33-S33 | U33: =D33+R33 | V33: =H33*0.9235 | W33: =IF(H33>0,2*impuestos_ssTasa*MIN(V33,MAX(0,impuestos_ssTope*C33-U33))+2*impuestos_medicareTasa*V33,0) | X33: =impuestos_ssTasa*MIN(U33,impuestos_ssTope*C33)+impuestos_medicareTasa*U33+impuestos_medicareAdicional*MAX(0,U33+H33*0.9235-impuestos_medicareUmbral) | Y33: =MAX(0,D33-O33+R33+T33+H33-W33/2) | Z33: =MAX(0,Y33-impuestos_deduccionEstandar*C33) | AA33: =MIN(0.2*MAX(0,T33+H33-W33/2)*MAX(0,MIN(1,1-(Z33-impuestos_qbiUmbral*C33)/(impuestos_qbiRango*C33))),0.2*Z33) | AB33: =MAX(0,Z33-AA33) | AC33: =SUMPRODUCT((AB33>tb_federalBrackets_lo*C33)*(AB33-tb_federalBrackets_lo*C33)*tb_federalBrackets_dr) | AD33: =MAX(0,Y33-impuestos_nyDeduccion*C33) | AE33: =CHOOSE(loc_taxcode,0,impuestos_ohTasa*MAX(0,Y33-impuestos_ohExento*C33)+impuestos_ohMunicipal*U33,SUMPRODUCT((AD33>tb_nyBrackets_lo*C33)*(AD33-tb_nyBrackets_lo*C33)*tb_nyBrackets_dr)+loc_nyc*SUMPRODUCT((AD33>tb_nycBrackets_lo*C33)*(AD33-tb_nycBrackets_lo*C33)*tb_nycBrackets_dr)) | AF33: =AC33+AE33+X33+W33 | AG33: =D33+F33+R33+T33+H33 | AH33: =AG33-AF33-O33 | AI33: =D33+F33+G33+H33 | AJ33: =loc_gastosVida*C33*g_gastos | AK33: =IF(0=0,personal_liquidoInicial,DR32) | AL33: =IF(0=0,0,BB32) | AM33: =CHOOSE(sel_cfgIdx,loc_precio_duplex,loc_precio_inlaw,loc_precio_dosCasas,loc_precio_casaAdu,loc_precio_multi) | AN33: =AM33*(1+g_appr)^(A33-2026) | AO33: =IF(AND(M33=1,vivienda_prestamoMedico=1),1,0) | AP33: =IF(AO33=1,0.05,vivienda_enganchePct) | AQ33: =AN33*(1-AP33) | AR33: =PMT(g_mortRate/12,vivienda_plazoHipoteca*12,-AQ33) | AS33: =INDEX(cfg_units,sel_cfgIdx) | AT33: =AS33*loc_rentaUnidad*(1+g_inf)^(A33-2026)*(1-vivienda_vacancia) | AU33: =AR33+AN33*loc_impuestoPropPct/12+AM33*loc_seguroPct*(1+vivienda_inflacionSeguro)^(A33-2026)/12+IF(AND(AO33=0,AP33<0.2),AQ33*vivienda_pmiTasa/12,0) | AV33: =AN33*AP33+AN33*vivienda_cierrePct+general_reservaMeses/12*AJ33 | AW33: =(IF(0=0,MIN(personal_irsSaldo,personal_irsPagoMensual*12),MIN(CD32,personal_irsPagoMensual*12))+IF(CE33>0,PMT(CF33,MAX(1,prestamos_plazoAnios-CG33),-CE33),0)+IF(CR33>0,PMT(CS33,MAX(1,prestamos_plazoAnios-CT33),-CR33),0))/12 | AX33: =IF(OR(sel_cfg="duplex",sel_cfg="multi",sel_cfg="dosCasas"),0.75*personal_aporteFamiliaMensual,0) | AY33: =AU33-0.75*AT33-AX33+AW33 | AZ33: =(D33+G33+H33+0.5*F33)/12 | BA33: =IF(AND(AL33=0,A33>=vivienda_anioMinCompra,J33<0.5,AI33>0,AK33>=AV33,AY33<=vivienda_dtiMax*AZ33),1,0) | BB33: =MAX(AL33,BA33) | BC33: =IF(BA33=1,A33,IF(0=0,"",BC32)) | BD33: =AK33-IF(BA33=1,AN33*AP33+AN33*vivienda_cierrePct,0) | BE33: =IF(BA33=1,AN33,IF(0=0,0,BE32)) | BF33: =IF(BA33=1,AR33,IF(0=0,0,BF32)) | BG33: =IF(BA33=1,IF(AND(AO33=0,AP33<0.2),1,0),IF(0=0,0,BY32)) | BH33: =IF(sel_cfg="casaAdu",1,0) | BI33: =IF(AND(BB33=1,BH33=1,IF(0=0,0,BJ32)=0,A33>=IF(BC33="",9999,BC33)+vivienda_aduRetrasoAnios),1,0) | BJ33: =MAX(IF(0=0,0,BJ32),BI33) | BK33: =IF(BI33=1,PMT((g_mortRate+0.005)/12,180,-loc_precio_aduCosto*C33),IF(0=0,0,BK32)) | BL33: =IF(BA33=1,AN33,IF(0=0,0,DT32))+IF(BI33=1,loc_precio_aduCosto*C33,0) | BM33: =IF(BA33=1,AQ33,IF(0=0,0,DU32)) | BN33: =IF(BM33<=0,0,FV(g_mortRate/12,12,BF33,-BM33)) | BO33: =IF(BM33<=0,0,12*BF33+MIN(0,BN33)) | BP33: =MAX(0,BN33) | BQ33: =IF(BI33=1,loc_precio_aduCosto*C33,IF(0=0,0,DV32)) | BR33: =IF(BQ33<=0,0,FV((g_mortRate+0.005)/12,12,BK33,-BQ33)) | BS33: =IF(BQ33<=0,0,12*BK33+MIN(0,BR33)) | BT33: =MAX(0,BR33) | BU33: =IF(BB33=1,AM33*loc_seguroPct*(1+vivienda_inflacionSeguro)^(A33-2026)*IF(BJ33=1,1+loc_precio_aduCosto/AM33,1),0) | BV33: =BL33*loc_impuestoPropPct | BW33: =BL33*vivienda_mantenimientoPct | BX33: =IF(AND(BG33=1,BP33>0.8*BE33),BE33*(1-vivienda_enganchePct)*vivienda_pmiTasa,0) | BY33: =IF(AND(BG33=1,BP33>0.8*BE33),1,0) | BZ33: =IF(BB33=1,AS33*loc_rentaUnidad*12*C33*(1-vivienda_vacancia)*(1-vivienda_gestionPct),0) | CA33: =IF(BB33=1,BO33+BS33+BU33+BV33+BW33+BX33,loc_rentaMensual*12*C33) | CB33: =IF(BB33=1,personal_aporteFamiliaMensual*12,0) | CC33: =MIN(IF(0=0,personal_irsSaldo,CD32),personal_irsPagoMensual*12) | CD33: =IF(0=0,personal_irsSaldo,CD32)-CC33 | CE33: =IF(0=0,IF(personal_deudaEsFederal=1,personal_deudaEstudiantil,0),DW32) | CF33: =IF(0=0,personal_tasaDeudaEstudiantil,DX32) | CG33: =IF(0=0,0,DY32) | CH33: =IF(J33>=0.5,1,0) | CI33: =IF(AND(CH33=0,prestamos_pslfActivo=1,K33>=0.5,CE33>0),1,0) | CJ33: =CE33*CF33 | CK33: =MAX(prestamos_rapPagoMinimoAnual,IF(Y33<10000,0,MIN(0.1,INT(Y33/10000)/100))*Y33) | CL33: =IF(CE33<=0,0,IF(CH33=1,0,IF(CI33=1,MIN(CE33+CJ33,CK33),PMT(CF33,MAX(1,prestamos_plazoAnios-CG33),-CE33)))) | CM33: =IF(CE33<=0,0,IF(CH33=1,CE33+CJ33,IF(CI33=1,MAX(0,CE33-MAX(CL33-CJ33,MIN(600,CL33))),MAX(0,CE33*(1+CF33)-CL33)))) | CN33: =IF(0=0,0,CN32)+IF(CI33=1,12*MIN(1,K33),0) | CO33: =IF(AND(CI33=1,CN33>=prestamos_pslfPagos,CM33>0),CM33,0) | CP33: =CM33-CO33 | CQ33: =IF(AND(CE33>0,CH33=0,CI33=0),CG33+1,CG33) | CR33: =IF(0=0,IF(personal_deudaEsFederal=1,0,personal_deudaEstudiantil),EA32) | CS33: =IF(0=0,IF(personal_deudaEsFederal=1,prestamos_tasaPrivada,personal_tasaDeudaEstudiantil),EB32) | CT33: =IF(0=0,0,EC32) | CU33: =IF(OR(CR33<=0,CH33=1),0,PMT(CS33,MAX(1,prestamos_plazoAnios-CT33),-CR33)) | CV33: =IF(CR33<=0,0,IF(CH33=1,CR33*(1+CS33),MAX(0,CR33*(1+CS33)-CU33))) | CW33: =IF(AND(CR33>0,CH33=0),CT33+1,CT33) | CX33: =IF(0=0,0,ED32)*(1+general_tasaDeudaConsumo) | CY33: =L33*12*tiempos_travelGastoExtraMes*C33 | CZ33: =AJ33+CY33+CA33+CC33+CL33+CU33+I33+N33-BZ33-CB33 | DA33: =AH33-CZ33 | DB33: =IF(0=0,0,DB32)+DA33 | DC33: =AN33*vivienda_enganchePct+AN33*vivienda_cierrePct+general_reservaMeses/12*AJ33 | DD33: =IF(BB33=1,g_ret,IF(BD33>0,MIN(1,DC33/BD33),1)*g_cash+(1-IF(BD33>0,MIN(1,DC33/BD33),1))*g_ret) | DE33: =IF(DA33>=0,MIN(CX33,DA33),0) | DF33: =IF(DA33>=0,(1-general_tasaAhorro)*(DA33-DE33),0) | DG33: =IF(DA33>=0,DA33-DE33-DF33,0) | DH33: =MIN(personal_rothAnual,DG33) | DI33: =IF(AND(DA33>=0,BB33=1,BP33+BT33>0),MIN(vivienda_prepagoPct*(DG33-DH33),BP33+BT33),0) | DJ33: =MIN(DI33,BP33) | DK33: =IF(DA33<0,MIN(MAX(0,BD33),-DA33),0) | DL33: =IF(DA33<0,-DA33-DK33,0) | DM33: =IF(0=0,0,DZ32) | DN33: =IF(AND(DL33>0,J33>0),MIN(DL33,MIN(prestamos_topeAnualPosgrado*MIN(1,J33),MAX(0,prestamos_topeTotalPosgrado-DM33))),0) | DO33: =IF(AND(DL33>0,J33>0),DL33-DN33,0) | DP33: =IF(AND(DL33>0,J33<=0),DL33,0) | DQ33: =IF(DA33>=0,DG33-DH33-DI33,-DK33) | DR33: =BD33*(1+DD33)+DQ33*(1+DD33/2) | DS33: =IF(0=0,personal_retiroInicial,DS32)*(1+g_ret)+(O33+P33+DH33)*(1+g_ret/2) | DT33: =IF(BB33=1,BL33*(1+g_appr),0) | DU33: =BP33-DJ33 | DV33: =BT33-(DI33-DJ33) | DW33: =CP33+DN33 | DX33: =IF(DN33>0,(CP33*CF33+DN33*prestamos_tasaFederalPosgrado)/(CP33+DN33),CF33) | DY33: =IF(DN33>0,0,CQ33) | DZ33: =DM33+DN33 | EA33: =CV33+DO33 | EB33: =IF(DO33>0,(CV33*CS33+DO33*prestamos_tasaPrivada)/(CV33+DO33),CS33) | EC33: =IF(DO33>0,0,CW33) | ED33: =CX33-DE33+DP33 | EE33: =IF(IF(0=0,"",EE32)<>"",EE32,IF(AND(BB33=1,DU33<=0.5,DV33<=0.5,OR(BH33=0,BJ33=1)),A33,"")) | EF33: =DU33+DV33+DW33+EA33+ED33+CD33 | EG33: =DR33+DS33+DT33-EF33 | EH33: =EG33/(1+g_inf)^(A33+1-2026)
A34: 2028 | B34: 1 | C34: =(1+g_inf)^(A34-2026) | D34: =SUMPRODUCT($U$5:$U$29,$E$5:$E$29*(1+$F$5:$F$29)^(A34-2026)*$G$5:$G$29*$H$5:$H$29*(1-$N$5:$N$29*$O$5:$O$29))*g_salMult+SUMPRODUCT(($B$5:$B$29>=A34)*($B$5:$B$29<A34+1)*$I$5:$I$29)*g_salMult | E34: =SUMPRODUCT($U$5:$U$29,$E$5:$E$29*(1+$F$5:$F$29)^(A34-2026)*$G$5:$G$29*$H$5:$H$29*$M$5:$M$29)*g_salMult | F34: =SUMPRODUCT($U$5:$U$29,$E$5:$E$29*(1+$F$5:$F$29)^(A34-2026)*$G$5:$G$29*$H$5:$H$29*$N$5:$N$29*$O$5:$O$29)*g_salMult | G34: =SUMPRODUCT($U$5:$U$29,$P$5:$P$29*(1+$F$5:$F$29)^(A34-2026)) | H34: =SUMPRODUCT($U$5:$U$29,$Q$5:$Q$29*(1+$F$5:$F$29)^(A34-2026))+IF(personal_llcActivo=1,personal_llcNeto*(1+personal_llcCrecimiento)^1,0) | I34: =SUMPRODUCT($U$5:$U$29,$J$5:$J$29/($C$5:$C$29-$B$5:$B$29+($C$5:$C$29=$B$5:$B$29)))*C34 | J34: =SUMPRODUCT($U$5:$U$29,$K$5:$K$29) | K34: =SUMPRODUCT($U$5:$U$29,$L$5:$L$29) | L34: =SUMPRODUCT($U$5:$U$29,$N$5:$N$29) | M34: =IF(SUMPRODUCT($U$5:$U$29,$R$5:$R$29)>0,1,0) | N34: =SUMPRODUCT(($AO$5:$AO$24>=A34)*($AO$5:$AO$24<A34+1)*$AP$5:$AP$24)*C34+IF(1=0,IF(sel_loc<>"miami",personal_costoMudanzaInicial,0),0) | O34: =MIN(personal_aporte403bPct*D34,retiro_limite403b*C34) | P34: =MIN(personal_aporte403bPct,personal_match403bPct)*E34 | Q34: =IF(G34>0,MAX(0,G34-impuestos_scorpCostoAnual*C34),0) | R34: =Q34*impuestos_scorpSalarioPct/(1+impuestos_ssTasa+impuestos_medicareTasa) | S34: =impuestos_ssTasa*MIN(R34,MAX(0,impuestos_ssTope*C34-D34))+impuestos_medicareTasa*R34 | T34: =Q34-R34-S34 | U34: =D34+R34 | V34: =H34*0.9235 | W34: =IF(H34>0,2*impuestos_ssTasa*MIN(V34,MAX(0,impuestos_ssTope*C34-U34))+2*impuestos_medicareTasa*V34,0) | X34: =impuestos_ssTasa*MIN(U34,impuestos_ssTope*C34)+impuestos_medicareTasa*U34+impuestos_medicareAdicional*MAX(0,U34+H34*0.9235-impuestos_medicareUmbral) | Y34: =MAX(0,D34-O34+R34+T34+H34-W34/2) | Z34: =MAX(0,Y34-impuestos_deduccionEstandar*C34) | AA34: =MIN(0.2*MAX(0,T34+H34-W34/2)*MAX(0,MIN(1,1-(Z34-impuestos_qbiUmbral*C34)/(impuestos_qbiRango*C34))),0.2*Z34) | AB34: =MAX(0,Z34-AA34) | AC34: =SUMPRODUCT((AB34>tb_federalBrackets_lo*C34)*(AB34-tb_federalBrackets_lo*C34)*tb_federalBrackets_dr) | AD34: =MAX(0,Y34-impuestos_nyDeduccion*C34) | AE34: =CHOOSE(loc_taxcode,0,impuestos_ohTasa*MAX(0,Y34-impuestos_ohExento*C34)+impuestos_ohMunicipal*U34,SUMPRODUCT((AD34>tb_nyBrackets_lo*C34)*(AD34-tb_nyBrackets_lo*C34)*tb_nyBrackets_dr)+loc_nyc*SUMPRODUCT((AD34>tb_nycBrackets_lo*C34)*(AD34-tb_nycBrackets_lo*C34)*tb_nycBrackets_dr)) | AF34: =AC34+AE34+X34+W34 | AG34: =D34+F34+R34+T34+H34 | AH34: =AG34-AF34-O34 | AI34: =D34+F34+G34+H34 | AJ34: =loc_gastosVida*C34*g_gastos | AK34: =IF(1=0,personal_liquidoInicial,DR33) | AL34: =IF(1=0,0,BB33) | AM34: =CHOOSE(sel_cfgIdx,loc_precio_duplex,loc_precio_inlaw,loc_precio_dosCasas,loc_precio_casaAdu,loc_precio_multi) | AN34: =AM34*(1+g_appr)^(A34-2026) | AO34: =IF(AND(M34=1,vivienda_prestamoMedico=1),1,0) | AP34: =IF(AO34=1,0.05,vivienda_enganchePct) | AQ34: =AN34*(1-AP34) | AR34: =PMT(g_mortRate/12,vivienda_plazoHipoteca*12,-AQ34) | AS34: =INDEX(cfg_units,sel_cfgIdx) | AT34: =AS34*loc_rentaUnidad*(1+g_inf)^(A34-2026)*(1-vivienda_vacancia) | AU34: =AR34+AN34*loc_impuestoPropPct/12+AM34*loc_seguroPct*(1+vivienda_inflacionSeguro)^(A34-2026)/12+IF(AND(AO34=0,AP34<0.2),AQ34*vivienda_pmiTasa/12,0) | AV34: =AN34*AP34+AN34*vivienda_cierrePct+general_reservaMeses/12*AJ34 | AW34: =(IF(1=0,MIN(personal_irsSaldo,personal_irsPagoMensual*12),MIN(CD33,personal_irsPagoMensual*12))+IF(CE34>0,PMT(CF34,MAX(1,prestamos_plazoAnios-CG34),-CE34),0)+IF(CR34>0,PMT(CS34,MAX(1,prestamos_plazoAnios-CT34),-CR34),0))/12 | AX34: =IF(OR(sel_cfg="duplex",sel_cfg="multi",sel_cfg="dosCasas"),0.75*personal_aporteFamiliaMensual,0) | AY34: =AU34-0.75*AT34-AX34+AW34 | AZ34: =(D34+G34+H34+0.5*F34)/12 | BA34: =IF(AND(AL34=0,A34>=vivienda_anioMinCompra,J34<0.5,AI34>0,AK34>=AV34,AY34<=vivienda_dtiMax*AZ34),1,0) | BB34: =MAX(AL34,BA34) | BC34: =IF(BA34=1,A34,IF(1=0,"",BC33)) | BD34: =AK34-IF(BA34=1,AN34*AP34+AN34*vivienda_cierrePct,0) | BE34: =IF(BA34=1,AN34,IF(1=0,0,BE33)) | BF34: =IF(BA34=1,AR34,IF(1=0,0,BF33)) | BG34: =IF(BA34=1,IF(AND(AO34=0,AP34<0.2),1,0),IF(1=0,0,BY33)) | BH34: =IF(sel_cfg="casaAdu",1,0) | BI34: =IF(AND(BB34=1,BH34=1,IF(1=0,0,BJ33)=0,A34>=IF(BC34="",9999,BC34)+vivienda_aduRetrasoAnios),1,0) | BJ34: =MAX(IF(1=0,0,BJ33),BI34) | BK34: =IF(BI34=1,PMT((g_mortRate+0.005)/12,180,-loc_precio_aduCosto*C34),IF(1=0,0,BK33)) | BL34: =IF(BA34=1,AN34,IF(1=0,0,DT33))+IF(BI34=1,loc_precio_aduCosto*C34,0) | BM34: =IF(BA34=1,AQ34,IF(1=0,0,DU33)) | BN34: =IF(BM34<=0,0,FV(g_mortRate/12,12,BF34,-BM34)) | BO34: =IF(BM34<=0,0,12*BF34+MIN(0,BN34)) | BP34: =MAX(0,BN34) | BQ34: =IF(BI34=1,loc_precio_aduCosto*C34,IF(1=0,0,DV33)) | BR34: =IF(BQ34<=0,0,FV((g_mortRate+0.005)/12,12,BK34,-BQ34)) | BS34: =IF(BQ34<=0,0,12*BK34+MIN(0,BR34)) | BT34: =MAX(0,BR34) | BU34: =IF(BB34=1,AM34*loc_seguroPct*(1+vivienda_inflacionSeguro)^(A34-2026)*IF(BJ34=1,1+loc_precio_aduCosto/AM34,1),0) | BV34: =BL34*loc_impuestoPropPct | BW34: =BL34*vivienda_mantenimientoPct | BX34: =IF(AND(BG34=1,BP34>0.8*BE34),BE34*(1-vivienda_enganchePct)*vivienda_pmiTasa,0) | BY34: =IF(AND(BG34=1,BP34>0.8*BE34),1,0) | BZ34: =IF(BB34=1,AS34*loc_rentaUnidad*12*C34*(1-vivienda_vacancia)*(1-vivienda_gestionPct),0) | CA34: =IF(BB34=1,BO34+BS34+BU34+BV34+BW34+BX34,loc_rentaMensual*12*C34) | CB34: =IF(BB34=1,personal_aporteFamiliaMensual*12,0) | CC34: =MIN(IF(1=0,personal_irsSaldo,CD33),personal_irsPagoMensual*12) | CD34: =IF(1=0,personal_irsSaldo,CD33)-CC34 | CE34: =IF(1=0,IF(personal_deudaEsFederal=1,personal_deudaEstudiantil,0),DW33) | CF34: =IF(1=0,personal_tasaDeudaEstudiantil,DX33) | CG34: =IF(1=0,0,DY33) | CH34: =IF(J34>=0.5,1,0) | CI34: =IF(AND(CH34=0,prestamos_pslfActivo=1,K34>=0.5,CE34>0),1,0) | CJ34: =CE34*CF34 | CK34: =MAX(prestamos_rapPagoMinimoAnual,IF(Y34<10000,0,MIN(0.1,INT(Y34/10000)/100))*Y34) | CL34: =IF(CE34<=0,0,IF(CH34=1,0,IF(CI34=1,MIN(CE34+CJ34,CK34),PMT(CF34,MAX(1,prestamos_plazoAnios-CG34),-CE34)))) | CM34: =IF(CE34<=0,0,IF(CH34=1,CE34+CJ34,IF(CI34=1,MAX(0,CE34-MAX(CL34-CJ34,MIN(600,CL34))),MAX(0,CE34*(1+CF34)-CL34)))) | CN34: =IF(1=0,0,CN33)+IF(CI34=1,12*MIN(1,K34),0) | CO34: =IF(AND(CI34=1,CN34>=prestamos_pslfPagos,CM34>0),CM34,0) | CP34: =CM34-CO34 | CQ34: =IF(AND(CE34>0,CH34=0,CI34=0),CG34+1,CG34) | CR34: =IF(1=0,IF(personal_deudaEsFederal=1,0,personal_deudaEstudiantil),EA33) | CS34: =IF(1=0,IF(personal_deudaEsFederal=1,prestamos_tasaPrivada,personal_tasaDeudaEstudiantil),EB33) | CT34: =IF(1=0,0,EC33) | CU34: =IF(OR(CR34<=0,CH34=1),0,PMT(CS34,MAX(1,prestamos_plazoAnios-CT34),-CR34)) | CV34: =IF(CR34<=0,0,IF(CH34=1,CR34*(1+CS34),MAX(0,CR34*(1+CS34)-CU34))) | CW34: =IF(AND(CR34>0,CH34=0),CT34+1,CT34) | CX34: =IF(1=0,0,ED33)*(1+general_tasaDeudaConsumo) | CY34: =L34*12*tiempos_travelGastoExtraMes*C34 | CZ34: =AJ34+CY34+CA34+CC34+CL34+CU34+I34+N34-BZ34-CB34 | DA34: =AH34-CZ34 | DB34: =IF(1=0,0,DB33)+DA34 | DC34: =AN34*vivienda_enganchePct+AN34*vivienda_cierrePct+general_reservaMeses/12*AJ34 | DD34: =IF(BB34=1,g_ret,IF(BD34>0,MIN(1,DC34/BD34),1)*g_cash+(1-IF(BD34>0,MIN(1,DC34/BD34),1))*g_ret) | DE34: =IF(DA34>=0,MIN(CX34,DA34),0) | DF34: =IF(DA34>=0,(1-general_tasaAhorro)*(DA34-DE34),0) | DG34: =IF(DA34>=0,DA34-DE34-DF34,0) | DH34: =MIN(personal_rothAnual,DG34) | DI34: =IF(AND(DA34>=0,BB34=1,BP34+BT34>0),MIN(vivienda_prepagoPct*(DG34-DH34),BP34+BT34),0) | DJ34: =MIN(DI34,BP34) | DK34: =IF(DA34<0,MIN(MAX(0,BD34),-DA34),0) | DL34: =IF(DA34<0,-DA34-DK34,0) | DM34: =IF(1=0,0,DZ33) | DN34: =IF(AND(DL34>0,J34>0),MIN(DL34,MIN(prestamos_topeAnualPosgrado*MIN(1,J34),MAX(0,prestamos_topeTotalPosgrado-DM34))),0) | DO34: =IF(AND(DL34>0,J34>0),DL34-DN34,0) | DP34: =IF(AND(DL34>0,J34<=0),DL34,0) | DQ34: =IF(DA34>=0,DG34-DH34-DI34,-DK34) | DR34: =BD34*(1+DD34)+DQ34*(1+DD34/2) | DS34: =IF(1=0,personal_retiroInicial,DS33)*(1+g_ret)+(O34+P34+DH34)*(1+g_ret/2) | DT34: =IF(BB34=1,BL34*(1+g_appr),0) | DU34: =BP34-DJ34 | DV34: =BT34-(DI34-DJ34) | DW34: =CP34+DN34 | DX34: =IF(DN34>0,(CP34*CF34+DN34*prestamos_tasaFederalPosgrado)/(CP34+DN34),CF34) | DY34: =IF(DN34>0,0,CQ34) | DZ34: =DM34+DN34 | EA34: =CV34+DO34 | EB34: =IF(DO34>0,(CV34*CS34+DO34*prestamos_tasaPrivada)/(CV34+DO34),CS34) | EC34: =IF(DO34>0,0,CW34) | ED34: =CX34-DE34+DP34 | EE34: =IF(IF(1=0,"",EE33)<>"",EE33,IF(AND(BB34=1,DU34<=0.5,DV34<=0.5,OR(BH34=0,BJ34=1)),A34,"")) | EF34: =DU34+DV34+DW34+EA34+ED34+CD34 | EG34: =DR34+DS34+DT34-EF34 | EH34: =EG34/(1+g_inf)^(A34+1-2026)
A35: 2029 | B35: 2 | C35: =(1+g_inf)^(A35-2026) | D35: =SUMPRODUCT($V$5:$V$29,$E$5:$E$29*(1+$F$5:$F$29)^(A35-2026)*$G$5:$G$29*$H$5:$H$29*(1-$N$5:$N$29*$O$5:$O$29))*g_salMult+SUMPRODUCT(($B$5:$B$29>=A35)*($B$5:$B$29<A35+1)*$I$5:$I$29)*g_salMult | E35: =SUMPRODUCT($V$5:$V$29,$E$5:$E$29*(1+$F$5:$F$29)^(A35-2026)*$G$5:$G$29*$H$5:$H$29*$M$5:$M$29)*g_salMult | F35: =SUMPRODUCT($V$5:$V$29,$E$5:$E$29*(1+$F$5:$F$29)^(A35-2026)*$G$5:$G$29*$H$5:$H$29*$N$5:$N$29*$O$5:$O$29)*g_salMult | G35: =SUMPRODUCT($V$5:$V$29,$P$5:$P$29*(1+$F$5:$F$29)^(A35-2026)) | H35: =SUMPRODUCT($V$5:$V$29,$Q$5:$Q$29*(1+$F$5:$F$29)^(A35-2026))+IF(personal_llcActivo=1,personal_llcNeto*(1+personal_llcCrecimiento)^2,0) | I35: =SUMPRODUCT($V$5:$V$29,$J$5:$J$29/($C$5:$C$29-$B$5:$B$29+($C$5:$C$29=$B$5:$B$29)))*C35 | J35: =SUMPRODUCT($V$5:$V$29,$K$5:$K$29) | K35: =SUMPRODUCT($V$5:$V$29,$L$5:$L$29) | L35: =SUMPRODUCT($V$5:$V$29,$N$5:$N$29) | M35: =IF(SUMPRODUCT($V$5:$V$29,$R$5:$R$29)>0,1,0) | N35: =SUMPRODUCT(($AO$5:$AO$24>=A35)*($AO$5:$AO$24<A35+1)*$AP$5:$AP$24)*C35+IF(2=0,IF(sel_loc<>"miami",personal_costoMudanzaInicial,0),0) | O35: =MIN(personal_aporte403bPct*D35,retiro_limite403b*C35) | P35: =MIN(personal_aporte403bPct,personal_match403bPct)*E35 | Q35: =IF(G35>0,MAX(0,G35-impuestos_scorpCostoAnual*C35),0) | R35: =Q35*impuestos_scorpSalarioPct/(1+impuestos_ssTasa+impuestos_medicareTasa) | S35: =impuestos_ssTasa*MIN(R35,MAX(0,impuestos_ssTope*C35-D35))+impuestos_medicareTasa*R35 | T35: =Q35-R35-S35 | U35: =D35+R35 | V35: =H35*0.9235 | W35: =IF(H35>0,2*impuestos_ssTasa*MIN(V35,MAX(0,impuestos_ssTope*C35-U35))+2*impuestos_medicareTasa*V35,0) | X35: =impuestos_ssTasa*MIN(U35,impuestos_ssTope*C35)+impuestos_medicareTasa*U35+impuestos_medicareAdicional*MAX(0,U35+H35*0.9235-impuestos_medicareUmbral) | Y35: =MAX(0,D35-O35+R35+T35+H35-W35/2) | Z35: =MAX(0,Y35-impuestos_deduccionEstandar*C35) | AA35: =MIN(0.2*MAX(0,T35+H35-W35/2)*MAX(0,MIN(1,1-(Z35-impuestos_qbiUmbral*C35)/(impuestos_qbiRango*C35))),0.2*Z35) | AB35: =MAX(0,Z35-AA35) | AC35: =SUMPRODUCT((AB35>tb_federalBrackets_lo*C35)*(AB35-tb_federalBrackets_lo*C35)*tb_federalBrackets_dr) | AD35: =MAX(0,Y35-impuestos_nyDeduccion*C35) | AE35: =CHOOSE(loc_taxcode,0,impuestos_ohTasa*MAX(0,Y35-impuestos_ohExento*C35)+impuestos_ohMunicipal*U35,SUMPRODUCT((AD35>tb_nyBrackets_lo*C35)*(AD35-tb_nyBrackets_lo*C35)*tb_nyBrackets_dr)+loc_nyc*SUMPRODUCT((AD35>tb_nycBrackets_lo*C35)*(AD35-tb_nycBrackets_lo*C35)*tb_nycBrackets_dr)) | AF35: =AC35+AE35+X35+W35 | AG35: =D35+F35+R35+T35+H35 | AH35: =AG35-AF35-O35 | AI35: =D35+F35+G35+H35 | AJ35: =loc_gastosVida*C35*g_gastos | AK35: =IF(2=0,personal_liquidoInicial,DR34) | AL35: =IF(2=0,0,BB34) | AM35: =CHOOSE(sel_cfgIdx,loc_precio_duplex,loc_precio_inlaw,loc_precio_dosCasas,loc_precio_casaAdu,loc_precio_multi) | AN35: =AM35*(1+g_appr)^(A35-2026) | AO35: =IF(AND(M35=1,vivienda_prestamoMedico=1),1,0) | AP35: =IF(AO35=1,0.05,vivienda_enganchePct) | AQ35: =AN35*(1-AP35) | AR35: =PMT(g_mortRate/12,vivienda_plazoHipoteca*12,-AQ35) | AS35: =INDEX(cfg_units,sel_cfgIdx) | AT35: =AS35*loc_rentaUnidad*(1+g_inf)^(A35-2026)*(1-vivienda_vacancia) | AU35: =AR35+AN35*loc_impuestoPropPct/12+AM35*loc_seguroPct*(1+vivienda_inflacionSeguro)^(A35-2026)/12+IF(AND(AO35=0,AP35<0.2),AQ35*vivienda_pmiTasa/12,0) | AV35: =AN35*AP35+AN35*vivienda_cierrePct+general_reservaMeses/12*AJ35 | AW35: =(IF(2=0,MIN(personal_irsSaldo,personal_irsPagoMensual*12),MIN(CD34,personal_irsPagoMensual*12))+IF(CE35>0,PMT(CF35,MAX(1,prestamos_plazoAnios-CG35),-CE35),0)+IF(CR35>0,PMT(CS35,MAX(1,prestamos_plazoAnios-CT35),-CR35),0))/12 | AX35: =IF(OR(sel_cfg="duplex",sel_cfg="multi",sel_cfg="dosCasas"),0.75*personal_aporteFamiliaMensual,0) | AY35: =AU35-0.75*AT35-AX35+AW35 | AZ35: =(D35+G35+H35+0.5*F35)/12 | BA35: =IF(AND(AL35=0,A35>=vivienda_anioMinCompra,J35<0.5,AI35>0,AK35>=AV35,AY35<=vivienda_dtiMax*AZ35),1,0) | BB35: =MAX(AL35,BA35) | BC35: =IF(BA35=1,A35,IF(2=0,"",BC34)) | BD35: =AK35-IF(BA35=1,AN35*AP35+AN35*vivienda_cierrePct,0) | BE35: =IF(BA35=1,AN35,IF(2=0,0,BE34)) | BF35: =IF(BA35=1,AR35,IF(2=0,0,BF34)) | BG35: =IF(BA35=1,IF(AND(AO35=0,AP35<0.2),1,0),IF(2=0,0,BY34)) | BH35: =IF(sel_cfg="casaAdu",1,0) | BI35: =IF(AND(BB35=1,BH35=1,IF(2=0,0,BJ34)=0,A35>=IF(BC35="",9999,BC35)+vivienda_aduRetrasoAnios),1,0) | BJ35: =MAX(IF(2=0,0,BJ34),BI35) | BK35: =IF(BI35=1,PMT((g_mortRate+0.005)/12,180,-loc_precio_aduCosto*C35),IF(2=0,0,BK34)) | BL35: =IF(BA35=1,AN35,IF(2=0,0,DT34))+IF(BI35=1,loc_precio_aduCosto*C35,0) | BM35: =IF(BA35=1,AQ35,IF(2=0,0,DU34)) | BN35: =IF(BM35<=0,0,FV(g_mortRate/12,12,BF35,-BM35)) | BO35: =IF(BM35<=0,0,12*BF35+MIN(0,BN35)) | BP35: =MAX(0,BN35) | BQ35: =IF(BI35=1,loc_precio_aduCosto*C35,IF(2=0,0,DV34)) | BR35: =IF(BQ35<=0,0,FV((g_mortRate+0.005)/12,12,BK35,-BQ35)) | BS35: =IF(BQ35<=0,0,12*BK35+MIN(0,BR35)) | BT35: =MAX(0,BR35) | BU35: =IF(BB35=1,AM35*loc_seguroPct*(1+vivienda_inflacionSeguro)^(A35-2026)*IF(BJ35=1,1+loc_precio_aduCosto/AM35,1),0) | BV35: =BL35*loc_impuestoPropPct | BW35: =BL35*vivienda_mantenimientoPct | BX35: =IF(AND(BG35=1,BP35>0.8*BE35),BE35*(1-vivienda_enganchePct)*vivienda_pmiTasa,0) | BY35: =IF(AND(BG35=1,BP35>0.8*BE35),1,0) | BZ35: =IF(BB35=1,AS35*loc_rentaUnidad*12*C35*(1-vivienda_vacancia)*(1-vivienda_gestionPct),0) | CA35: =IF(BB35=1,BO35+BS35+BU35+BV35+BW35+BX35,loc_rentaMensual*12*C35) | CB35: =IF(BB35=1,personal_aporteFamiliaMensual*12,0) | CC35: =MIN(IF(2=0,personal_irsSaldo,CD34),personal_irsPagoMensual*12) | CD35: =IF(2=0,personal_irsSaldo,CD34)-CC35 | CE35: =IF(2=0,IF(personal_deudaEsFederal=1,personal_deudaEstudiantil,0),DW34) | CF35: =IF(2=0,personal_tasaDeudaEstudiantil,DX34) | CG35: =IF(2=0,0,DY34) | CH35: =IF(J35>=0.5,1,0) | CI35: =IF(AND(CH35=0,prestamos_pslfActivo=1,K35>=0.5,CE35>0),1,0) | CJ35: =CE35*CF35 | CK35: =MAX(prestamos_rapPagoMinimoAnual,IF(Y35<10000,0,MIN(0.1,INT(Y35/10000)/100))*Y35) | CL35: =IF(CE35<=0,0,IF(CH35=1,0,IF(CI35=1,MIN(CE35+CJ35,CK35),PMT(CF35,MAX(1,prestamos_plazoAnios-CG35),-CE35)))) | CM35: =IF(CE35<=0,0,IF(CH35=1,CE35+CJ35,IF(CI35=1,MAX(0,CE35-MAX(CL35-CJ35,MIN(600,CL35))),MAX(0,CE35*(1+CF35)-CL35)))) | CN35: =IF(2=0,0,CN34)+IF(CI35=1,12*MIN(1,K35),0) | CO35: =IF(AND(CI35=1,CN35>=prestamos_pslfPagos,CM35>0),CM35,0) | CP35: =CM35-CO35 | CQ35: =IF(AND(CE35>0,CH35=0,CI35=0),CG35+1,CG35) | CR35: =IF(2=0,IF(personal_deudaEsFederal=1,0,personal_deudaEstudiantil),EA34) | CS35: =IF(2=0,IF(personal_deudaEsFederal=1,prestamos_tasaPrivada,personal_tasaDeudaEstudiantil),EB34) | CT35: =IF(2=0,0,EC34) | CU35: =IF(OR(CR35<=0,CH35=1),0,PMT(CS35,MAX(1,prestamos_plazoAnios-CT35),-CR35)) | CV35: =IF(CR35<=0,0,IF(CH35=1,CR35*(1+CS35),MAX(0,CR35*(1+CS35)-CU35))) | CW35: =IF(AND(CR35>0,CH35=0),CT35+1,CT35) | CX35: =IF(2=0,0,ED34)*(1+general_tasaDeudaConsumo) | CY35: =L35*12*tiempos_travelGastoExtraMes*C35 | CZ35: =AJ35+CY35+CA35+CC35+CL35+CU35+I35+N35-BZ35-CB35 | DA35: =AH35-CZ35 | DB35: =IF(2=0,0,DB34)+DA35 | DC35: =AN35*vivienda_enganchePct+AN35*vivienda_cierrePct+general_reservaMeses/12*AJ35 | DD35: =IF(BB35=1,g_ret,IF(BD35>0,MIN(1,DC35/BD35),1)*g_cash+(1-IF(BD35>0,MIN(1,DC35/BD35),1))*g_ret) | DE35: =IF(DA35>=0,MIN(CX35,DA35),0) | DF35: =IF(DA35>=0,(1-general_tasaAhorro)*(DA35-DE35),0) | DG35: =IF(DA35>=0,DA35-DE35-DF35,0) | DH35: =MIN(personal_rothAnual,DG35) | DI35: =IF(AND(DA35>=0,BB35=1,BP35+BT35>0),MIN(vivienda_prepagoPct*(DG35-DH35),BP35+BT35),0) | DJ35: =MIN(DI35,BP35) | DK35: =IF(DA35<0,MIN(MAX(0,BD35),-DA35),0) | DL35: =IF(DA35<0,-DA35-DK35,0) | DM35: =IF(2=0,0,DZ34) | DN35: =IF(AND(DL35>0,J35>0),MIN(DL35,MIN(prestamos_topeAnualPosgrado*MIN(1,J35),MAX(0,prestamos_topeTotalPosgrado-DM35))),0) | DO35: =IF(AND(DL35>0,J35>0),DL35-DN35,0) | DP35: =IF(AND(DL35>0,J35<=0),DL35,0) | DQ35: =IF(DA35>=0,DG35-DH35-DI35,-DK35) | DR35: =BD35*(1+DD35)+DQ35*(1+DD35/2) | DS35: =IF(2=0,personal_retiroInicial,DS34)*(1+g_ret)+(O35+P35+DH35)*(1+g_ret/2) | DT35: =IF(BB35=1,BL35*(1+g_appr),0) | DU35: =BP35-DJ35 | DV35: =BT35-(DI35-DJ35) | DW35: =CP35+DN35 | DX35: =IF(DN35>0,(CP35*CF35+DN35*prestamos_tasaFederalPosgrado)/(CP35+DN35),CF35) | DY35: =IF(DN35>0,0,CQ35) | DZ35: =DM35+DN35 | EA35: =CV35+DO35 | EB35: =IF(DO35>0,(CV35*CS35+DO35*prestamos_tasaPrivada)/(CV35+DO35),CS35) | EC35: =IF(DO35>0,0,CW35) | ED35: =CX35-DE35+DP35 | EE35: =IF(IF(2=0,"",EE34)<>"",EE34,IF(AND(BB35=1,DU35<=0.5,DV35<=0.5,OR(BH35=0,BJ35=1)),A35,"")) | EF35: =DU35+DV35+DW35+EA35+ED35+CD35 | EG35: =DR35+DS35+DT35-EF35 | EH35: =EG35/(1+g_inf)^(A35+1-2026)
A36: 2030 | B36: 3 | C36: =(1+g_inf)^(A36-2026) | D36: =SUMPRODUCT($W$5:$W$29,$E$5:$E$29*(1+$F$5:$F$29)^(A36-2026)*$G$5:$G$29*$H$5:$H$29*(1-$N$5:$N$29*$O$5:$O$29))*g_salMult+SUMPRODUCT(($B$5:$B$29>=A36)*($B$5:$B$29<A36+1)*$I$5:$I$29)*g_salMult | E36: =SUMPRODUCT($W$5:$W$29,$E$5:$E$29*(1+$F$5:$F$29)^(A36-2026)*$G$5:$G$29*$H$5:$H$29*$M$5:$M$29)*g_salMult | F36: =SUMPRODUCT($W$5:$W$29,$E$5:$E$29*(1+$F$5:$F$29)^(A36-2026)*$G$5:$G$29*$H$5:$H$29*$N$5:$N$29*$O$5:$O$29)*g_salMult | G36: =SUMPRODUCT($W$5:$W$29,$P$5:$P$29*(1+$F$5:$F$29)^(A36-2026)) | H36: =SUMPRODUCT($W$5:$W$29,$Q$5:$Q$29*(1+$F$5:$F$29)^(A36-2026))+IF(personal_llcActivo=1,personal_llcNeto*(1+personal_llcCrecimiento)^3,0) | I36: =SUMPRODUCT($W$5:$W$29,$J$5:$J$29/($C$5:$C$29-$B$5:$B$29+($C$5:$C$29=$B$5:$B$29)))*C36 | J36: =SUMPRODUCT($W$5:$W$29,$K$5:$K$29) | K36: =SUMPRODUCT($W$5:$W$29,$L$5:$L$29) | L36: =SUMPRODUCT($W$5:$W$29,$N$5:$N$29) | M36: =IF(SUMPRODUCT($W$5:$W$29,$R$5:$R$29)>0,1,0) | N36: =SUMPRODUCT(($AO$5:$AO$24>=A36)*($AO$5:$AO$24<A36+1)*$AP$5:$AP$24)*C36+IF(3=0,IF(sel_loc<>"miami",personal_costoMudanzaInicial,0),0) | O36: =MIN(personal_aporte403bPct*D36,retiro_limite403b*C36) | P36: =MIN(personal_aporte403bPct,personal_match403bPct)*E36 | Q36: =IF(G36>0,MAX(0,G36-impuestos_scorpCostoAnual*C36),0) | R36: =Q36*impuestos_scorpSalarioPct/(1+impuestos_ssTasa+impuestos_medicareTasa) | S36: =impuestos_ssTasa*MIN(R36,MAX(0,impuestos_ssTope*C36-D36))+impuestos_medicareTasa*R36 | T36: =Q36-R36-S36 | U36: =D36+R36 | V36: =H36*0.9235 | W36: =IF(H36>0,2*impuestos_ssTasa*MIN(V36,MAX(0,impuestos_ssTope*C36-U36))+2*impuestos_medicareTasa*V36,0) | X36: =impuestos_ssTasa*MIN(U36,impuestos_ssTope*C36)+impuestos_medicareTasa*U36+impuestos_medicareAdicional*MAX(0,U36+H36*0.9235-impuestos_medicareUmbral) | Y36: =MAX(0,D36-O36+R36+T36+H36-W36/2) | Z36: =MAX(0,Y36-impuestos_deduccionEstandar*C36) | AA36: =MIN(0.2*MAX(0,T36+H36-W36/2)*MAX(0,MIN(1,1-(Z36-impuestos_qbiUmbral*C36)/(impuestos_qbiRango*C36))),0.2*Z36) | AB36: =MAX(0,Z36-AA36) | AC36: =SUMPRODUCT((AB36>tb_federalBrackets_lo*C36)*(AB36-tb_federalBrackets_lo*C36)*tb_federalBrackets_dr) | AD36: =MAX(0,Y36-impuestos_nyDeduccion*C36) | AE36: =CHOOSE(loc_taxcode,0,impuestos_ohTasa*MAX(0,Y36-impuestos_ohExento*C36)+impuestos_ohMunicipal*U36,SUMPRODUCT((AD36>tb_nyBrackets_lo*C36)*(AD36-tb_nyBrackets_lo*C36)*tb_nyBrackets_dr)+loc_nyc*SUMPRODUCT((AD36>tb_nycBrackets_lo*C36)*(AD36-tb_nycBrackets_lo*C36)*tb_nycBrackets_dr)) | AF36: =AC36+AE36+X36+W36 | AG36: =D36+F36+R36+T36+H36 | AH36: =AG36-AF36-O36 | AI36: =D36+F36+G36+H36 | AJ36: =loc_gastosVida*C36*g_gastos | AK36: =IF(3=0,personal_liquidoInicial,DR35) | AL36: =IF(3=0,0,BB35) | AM36: =CHOOSE(sel_cfgIdx,loc_precio_duplex,loc_precio_inlaw,loc_precio_dosCasas,loc_precio_casaAdu,loc_precio_multi) | AN36: =AM36*(1+g_appr)^(A36-2026) | AO36: =IF(AND(M36=1,vivienda_prestamoMedico=1),1,0) | AP36: =IF(AO36=1,0.05,vivienda_enganchePct) | AQ36: =AN36*(1-AP36) | AR36: =PMT(g_mortRate/12,vivienda_plazoHipoteca*12,-AQ36) | AS36: =INDEX(cfg_units,sel_cfgIdx) | AT36: =AS36*loc_rentaUnidad*(1+g_inf)^(A36-2026)*(1-vivienda_vacancia) | AU36: =AR36+AN36*loc_impuestoPropPct/12+AM36*loc_seguroPct*(1+vivienda_inflacionSeguro)^(A36-2026)/12+IF(AND(AO36=0,AP36<0.2),AQ36*vivienda_pmiTasa/12,0) | AV36: =AN36*AP36+AN36*vivienda_cierrePct+general_reservaMeses/12*AJ36 | AW36: =(IF(3=0,MIN(personal_irsSaldo,personal_irsPagoMensual*12),MIN(CD35,personal_irsPagoMensual*12))+IF(CE36>0,PMT(CF36,MAX(1,prestamos_plazoAnios-CG36),-CE36),0)+IF(CR36>0,PMT(CS36,MAX(1,prestamos_plazoAnios-CT36),-CR36),0))/12 | AX36: =IF(OR(sel_cfg="duplex",sel_cfg="multi",sel_cfg="dosCasas"),0.75*personal_aporteFamiliaMensual,0) | AY36: =AU36-0.75*AT36-AX36+AW36 | AZ36: =(D36+G36+H36+0.5*F36)/12 | BA36: =IF(AND(AL36=0,A36>=vivienda_anioMinCompra,J36<0.5,AI36>0,AK36>=AV36,AY36<=vivienda_dtiMax*AZ36),1,0) | BB36: =MAX(AL36,BA36) | BC36: =IF(BA36=1,A36,IF(3=0,"",BC35)) | BD36: =AK36-IF(BA36=1,AN36*AP36+AN36*vivienda_cierrePct,0) | BE36: =IF(BA36=1,AN36,IF(3=0,0,BE35)) | BF36: =IF(BA36=1,AR36,IF(3=0,0,BF35)) | BG36: =IF(BA36=1,IF(AND(AO36=0,AP36<0.2),1,0),IF(3=0,0,BY35)) | BH36: =IF(sel_cfg="casaAdu",1,0) | BI36: =IF(AND(BB36=1,BH36=1,IF(3=0,0,BJ35)=0,A36>=IF(BC36="",9999,BC36)+vivienda_aduRetrasoAnios),1,0) | BJ36: =MAX(IF(3=0,0,BJ35),BI36) | BK36: =IF(BI36=1,PMT((g_mortRate+0.005)/12,180,-loc_precio_aduCosto*C36),IF(3=0,0,BK35)) | BL36: =IF(BA36=1,AN36,IF(3=0,0,DT35))+IF(BI36=1,loc_precio_aduCosto*C36,0) | BM36: =IF(BA36=1,AQ36,IF(3=0,0,DU35)) | BN36: =IF(BM36<=0,0,FV(g_mortRate/12,12,BF36,-BM36)) | BO36: =IF(BM36<=0,0,12*BF36+MIN(0,BN36)) | BP36: =MAX(0,BN36) | BQ36: =IF(BI36=1,loc_precio_aduCosto*C36,IF(3=0,0,DV35)) | BR36: =IF(BQ36<=0,0,FV((g_mortRate+0.005)/12,12,BK36,-BQ36)) | BS36: =IF(BQ36<=0,0,12*BK36+MIN(0,BR36)) | BT36: =MAX(0,BR36) | BU36: =IF(BB36=1,AM36*loc_seguroPct*(1+vivienda_inflacionSeguro)^(A36-2026)*IF(BJ36=1,1+loc_precio_aduCosto/AM36,1),0) | BV36: =BL36*loc_impuestoPropPct | BW36: =BL36*vivienda_mantenimientoPct | BX36: =IF(AND(BG36=1,BP36>0.8*BE36),BE36*(1-vivienda_enganchePct)*vivienda_pmiTasa,0) | BY36: =IF(AND(BG36=1,BP36>0.8*BE36),1,0) | BZ36: =IF(BB36=1,AS36*loc_rentaUnidad*12*C36*(1-vivienda_vacancia)*(1-vivienda_gestionPct),0) | CA36: =IF(BB36=1,BO36+BS36+BU36+BV36+BW36+BX36,loc_rentaMensual*12*C36) | CB36: =IF(BB36=1,personal_aporteFamiliaMensual*12,0) | CC36: =MIN(IF(3=0,personal_irsSaldo,CD35),personal_irsPagoMensual*12) | CD36: =IF(3=0,personal_irsSaldo,CD35)-CC36 | CE36: =IF(3=0,IF(personal_deudaEsFederal=1,personal_deudaEstudiantil,0),DW35) | CF36: =IF(3=0,personal_tasaDeudaEstudiantil,DX35) | CG36: =IF(3=0,0,DY35) | CH36: =IF(J36>=0.5,1,0) | CI36: =IF(AND(CH36=0,prestamos_pslfActivo=1,K36>=0.5,CE36>0),1,0) | CJ36: =CE36*CF36 | CK36: =MAX(prestamos_rapPagoMinimoAnual,IF(Y36<10000,0,MIN(0.1,INT(Y36/10000)/100))*Y36) | CL36: =IF(CE36<=0,0,IF(CH36=1,0,IF(CI36=1,MIN(CE36+CJ36,CK36),PMT(CF36,MAX(1,prestamos_plazoAnios-CG36),-CE36)))) | CM36: =IF(CE36<=0,0,IF(CH36=1,CE36+CJ36,IF(CI36=1,MAX(0,CE36-MAX(CL36-CJ36,MIN(600,CL36))),MAX(0,CE36*(1+CF36)-CL36)))) | CN36: =IF(3=0,0,CN35)+IF(CI36=1,12*MIN(1,K36),0) | CO36: =IF(AND(CI36=1,CN36>=prestamos_pslfPagos,CM36>0),CM36,0) | CP36: =CM36-CO36 | CQ36: =IF(AND(CE36>0,CH36=0,CI36=0),CG36+1,CG36) | CR36: =IF(3=0,IF(personal_deudaEsFederal=1,0,personal_deudaEstudiantil),EA35) | CS36: =IF(3=0,IF(personal_deudaEsFederal=1,prestamos_tasaPrivada,personal_tasaDeudaEstudiantil),EB35) | CT36: =IF(3=0,0,EC35) | CU36: =IF(OR(CR36<=0,CH36=1),0,PMT(CS36,MAX(1,prestamos_plazoAnios-CT36),-CR36)) | CV36: =IF(CR36<=0,0,IF(CH36=1,CR36*(1+CS36),MAX(0,CR36*(1+CS36)-CU36))) | CW36: =IF(AND(CR36>0,CH36=0),CT36+1,CT36) | CX36: =IF(3=0,0,ED35)*(1+general_tasaDeudaConsumo) | CY36: =L36*12*tiempos_travelGastoExtraMes*C36 | CZ36: =AJ36+CY36+CA36+CC36+CL36+CU36+I36+N36-BZ36-CB36 | DA36: =AH36-CZ36 | DB36: =IF(3=0,0,DB35)+DA36 | DC36: =AN36*vivienda_enganchePct+AN36*vivienda_cierrePct+general_reservaMeses/12*AJ36 | DD36: =IF(BB36=1,g_ret,IF(BD36>0,MIN(1,DC36/BD36),1)*g_cash+(1-IF(BD36>0,MIN(1,DC36/BD36),1))*g_ret) | DE36: =IF(DA36>=0,MIN(CX36,DA36),0) | DF36: =IF(DA36>=0,(1-general_tasaAhorro)*(DA36-DE36),0) | DG36: =IF(DA36>=0,DA36-DE36-DF36,0) | DH36: =MIN(personal_rothAnual,DG36) | DI36: =IF(AND(DA36>=0,BB36=1,BP36+BT36>0),MIN(vivienda_prepagoPct*(DG36-DH36),BP36+BT36),0) | DJ36: =MIN(DI36,BP36) | DK36: =IF(DA36<0,MIN(MAX(0,BD36),-DA36),0) | DL36: =IF(DA36<0,-DA36-DK36,0) | DM36: =IF(3=0,0,DZ35) | DN36: =IF(AND(DL36>0,J36>0),MIN(DL36,MIN(prestamos_topeAnualPosgrado*MIN(1,J36),MAX(0,prestamos_topeTotalPosgrado-DM36))),0) | DO36: =IF(AND(DL36>0,J36>0),DL36-DN36,0) | DP36: =IF(AND(DL36>0,J36<=0),DL36,0) | DQ36: =IF(DA36>=0,DG36-DH36-DI36,-DK36) | DR36: =BD36*(1+DD36)+DQ36*(1+DD36/2) | DS36: =IF(3=0,personal_retiroInicial,DS35)*(1+g_ret)+(O36+P36+DH36)*(1+g_ret/2) | DT36: =IF(BB36=1,BL36*(1+g_appr),0) | DU36: =BP36-DJ36 | DV36: =BT36-(DI36-DJ36) | DW36: =CP36+DN36 | DX36: =IF(DN36>0,(CP36*CF36+DN36*prestamos_tasaFederalPosgrado)/(CP36+DN36),CF36) | DY36: =IF(DN36>0,0,CQ36) | DZ36: =DM36+DN36 | EA36: =CV36+DO36 | EB36: =IF(DO36>0,(CV36*CS36+DO36*prestamos_tasaPrivada)/(CV36+DO36),CS36) | EC36: =IF(DO36>0,0,CW36) | ED36: =CX36-DE36+DP36 | EE36: =IF(IF(3=0,"",EE35)<>"",EE35,IF(AND(BB36=1,DU36<=0.5,DV36<=0.5,OR(BH36=0,BJ36=1)),A36,"")) | EF36: =DU36+DV36+DW36+EA36+ED36+CD36 | EG36: =DR36+DS36+DT36-EF36 | EH36: =EG36/(1+g_inf)^(A36+1-2026)
A37: 2031 | B37: 4 | C37: =(1+g_inf)^(A37-2026) | D37: =SUMPRODUCT($X$5:$X$29,$E$5:$E$29*(1+$F$5:$F$29)^(A37-2026)*$G$5:$G$29*$H$5:$H$29*(1-$N$5:$N$29*$O$5:$O$29))*g_salMult+SUMPRODUCT(($B$5:$B$29>=A37)*($B$5:$B$29<A37+1)*$I$5:$I$29)*g_salMult | E37: =SUMPRODUCT($X$5:$X$29,$E$5:$E$29*(1+$F$5:$F$29)^(A37-2026)*$G$5:$G$29*$H$5:$H$29*$M$5:$M$29)*g_salMult | F37: =SUMPRODUCT($X$5:$X$29,$E$5:$E$29*(1+$F$5:$F$29)^(A37-2026)*$G$5:$G$29*$H$5:$H$29*$N$5:$N$29*$O$5:$O$29)*g_salMult | G37: =SUMPRODUCT($X$5:$X$29,$P$5:$P$29*(1+$F$5:$F$29)^(A37-2026)) | H37: =SUMPRODUCT($X$5:$X$29,$Q$5:$Q$29*(1+$F$5:$F$29)^(A37-2026))+IF(personal_llcActivo=1,personal_llcNeto*(1+personal_llcCrecimiento)^4,0) | I37: =SUMPRODUCT($X$5:$X$29,$J$5:$J$29/($C$5:$C$29-$B$5:$B$29+($C$5:$C$29=$B$5:$B$29)))*C37 | J37: =SUMPRODUCT($X$5:$X$29,$K$5:$K$29) | K37: =SUMPRODUCT($X$5:$X$29,$L$5:$L$29) | L37: =SUMPRODUCT($X$5:$X$29,$N$5:$N$29) | M37: =IF(SUMPRODUCT($X$5:$X$29,$R$5:$R$29)>0,1,0) | N37: =SUMPRODUCT(($AO$5:$AO$24>=A37)*($AO$5:$AO$24<A37+1)*$AP$5:$AP$24)*C37+IF(4=0,IF(sel_loc<>"miami",personal_costoMudanzaInicial,0),0) | O37: =MIN(personal_aporte403bPct*D37,retiro_limite403b*C37) | P37: =MIN(personal_aporte403bPct,personal_match403bPct)*E37 | Q37: =IF(G37>0,MAX(0,G37-impuestos_scorpCostoAnual*C37),0) | R37: =Q37*impuestos_scorpSalarioPct/(1+impuestos_ssTasa+impuestos_medicareTasa) | S37: =impuestos_ssTasa*MIN(R37,MAX(0,impuestos_ssTope*C37-D37))+impuestos_medicareTasa*R37 | T37: =Q37-R37-S37 | U37: =D37+R37 | V37: =H37*0.9235 | W37: =IF(H37>0,2*impuestos_ssTasa*MIN(V37,MAX(0,impuestos_ssTope*C37-U37))+2*impuestos_medicareTasa*V37,0) | X37: =impuestos_ssTasa*MIN(U37,impuestos_ssTope*C37)+impuestos_medicareTasa*U37+impuestos_medicareAdicional*MAX(0,U37+H37*0.9235-impuestos_medicareUmbral) | Y37: =MAX(0,D37-O37+R37+T37+H37-W37/2) | Z37: =MAX(0,Y37-impuestos_deduccionEstandar*C37) | AA37: =MIN(0.2*MAX(0,T37+H37-W37/2)*MAX(0,MIN(1,1-(Z37-impuestos_qbiUmbral*C37)/(impuestos_qbiRango*C37))),0.2*Z37) | AB37: =MAX(0,Z37-AA37) | AC37: =SUMPRODUCT((AB37>tb_federalBrackets_lo*C37)*(AB37-tb_federalBrackets_lo*C37)*tb_federalBrackets_dr) | AD37: =MAX(0,Y37-impuestos_nyDeduccion*C37) | AE37: =CHOOSE(loc_taxcode,0,impuestos_ohTasa*MAX(0,Y37-impuestos_ohExento*C37)+impuestos_ohMunicipal*U37,SUMPRODUCT((AD37>tb_nyBrackets_lo*C37)*(AD37-tb_nyBrackets_lo*C37)*tb_nyBrackets_dr)+loc_nyc*SUMPRODUCT((AD37>tb_nycBrackets_lo*C37)*(AD37-tb_nycBrackets_lo*C37)*tb_nycBrackets_dr)) | AF37: =AC37+AE37+X37+W37 | AG37: =D37+F37+R37+T37+H37 | AH37: =AG37-AF37-O37 | AI37: =D37+F37+G37+H37 | AJ37: =loc_gastosVida*C37*g_gastos | AK37: =IF(4=0,personal_liquidoInicial,DR36) | AL37: =IF(4=0,0,BB36) | AM37: =CHOOSE(sel_cfgIdx,loc_precio_duplex,loc_precio_inlaw,loc_precio_dosCasas,loc_precio_casaAdu,loc_precio_multi) | AN37: =AM37*(1+g_appr)^(A37-2026) | AO37: =IF(AND(M37=1,vivienda_prestamoMedico=1),1,0) | AP37: =IF(AO37=1,0.05,vivienda_enganchePct) | AQ37: =AN37*(1-AP37) | AR37: =PMT(g_mortRate/12,vivienda_plazoHipoteca*12,-AQ37) | AS37: =INDEX(cfg_units,sel_cfgIdx) | AT37: =AS37*loc_rentaUnidad*(1+g_inf)^(A37-2026)*(1-vivienda_vacancia) | AU37: =AR37+AN37*loc_impuestoPropPct/12+AM37*loc_seguroPct*(1+vivienda_inflacionSeguro)^(A37-2026)/12+IF(AND(AO37=0,AP37<0.2),AQ37*vivienda_pmiTasa/12,0) | AV37: =AN37*AP37+AN37*vivienda_cierrePct+general_reservaMeses/12*AJ37 | AW37: =(IF(4=0,MIN(personal_irsSaldo,personal_irsPagoMensual*12),MIN(CD36,personal_irsPagoMensual*12))+IF(CE37>0,PMT(CF37,MAX(1,prestamos_plazoAnios-CG37),-CE37),0)+IF(CR37>0,PMT(CS37,MAX(1,prestamos_plazoAnios-CT37),-CR37),0))/12 | AX37: =IF(OR(sel_cfg="duplex",sel_cfg="multi",sel_cfg="dosCasas"),0.75*personal_aporteFamiliaMensual,0) | AY37: =AU37-0.75*AT37-AX37+AW37 | AZ37: =(D37+G37+H37+0.5*F37)/12 | BA37: =IF(AND(AL37=0,A37>=vivienda_anioMinCompra,J37<0.5,AI37>0,AK37>=AV37,AY37<=vivienda_dtiMax*AZ37),1,0) | BB37: =MAX(AL37,BA37) | BC37: =IF(BA37=1,A37,IF(4=0,"",BC36)) | BD37: =AK37-IF(BA37=1,AN37*AP37+AN37*vivienda_cierrePct,0) | BE37: =IF(BA37=1,AN37,IF(4=0,0,BE36)) | BF37: =IF(BA37=1,AR37,IF(4=0,0,BF36)) | BG37: =IF(BA37=1,IF(AND(AO37=0,AP37<0.2),1,0),IF(4=0,0,BY36)) | BH37: =IF(sel_cfg="casaAdu",1,0) | BI37: =IF(AND(BB37=1,BH37=1,IF(4=0,0,BJ36)=0,A37>=IF(BC37="",9999,BC37)+vivienda_aduRetrasoAnios),1,0) | BJ37: =MAX(IF(4=0,0,BJ36),BI37) | BK37: =IF(BI37=1,PMT((g_mortRate+0.005)/12,180,-loc_precio_aduCosto*C37),IF(4=0,0,BK36)) | BL37: =IF(BA37=1,AN37,IF(4=0,0,DT36))+IF(BI37=1,loc_precio_aduCosto*C37,0) | BM37: =IF(BA37=1,AQ37,IF(4=0,0,DU36)) | BN37: =IF(BM37<=0,0,FV(g_mortRate/12,12,BF37,-BM37)) | BO37: =IF(BM37<=0,0,12*BF37+MIN(0,BN37)) | BP37: =MAX(0,BN37) | BQ37: =IF(BI37=1,loc_precio_aduCosto*C37,IF(4=0,0,DV36)) | BR37: =IF(BQ37<=0,0,FV((g_mortRate+0.005)/12,12,BK37,-BQ37)) | BS37: =IF(BQ37<=0,0,12*BK37+MIN(0,BR37)) | BT37: =MAX(0,BR37) | BU37: =IF(BB37=1,AM37*loc_seguroPct*(1+vivienda_inflacionSeguro)^(A37-2026)*IF(BJ37=1,1+loc_precio_aduCosto/AM37,1),0) | BV37: =BL37*loc_impuestoPropPct | BW37: =BL37*vivienda_mantenimientoPct | BX37: =IF(AND(BG37=1,BP37>0.8*BE37),BE37*(1-vivienda_enganchePct)*vivienda_pmiTasa,0) | BY37: =IF(AND(BG37=1,BP37>0.8*BE37),1,0) | BZ37: =IF(BB37=1,AS37*loc_rentaUnidad*12*C37*(1-vivienda_vacancia)*(1-vivienda_gestionPct),0) | CA37: =IF(BB37=1,BO37+BS37+BU37+BV37+BW37+BX37,loc_rentaMensual*12*C37) | CB37: =IF(BB37=1,personal_aporteFamiliaMensual*12,0) | CC37: =MIN(IF(4=0,personal_irsSaldo,CD36),personal_irsPagoMensual*12) | CD37: =IF(4=0,personal_irsSaldo,CD36)-CC37 | CE37: =IF(4=0,IF(personal_deudaEsFederal=1,personal_deudaEstudiantil,0),DW36) | CF37: =IF(4=0,personal_tasaDeudaEstudiantil,DX36) | CG37: =IF(4=0,0,DY36) | CH37: =IF(J37>=0.5,1,0) | CI37: =IF(AND(CH37=0,prestamos_pslfActivo=1,K37>=0.5,CE37>0),1,0) | CJ37: =CE37*CF37 | CK37: =MAX(prestamos_rapPagoMinimoAnual,IF(Y37<10000,0,MIN(0.1,INT(Y37/10000)/100))*Y37) | CL37: =IF(CE37<=0,0,IF(CH37=1,0,IF(CI37=1,MIN(CE37+CJ37,CK37),PMT(CF37,MAX(1,prestamos_plazoAnios-CG37),-CE37)))) | CM37: =IF(CE37<=0,0,IF(CH37=1,CE37+CJ37,IF(CI37=1,MAX(0,CE37-MAX(CL37-CJ37,MIN(600,CL37))),MAX(0,CE37*(1+CF37)-CL37)))) | CN37: =IF(4=0,0,CN36)+IF(CI37=1,12*MIN(1,K37),0) | CO37: =IF(AND(CI37=1,CN37>=prestamos_pslfPagos,CM37>0),CM37,0) | CP37: =CM37-CO37 | CQ37: =IF(AND(CE37>0,CH37=0,CI37=0),CG37+1,CG37) | CR37: =IF(4=0,IF(personal_deudaEsFederal=1,0,personal_deudaEstudiantil),EA36) | CS37: =IF(4=0,IF(personal_deudaEsFederal=1,prestamos_tasaPrivada,personal_tasaDeudaEstudiantil),EB36) | CT37: =IF(4=0,0,EC36) | CU37: =IF(OR(CR37<=0,CH37=1),0,PMT(CS37,MAX(1,prestamos_plazoAnios-CT37),-CR37)) | CV37: =IF(CR37<=0,0,IF(CH37=1,CR37*(1+CS37),MAX(0,CR37*(1+CS37)-CU37))) | CW37: =IF(AND(CR37>0,CH37=0),CT37+1,CT37) | CX37: =IF(4=0,0,ED36)*(1+general_tasaDeudaConsumo) | CY37: =L37*12*tiempos_travelGastoExtraMes*C37 | CZ37: =AJ37+CY37+CA37+CC37+CL37+CU37+I37+N37-BZ37-CB37 | DA37: =AH37-CZ37 | DB37: =IF(4=0,0,DB36)+DA37 | DC37: =AN37*vivienda_enganchePct+AN37*vivienda_cierrePct+general_reservaMeses/12*AJ37 | DD37: =IF(BB37=1,g_ret,IF(BD37>0,MIN(1,DC37/BD37),1)*g_cash+(1-IF(BD37>0,MIN(1,DC37/BD37),1))*g_ret) | DE37: =IF(DA37>=0,MIN(CX37,DA37),0) | DF37: =IF(DA37>=0,(1-general_tasaAhorro)*(DA37-DE37),0) | DG37: =IF(DA37>=0,DA37-DE37-DF37,0) | DH37: =MIN(personal_rothAnual,DG37) | DI37: =IF(AND(DA37>=0,BB37=1,BP37+BT37>0),MIN(vivienda_prepagoPct*(DG37-DH37),BP37+BT37),0) | DJ37: =MIN(DI37,BP37) | DK37: =IF(DA37<0,MIN(MAX(0,BD37),-DA37),0) | DL37: =IF(DA37<0,-DA37-DK37,0) | DM37: =IF(4=0,0,DZ36) | DN37: =IF(AND(DL37>0,J37>0),MIN(DL37,MIN(prestamos_topeAnualPosgrado*MIN(1,J37),MAX(0,prestamos_topeTotalPosgrado-DM37))),0) | DO37: =IF(AND(DL37>0,J37>0),DL37-DN37,0) | DP37: =IF(AND(DL37>0,J37<=0),DL37,0) | DQ37: =IF(DA37>=0,DG37-DH37-DI37,-DK37) | DR37: =BD37*(1+DD37)+DQ37*(1+DD37/2) | DS37: =IF(4=0,personal_retiroInicial,DS36)*(1+g_ret)+(O37+P37+DH37)*(1+g_ret/2) | DT37: =IF(BB37=1,BL37*(1+g_appr),0) | DU37: =BP37-DJ37 | DV37: =BT37-(DI37-DJ37) | DW37: =CP37+DN37 | DX37: =IF(DN37>0,(CP37*CF37+DN37*prestamos_tasaFederalPosgrado)/(CP37+DN37),CF37) | DY37: =IF(DN37>0,0,CQ37) | DZ37: =DM37+DN37 | EA37: =CV37+DO37 | EB37: =IF(DO37>0,(CV37*CS37+DO37*prestamos_tasaPrivada)/(CV37+DO37),CS37) | EC37: =IF(DO37>0,0,CW37) | ED37: =CX37-DE37+DP37 | EE37: =IF(IF(4=0,"",EE36)<>"",EE36,IF(AND(BB37=1,DU37<=0.5,DV37<=0.5,OR(BH37=0,BJ37=1)),A37,"")) | EF37: =DU37+DV37+DW37+EA37+ED37+CD37 | EG37: =DR37+DS37+DT37-EF37 | EH37: =EG37/(1+g_inf)^(A37+1-2026)
A38: 2032 | B38: 5 | C38: =(1+g_inf)^(A38-2026) | D38: =SUMPRODUCT($Y$5:$Y$29,$E$5:$E$29*(1+$F$5:$F$29)^(A38-2026)*$G$5:$G$29*$H$5:$H$29*(1-$N$5:$N$29*$O$5:$O$29))*g_salMult+SUMPRODUCT(($B$5:$B$29>=A38)*($B$5:$B$29<A38+1)*$I$5:$I$29)*g_salMult | E38: =SUMPRODUCT($Y$5:$Y$29,$E$5:$E$29*(1+$F$5:$F$29)^(A38-2026)*$G$5:$G$29*$H$5:$H$29*$M$5:$M$29)*g_salMult | F38: =SUMPRODUCT($Y$5:$Y$29,$E$5:$E$29*(1+$F$5:$F$29)^(A38-2026)*$G$5:$G$29*$H$5:$H$29*$N$5:$N$29*$O$5:$O$29)*g_salMult | G38: =SUMPRODUCT($Y$5:$Y$29,$P$5:$P$29*(1+$F$5:$F$29)^(A38-2026)) | H38: =SUMPRODUCT($Y$5:$Y$29,$Q$5:$Q$29*(1+$F$5:$F$29)^(A38-2026))+IF(personal_llcActivo=1,personal_llcNeto*(1+personal_llcCrecimiento)^5,0) | I38: =SUMPRODUCT($Y$5:$Y$29,$J$5:$J$29/($C$5:$C$29-$B$5:$B$29+($C$5:$C$29=$B$5:$B$29)))*C38 | J38: =SUMPRODUCT($Y$5:$Y$29,$K$5:$K$29) | K38: =SUMPRODUCT($Y$5:$Y$29,$L$5:$L$29) | L38: =SUMPRODUCT($Y$5:$Y$29,$N$5:$N$29) | M38: =IF(SUMPRODUCT($Y$5:$Y$29,$R$5:$R$29)>0,1,0) | N38: =SUMPRODUCT(($AO$5:$AO$24>=A38)*($AO$5:$AO$24<A38+1)*$AP$5:$AP$24)*C38+IF(5=0,IF(sel_loc<>"miami",personal_costoMudanzaInicial,0),0) | O38: =MIN(personal_aporte403bPct*D38,retiro_limite403b*C38) | P38: =MIN(personal_aporte403bPct,personal_match403bPct)*E38 | Q38: =IF(G38>0,MAX(0,G38-impuestos_scorpCostoAnual*C38),0) | R38: =Q38*impuestos_scorpSalarioPct/(1+impuestos_ssTasa+impuestos_medicareTasa) | S38: =impuestos_ssTasa*MIN(R38,MAX(0,impuestos_ssTope*C38-D38))+impuestos_medicareTasa*R38 | T38: =Q38-R38-S38 | U38: =D38+R38 | V38: =H38*0.9235 | W38: =IF(H38>0,2*impuestos_ssTasa*MIN(V38,MAX(0,impuestos_ssTope*C38-U38))+2*impuestos_medicareTasa*V38,0) | X38: =impuestos_ssTasa*MIN(U38,impuestos_ssTope*C38)+impuestos_medicareTasa*U38+impuestos_medicareAdicional*MAX(0,U38+H38*0.9235-impuestos_medicareUmbral) | Y38: =MAX(0,D38-O38+R38+T38+H38-W38/2) | Z38: =MAX(0,Y38-impuestos_deduccionEstandar*C38) | AA38: =MIN(0.2*MAX(0,T38+H38-W38/2)*MAX(0,MIN(1,1-(Z38-impuestos_qbiUmbral*C38)/(impuestos_qbiRango*C38))),0.2*Z38) | AB38: =MAX(0,Z38-AA38) | AC38: =SUMPRODUCT((AB38>tb_federalBrackets_lo*C38)*(AB38-tb_federalBrackets_lo*C38)*tb_federalBrackets_dr) | AD38: =MAX(0,Y38-impuestos_nyDeduccion*C38) | AE38: =CHOOSE(loc_taxcode,0,impuestos_ohTasa*MAX(0,Y38-impuestos_ohExento*C38)+impuestos_ohMunicipal*U38,SUMPRODUCT((AD38>tb_nyBrackets_lo*C38)*(AD38-tb_nyBrackets_lo*C38)*tb_nyBrackets_dr)+loc_nyc*SUMPRODUCT((AD38>tb_nycBrackets_lo*C38)*(AD38-tb_nycBrackets_lo*C38)*tb_nycBrackets_dr)) | AF38: =AC38+AE38+X38+W38 | AG38: =D38+F38+R38+T38+H38 | AH38: =AG38-AF38-O38 | AI38: =D38+F38+G38+H38 | AJ38: =loc_gastosVida*C38*g_gastos | AK38: =IF(5=0,personal_liquidoInicial,DR37) | AL38: =IF(5=0,0,BB37) | AM38: =CHOOSE(sel_cfgIdx,loc_precio_duplex,loc_precio_inlaw,loc_precio_dosCasas,loc_precio_casaAdu,loc_precio_multi) | AN38: =AM38*(1+g_appr)^(A38-2026) | AO38: =IF(AND(M38=1,vivienda_prestamoMedico=1),1,0) | AP38: =IF(AO38=1,0.05,vivienda_enganchePct) | AQ38: =AN38*(1-AP38) | AR38: =PMT(g_mortRate/12,vivienda_plazoHipoteca*12,-AQ38) | AS38: =INDEX(cfg_units,sel_cfgIdx) | AT38: =AS38*loc_rentaUnidad*(1+g_inf)^(A38-2026)*(1-vivienda_vacancia) | AU38: =AR38+AN38*loc_impuestoPropPct/12+AM38*loc_seguroPct*(1+vivienda_inflacionSeguro)^(A38-2026)/12+IF(AND(AO38=0,AP38<0.2),AQ38*vivienda_pmiTasa/12,0) | AV38: =AN38*AP38+AN38*vivienda_cierrePct+general_reservaMeses/12*AJ38 | AW38: =(IF(5=0,MIN(personal_irsSaldo,personal_irsPagoMensual*12),MIN(CD37,personal_irsPagoMensual*12))+IF(CE38>0,PMT(CF38,MAX(1,prestamos_plazoAnios-CG38),-CE38),0)+IF(CR38>0,PMT(CS38,MAX(1,prestamos_plazoAnios-CT38),-CR38),0))/12 | AX38: =IF(OR(sel_cfg="duplex",sel_cfg="multi",sel_cfg="dosCasas"),0.75*personal_aporteFamiliaMensual,0) | AY38: =AU38-0.75*AT38-AX38+AW38 | AZ38: =(D38+G38+H38+0.5*F38)/12 | BA38: =IF(AND(AL38=0,A38>=vivienda_anioMinCompra,J38<0.5,AI38>0,AK38>=AV38,AY38<=vivienda_dtiMax*AZ38),1,0) | BB38: =MAX(AL38,BA38) | BC38: =IF(BA38=1,A38,IF(5=0,"",BC37)) | BD38: =AK38-IF(BA38=1,AN38*AP38+AN38*vivienda_cierrePct,0) | BE38: =IF(BA38=1,AN38,IF(5=0,0,BE37)) | BF38: =IF(BA38=1,AR38,IF(5=0,0,BF37)) | BG38: =IF(BA38=1,IF(AND(AO38=0,AP38<0.2),1,0),IF(5=0,0,BY37)) | BH38: =IF(sel_cfg="casaAdu",1,0) | BI38: =IF(AND(BB38=1,BH38=1,IF(5=0,0,BJ37)=0,A38>=IF(BC38="",9999,BC38)+vivienda_aduRetrasoAnios),1,0) | BJ38: =MAX(IF(5=0,0,BJ37),BI38) | BK38: =IF(BI38=1,PMT((g_mortRate+0.005)/12,180,-loc_precio_aduCosto*C38),IF(5=0,0,BK37)) | BL38: =IF(BA38=1,AN38,IF(5=0,0,DT37))+IF(BI38=1,loc_precio_aduCosto*C38,0) | BM38: =IF(BA38=1,AQ38,IF(5=0,0,DU37)) | BN38: =IF(BM38<=0,0,FV(g_mortRate/12,12,BF38,-BM38)) | BO38: =IF(BM38<=0,0,12*BF38+MIN(0,BN38)) | BP38: =MAX(0,BN38) | BQ38: =IF(BI38=1,loc_precio_aduCosto*C38,IF(5=0,0,DV37)) | BR38: =IF(BQ38<=0,0,FV((g_mortRate+0.005)/12,12,BK38,-BQ38)) | BS38: =IF(BQ38<=0,0,12*BK38+MIN(0,BR38)) | BT38: =MAX(0,BR38) | BU38: =IF(BB38=1,AM38*loc_seguroPct*(1+vivienda_inflacionSeguro)^(A38-2026)*IF(BJ38=1,1+loc_precio_aduCosto/AM38,1),0) | BV38: =BL38*loc_impuestoPropPct | BW38: =BL38*vivienda_mantenimientoPct | BX38: =IF(AND(BG38=1,BP38>0.8*BE38),BE38*(1-vivienda_enganchePct)*vivienda_pmiTasa,0) | BY38: =IF(AND(BG38=1,BP38>0.8*BE38),1,0) | BZ38: =IF(BB38=1,AS38*loc_rentaUnidad*12*C38*(1-vivienda_vacancia)*(1-vivienda_gestionPct),0) | CA38: =IF(BB38=1,BO38+BS38+BU38+BV38+BW38+BX38,loc_rentaMensual*12*C38) | CB38: =IF(BB38=1,personal_aporteFamiliaMensual*12,0) | CC38: =MIN(IF(5=0,personal_irsSaldo,CD37),personal_irsPagoMensual*12) | CD38: =IF(5=0,personal_irsSaldo,CD37)-CC38 | CE38: =IF(5=0,IF(personal_deudaEsFederal=1,personal_deudaEstudiantil,0),DW37) | CF38: =IF(5=0,personal_tasaDeudaEstudiantil,DX37) | CG38: =IF(5=0,0,DY37) | CH38: =IF(J38>=0.5,1,0) | CI38: =IF(AND(CH38=0,prestamos_pslfActivo=1,K38>=0.5,CE38>0),1,0) | CJ38: =CE38*CF38 | CK38: =MAX(prestamos_rapPagoMinimoAnual,IF(Y38<10000,0,MIN(0.1,INT(Y38/10000)/100))*Y38) | CL38: =IF(CE38<=0,0,IF(CH38=1,0,IF(CI38=1,MIN(CE38+CJ38,CK38),PMT(CF38,MAX(1,prestamos_plazoAnios-CG38),-CE38)))) | CM38: =IF(CE38<=0,0,IF(CH38=1,CE38+CJ38,IF(CI38=1,MAX(0,CE38-MAX(CL38-CJ38,MIN(600,CL38))),MAX(0,CE38*(1+CF38)-CL38)))) | CN38: =IF(5=0,0,CN37)+IF(CI38=1,12*MIN(1,K38),0) | CO38: =IF(AND(CI38=1,CN38>=prestamos_pslfPagos,CM38>0),CM38,0) | CP38: =CM38-CO38 | CQ38: =IF(AND(CE38>0,CH38=0,CI38=0),CG38+1,CG38) | CR38: =IF(5=0,IF(personal_deudaEsFederal=1,0,personal_deudaEstudiantil),EA37) | CS38: =IF(5=0,IF(personal_deudaEsFederal=1,prestamos_tasaPrivada,personal_tasaDeudaEstudiantil),EB37) | CT38: =IF(5=0,0,EC37) | CU38: =IF(OR(CR38<=0,CH38=1),0,PMT(CS38,MAX(1,prestamos_plazoAnios-CT38),-CR38)) | CV38: =IF(CR38<=0,0,IF(CH38=1,CR38*(1+CS38),MAX(0,CR38*(1+CS38)-CU38))) | CW38: =IF(AND(CR38>0,CH38=0),CT38+1,CT38) | CX38: =IF(5=0,0,ED37)*(1+general_tasaDeudaConsumo) | CY38: =L38*12*tiempos_travelGastoExtraMes*C38 | CZ38: =AJ38+CY38+CA38+CC38+CL38+CU38+I38+N38-BZ38-CB38 | DA38: =AH38-CZ38 | DB38: =IF(5=0,0,DB37)+DA38 | DC38: =AN38*vivienda_enganchePct+AN38*vivienda_cierrePct+general_reservaMeses/12*AJ38 | DD38: =IF(BB38=1,g_ret,IF(BD38>0,MIN(1,DC38/BD38),1)*g_cash+(1-IF(BD38>0,MIN(1,DC38/BD38),1))*g_ret) | DE38: =IF(DA38>=0,MIN(CX38,DA38),0) | DF38: =IF(DA38>=0,(1-general_tasaAhorro)*(DA38-DE38),0) | DG38: =IF(DA38>=0,DA38-DE38-DF38,0) | DH38: =MIN(personal_rothAnual,DG38) | DI38: =IF(AND(DA38>=0,BB38=1,BP38+BT38>0),MIN(vivienda_prepagoPct*(DG38-DH38),BP38+BT38),0) | DJ38: =MIN(DI38,BP38) | DK38: =IF(DA38<0,MIN(MAX(0,BD38),-DA38),0) | DL38: =IF(DA38<0,-DA38-DK38,0) | DM38: =IF(5=0,0,DZ37) | DN38: =IF(AND(DL38>0,J38>0),MIN(DL38,MIN(prestamos_topeAnualPosgrado*MIN(1,J38),MAX(0,prestamos_topeTotalPosgrado-DM38))),0) | DO38: =IF(AND(DL38>0,J38>0),DL38-DN38,0) | DP38: =IF(AND(DL38>0,J38<=0),DL38,0) | DQ38: =IF(DA38>=0,DG38-DH38-DI38,-DK38) | DR38: =BD38*(1+DD38)+DQ38*(1+DD38/2) | DS38: =IF(5=0,personal_retiroInicial,DS37)*(1+g_ret)+(O38+P38+DH38)*(1+g_ret/2) | DT38: =IF(BB38=1,BL38*(1+g_appr),0) | DU38: =BP38-DJ38 | DV38: =BT38-(DI38-DJ38) | DW38: =CP38+DN38 | DX38: =IF(DN38>0,(CP38*CF38+DN38*prestamos_tasaFederalPosgrado)/(CP38+DN38),CF38) | DY38: =IF(DN38>0,0,CQ38) | DZ38: =DM38+DN38 | EA38: =CV38+DO38 | EB38: =IF(DO38>0,(CV38*CS38+DO38*prestamos_tasaPrivada)/(CV38+DO38),CS38) | EC38: =IF(DO38>0,0,CW38) | ED38: =CX38-DE38+DP38 | EE38: =IF(IF(5=0,"",EE37)<>"",EE37,IF(AND(BB38=1,DU38<=0.5,DV38<=0.5,OR(BH38=0,BJ38=1)),A38,"")) | EF38: =DU38+DV38+DW38+EA38+ED38+CD38 | EG38: =DR38+DS38+DT38-EF38 | EH38: =EG38/(1+g_inf)^(A38+1-2026)
A39: 2033 | B39: 6 | C39: =(1+g_inf)^(A39-2026) | D39: =SUMPRODUCT($Z$5:$Z$29,$E$5:$E$29*(1+$F$5:$F$29)^(A39-2026)*$G$5:$G$29*$H$5:$H$29*(1-$N$5:$N$29*$O$5:$O$29))*g_salMult+SUMPRODUCT(($B$5:$B$29>=A39)*($B$5:$B$29<A39+1)*$I$5:$I$29)*g_salMult | E39: =SUMPRODUCT($Z$5:$Z$29,$E$5:$E$29*(1+$F$5:$F$29)^(A39-2026)*$G$5:$G$29*$H$5:$H$29*$M$5:$M$29)*g_salMult | F39: =SUMPRODUCT($Z$5:$Z$29,$E$5:$E$29*(1+$F$5:$F$29)^(A39-2026)*$G$5:$G$29*$H$5:$H$29*$N$5:$N$29*$O$5:$O$29)*g_salMult | G39: =SUMPRODUCT($Z$5:$Z$29,$P$5:$P$29*(1+$F$5:$F$29)^(A39-2026)) | H39: =SUMPRODUCT($Z$5:$Z$29,$Q$5:$Q$29*(1+$F$5:$F$29)^(A39-2026))+IF(personal_llcActivo=1,personal_llcNeto*(1+personal_llcCrecimiento)^6,0) | I39: =SUMPRODUCT($Z$5:$Z$29,$J$5:$J$29/($C$5:$C$29-$B$5:$B$29+($C$5:$C$29=$B$5:$B$29)))*C39 | J39: =SUMPRODUCT($Z$5:$Z$29,$K$5:$K$29) | K39: =SUMPRODUCT($Z$5:$Z$29,$L$5:$L$29) | L39: =SUMPRODUCT($Z$5:$Z$29,$N$5:$N$29) | M39: =IF(SUMPRODUCT($Z$5:$Z$29,$R$5:$R$29)>0,1,0) | N39: =SUMPRODUCT(($AO$5:$AO$24>=A39)*($AO$5:$AO$24<A39+1)*$AP$5:$AP$24)*C39+IF(6=0,IF(sel_loc<>"miami",personal_costoMudanzaInicial,0),0) | O39: =MIN(personal_aporte403bPct*D39,retiro_limite403b*C39) | P39: =MIN(personal_aporte403bPct,personal_match403bPct)*E39 | Q39: =IF(G39>0,MAX(0,G39-impuestos_scorpCostoAnual*C39),0) | R39: =Q39*impuestos_scorpSalarioPct/(1+impuestos_ssTasa+impuestos_medicareTasa) | S39: =impuestos_ssTasa*MIN(R39,MAX(0,impuestos_ssTope*C39-D39))+impuestos_medicareTasa*R39 | T39: =Q39-R39-S39 | U39: =D39+R39 | V39: =H39*0.9235 | W39: =IF(H39>0,2*impuestos_ssTasa*MIN(V39,MAX(0,impuestos_ssTope*C39-U39))+2*impuestos_medicareTasa*V39,0) | X39: =impuestos_ssTasa*MIN(U39,impuestos_ssTope*C39)+impuestos_medicareTasa*U39+impuestos_medicareAdicional*MAX(0,U39+H39*0.9235-impuestos_medicareUmbral) | Y39: =MAX(0,D39-O39+R39+T39+H39-W39/2) | Z39: =MAX(0,Y39-impuestos_deduccionEstandar*C39) | AA39: =MIN(0.2*MAX(0,T39+H39-W39/2)*MAX(0,MIN(1,1-(Z39-impuestos_qbiUmbral*C39)/(impuestos_qbiRango*C39))),0.2*Z39) | AB39: =MAX(0,Z39-AA39) | AC39: =SUMPRODUCT((AB39>tb_federalBrackets_lo*C39)*(AB39-tb_federalBrackets_lo*C39)*tb_federalBrackets_dr) | AD39: =MAX(0,Y39-impuestos_nyDeduccion*C39) | AE39: =CHOOSE(loc_taxcode,0,impuestos_ohTasa*MAX(0,Y39-impuestos_ohExento*C39)+impuestos_ohMunicipal*U39,SUMPRODUCT((AD39>tb_nyBrackets_lo*C39)*(AD39-tb_nyBrackets_lo*C39)*tb_nyBrackets_dr)+loc_nyc*SUMPRODUCT((AD39>tb_nycBrackets_lo*C39)*(AD39-tb_nycBrackets_lo*C39)*tb_nycBrackets_dr)) | AF39: =AC39+AE39+X39+W39 | AG39: =D39+F39+R39+T39+H39 | AH39: =AG39-AF39-O39 | AI39: =D39+F39+G39+H39 | AJ39: =loc_gastosVida*C39*g_gastos | AK39: =IF(6=0,personal_liquidoInicial,DR38) | AL39: =IF(6=0,0,BB38) | AM39: =CHOOSE(sel_cfgIdx,loc_precio_duplex,loc_precio_inlaw,loc_precio_dosCasas,loc_precio_casaAdu,loc_precio_multi) | AN39: =AM39*(1+g_appr)^(A39-2026) | AO39: =IF(AND(M39=1,vivienda_prestamoMedico=1),1,0) | AP39: =IF(AO39=1,0.05,vivienda_enganchePct) | AQ39: =AN39*(1-AP39) | AR39: =PMT(g_mortRate/12,vivienda_plazoHipoteca*12,-AQ39) | AS39: =INDEX(cfg_units,sel_cfgIdx) | AT39: =AS39*loc_rentaUnidad*(1+g_inf)^(A39-2026)*(1-vivienda_vacancia) | AU39: =AR39+AN39*loc_impuestoPropPct/12+AM39*loc_seguroPct*(1+vivienda_inflacionSeguro)^(A39-2026)/12+IF(AND(AO39=0,AP39<0.2),AQ39*vivienda_pmiTasa/12,0) | AV39: =AN39*AP39+AN39*vivienda_cierrePct+general_reservaMeses/12*AJ39 | AW39: =(IF(6=0,MIN(personal_irsSaldo,personal_irsPagoMensual*12),MIN(CD38,personal_irsPagoMensual*12))+IF(CE39>0,PMT(CF39,MAX(1,prestamos_plazoAnios-CG39),-CE39),0)+IF(CR39>0,PMT(CS39,MAX(1,prestamos_plazoAnios-CT39),-CR39),0))/12 | AX39: =IF(OR(sel_cfg="duplex",sel_cfg="multi",sel_cfg="dosCasas"),0.75*personal_aporteFamiliaMensual,0) | AY39: =AU39-0.75*AT39-AX39+AW39 | AZ39: =(D39+G39+H39+0.5*F39)/12 | BA39: =IF(AND(AL39=0,A39>=vivienda_anioMinCompra,J39<0.5,AI39>0,AK39>=AV39,AY39<=vivienda_dtiMax*AZ39),1,0) | BB39: =MAX(AL39,BA39) | BC39: =IF(BA39=1,A39,IF(6=0,"",BC38)) | BD39: =AK39-IF(BA39=1,AN39*AP39+AN39*vivienda_cierrePct,0) | BE39: =IF(BA39=1,AN39,IF(6=0,0,BE38)) | BF39: =IF(BA39=1,AR39,IF(6=0,0,BF38)) | BG39: =IF(BA39=1,IF(AND(AO39=0,AP39<0.2),1,0),IF(6=0,0,BY38)) | BH39: =IF(sel_cfg="casaAdu",1,0) | BI39: =IF(AND(BB39=1,BH39=1,IF(6=0,0,BJ38)=0,A39>=IF(BC39="",9999,BC39)+vivienda_aduRetrasoAnios),1,0) | BJ39: =MAX(IF(6=0,0,BJ38),BI39) | BK39: =IF(BI39=1,PMT((g_mortRate+0.005)/12,180,-loc_precio_aduCosto*C39),IF(6=0,0,BK38)) | BL39: =IF(BA39=1,AN39,IF(6=0,0,DT38))+IF(BI39=1,loc_precio_aduCosto*C39,0) | BM39: =IF(BA39=1,AQ39,IF(6=0,0,DU38)) | BN39: =IF(BM39<=0,0,FV(g_mortRate/12,12,BF39,-BM39)) | BO39: =IF(BM39<=0,0,12*BF39+MIN(0,BN39)) | BP39: =MAX(0,BN39) | BQ39: =IF(BI39=1,loc_precio_aduCosto*C39,IF(6=0,0,DV38)) | BR39: =IF(BQ39<=0,0,FV((g_mortRate+0.005)/12,12,BK39,-BQ39)) | BS39: =IF(BQ39<=0,0,12*BK39+MIN(0,BR39)) | BT39: =MAX(0,BR39) | BU39: =IF(BB39=1,AM39*loc_seguroPct*(1+vivienda_inflacionSeguro)^(A39-2026)*IF(BJ39=1,1+loc_precio_aduCosto/AM39,1),0) | BV39: =BL39*loc_impuestoPropPct | BW39: =BL39*vivienda_mantenimientoPct | BX39: =IF(AND(BG39=1,BP39>0.8*BE39),BE39*(1-vivienda_enganchePct)*vivienda_pmiTasa,0) | BY39: =IF(AND(BG39=1,BP39>0.8*BE39),1,0) | BZ39: =IF(BB39=1,AS39*loc_rentaUnidad*12*C39*(1-vivienda_vacancia)*(1-vivienda_gestionPct),0) | CA39: =IF(BB39=1,BO39+BS39+BU39+BV39+BW39+BX39,loc_rentaMensual*12*C39) | CB39: =IF(BB39=1,personal_aporteFamiliaMensual*12,0) | CC39: =MIN(IF(6=0,personal_irsSaldo,CD38),personal_irsPagoMensual*12) | CD39: =IF(6=0,personal_irsSaldo,CD38)-CC39 | CE39: =IF(6=0,IF(personal_deudaEsFederal=1,personal_deudaEstudiantil,0),DW38) | CF39: =IF(6=0,personal_tasaDeudaEstudiantil,DX38) | CG39: =IF(6=0,0,DY38) | CH39: =IF(J39>=0.5,1,0) | CI39: =IF(AND(CH39=0,prestamos_pslfActivo=1,K39>=0.5,CE39>0),1,0) | CJ39: =CE39*CF39 | CK39: =MAX(prestamos_rapPagoMinimoAnual,IF(Y39<10000,0,MIN(0.1,INT(Y39/10000)/100))*Y39) | CL39: =IF(CE39<=0,0,IF(CH39=1,0,IF(CI39=1,MIN(CE39+CJ39,CK39),PMT(CF39,MAX(1,prestamos_plazoAnios-CG39),-CE39)))) | CM39: =IF(CE39<=0,0,IF(CH39=1,CE39+CJ39,IF(CI39=1,MAX(0,CE39-MAX(CL39-CJ39,MIN(600,CL39))),MAX(0,CE39*(1+CF39)-CL39)))) | CN39: =IF(6=0,0,CN38)+IF(CI39=1,12*MIN(1,K39),0) | CO39: =IF(AND(CI39=1,CN39>=prestamos_pslfPagos,CM39>0),CM39,0) | CP39: =CM39-CO39 | CQ39: =IF(AND(CE39>0,CH39=0,CI39=0),CG39+1,CG39) | CR39: =IF(6=0,IF(personal_deudaEsFederal=1,0,personal_deudaEstudiantil),EA38) | CS39: =IF(6=0,IF(personal_deudaEsFederal=1,prestamos_tasaPrivada,personal_tasaDeudaEstudiantil),EB38) | CT39: =IF(6=0,0,EC38) | CU39: =IF(OR(CR39<=0,CH39=1),0,PMT(CS39,MAX(1,prestamos_plazoAnios-CT39),-CR39)) | CV39: =IF(CR39<=0,0,IF(CH39=1,CR39*(1+CS39),MAX(0,CR39*(1+CS39)-CU39))) | CW39: =IF(AND(CR39>0,CH39=0),CT39+1,CT39) | CX39: =IF(6=0,0,ED38)*(1+general_tasaDeudaConsumo) | CY39: =L39*12*tiempos_travelGastoExtraMes*C39 | CZ39: =AJ39+CY39+CA39+CC39+CL39+CU39+I39+N39-BZ39-CB39 | DA39: =AH39-CZ39 | DB39: =IF(6=0,0,DB38)+DA39 | DC39: =AN39*vivienda_enganchePct+AN39*vivienda_cierrePct+general_reservaMeses/12*AJ39 | DD39: =IF(BB39=1,g_ret,IF(BD39>0,MIN(1,DC39/BD39),1)*g_cash+(1-IF(BD39>0,MIN(1,DC39/BD39),1))*g_ret) | DE39: =IF(DA39>=0,MIN(CX39,DA39),0) | DF39: =IF(DA39>=0,(1-general_tasaAhorro)*(DA39-DE39),0) | DG39: =IF(DA39>=0,DA39-DE39-DF39,0) | DH39: =MIN(personal_rothAnual,DG39) | DI39: =IF(AND(DA39>=0,BB39=1,BP39+BT39>0),MIN(vivienda_prepagoPct*(DG39-DH39),BP39+BT39),0) | DJ39: =MIN(DI39,BP39) | DK39: =IF(DA39<0,MIN(MAX(0,BD39),-DA39),0) | DL39: =IF(DA39<0,-DA39-DK39,0) | DM39: =IF(6=0,0,DZ38) | DN39: =IF(AND(DL39>0,J39>0),MIN(DL39,MIN(prestamos_topeAnualPosgrado*MIN(1,J39),MAX(0,prestamos_topeTotalPosgrado-DM39))),0) | DO39: =IF(AND(DL39>0,J39>0),DL39-DN39,0) | DP39: =IF(AND(DL39>0,J39<=0),DL39,0) | DQ39: =IF(DA39>=0,DG39-DH39-DI39,-DK39) | DR39: =BD39*(1+DD39)+DQ39*(1+DD39/2) | DS39: =IF(6=0,personal_retiroInicial,DS38)*(1+g_ret)+(O39+P39+DH39)*(1+g_ret/2) | DT39: =IF(BB39=1,BL39*(1+g_appr),0) | DU39: =BP39-DJ39 | DV39: =BT39-(DI39-DJ39) | DW39: =CP39+DN39 | DX39: =IF(DN39>0,(CP39*CF39+DN39*prestamos_tasaFederalPosgrado)/(CP39+DN39),CF39) | DY39: =IF(DN39>0,0,CQ39) | DZ39: =DM39+DN39 | EA39: =CV39+DO39 | EB39: =IF(DO39>0,(CV39*CS39+DO39*prestamos_tasaPrivada)/(CV39+DO39),CS39) | EC39: =IF(DO39>0,0,CW39) | ED39: =CX39-DE39+DP39 | EE39: =IF(IF(6=0,"",EE38)<>"",EE38,IF(AND(BB39=1,DU39<=0.5,DV39<=0.5,OR(BH39=0,BJ39=1)),A39,"")) | EF39: =DU39+DV39+DW39+EA39+ED39+CD39 | EG39: =DR39+DS39+DT39-EF39 | EH39: =EG39/(1+g_inf)^(A39+1-2026)
A40: 2034 | B40: 7 | C40: =(1+g_inf)^(A40-2026) | D40: =SUMPRODUCT($AA$5:$AA$29,$E$5:$E$29*(1+$F$5:$F$29)^(A40-2026)*$G$5:$G$29*$H$5:$H$29*(1-$N$5:$N$29*$O$5:$O$29))*g_salMult+SUMPRODUCT(($B$5:$B$29>=A40)*($B$5:$B$29<A40+1)*$I$5:$I$29)*g_salMult | E40: =SUMPRODUCT($AA$5:$AA$29,$E$5:$E$29*(1+$F$5:$F$29)^(A40-2026)*$G$5:$G$29*$H$5:$H$29*$M$5:$M$29)*g_salMult | F40: =SUMPRODUCT($AA$5:$AA$29,$E$5:$E$29*(1+$F$5:$F$29)^(A40-2026)*$G$5:$G$29*$H$5:$H$29*$N$5:$N$29*$O$5:$O$29)*g_salMult | G40: =SUMPRODUCT($AA$5:$AA$29,$P$5:$P$29*(1+$F$5:$F$29)^(A40-2026)) | H40: =SUMPRODUCT($AA$5:$AA$29,$Q$5:$Q$29*(1+$F$5:$F$29)^(A40-2026))+IF(personal_llcActivo=1,personal_llcNeto*(1+personal_llcCrecimiento)^7,0) | I40: =SUMPRODUCT($AA$5:$AA$29,$J$5:$J$29/($C$5:$C$29-$B$5:$B$29+($C$5:$C$29=$B$5:$B$29)))*C40 | J40: =SUMPRODUCT($AA$5:$AA$29,$K$5:$K$29) | K40: =SUMPRODUCT($AA$5:$AA$29,$L$5:$L$29) | L40: =SUMPRODUCT($AA$5:$AA$29,$N$5:$N$29) | M40: =IF(SUMPRODUCT($AA$5:$AA$29,$R$5:$R$29)>0,1,0) | N40: =SUMPRODUCT(($AO$5:$AO$24>=A40)*($AO$5:$AO$24<A40+1)*$AP$5:$AP$24)*C40+IF(7=0,IF(sel_loc<>"miami",personal_costoMudanzaInicial,0),0) | O40: =MIN(personal_aporte403bPct*D40,retiro_limite403b*C40) | P40: =MIN(personal_aporte403bPct,personal_match403bPct)*E40 | Q40: =IF(G40>0,MAX(0,G40-impuestos_scorpCostoAnual*C40),0) | R40: =Q40*impuestos_scorpSalarioPct/(1+impuestos_ssTasa+impuestos_medicareTasa) | S40: =impuestos_ssTasa*MIN(R40,MAX(0,impuestos_ssTope*C40-D40))+impuestos_medicareTasa*R40 | T40: =Q40-R40-S40 | U40: =D40+R40 | V40: =H40*0.9235 | W40: =IF(H40>0,2*impuestos_ssTasa*MIN(V40,MAX(0,impuestos_ssTope*C40-U40))+2*impuestos_medicareTasa*V40,0) | X40: =impuestos_ssTasa*MIN(U40,impuestos_ssTope*C40)+impuestos_medicareTasa*U40+impuestos_medicareAdicional*MAX(0,U40+H40*0.9235-impuestos_medicareUmbral) | Y40: =MAX(0,D40-O40+R40+T40+H40-W40/2) | Z40: =MAX(0,Y40-impuestos_deduccionEstandar*C40) | AA40: =MIN(0.2*MAX(0,T40+H40-W40/2)*MAX(0,MIN(1,1-(Z40-impuestos_qbiUmbral*C40)/(impuestos_qbiRango*C40))),0.2*Z40) | AB40: =MAX(0,Z40-AA40) | AC40: =SUMPRODUCT((AB40>tb_federalBrackets_lo*C40)*(AB40-tb_federalBrackets_lo*C40)*tb_federalBrackets_dr) | AD40: =MAX(0,Y40-impuestos_nyDeduccion*C40) | AE40: =CHOOSE(loc_taxcode,0,impuestos_ohTasa*MAX(0,Y40-impuestos_ohExento*C40)+impuestos_ohMunicipal*U40,SUMPRODUCT((AD40>tb_nyBrackets_lo*C40)*(AD40-tb_nyBrackets_lo*C40)*tb_nyBrackets_dr)+loc_nyc*SUMPRODUCT((AD40>tb_nycBrackets_lo*C40)*(AD40-tb_nycBrackets_lo*C40)*tb_nycBrackets_dr)) | AF40: =AC40+AE40+X40+W40 | AG40: =D40+F40+R40+T40+H40 | AH40: =AG40-AF40-O40 | AI40: =D40+F40+G40+H40 | AJ40: =loc_gastosVida*C40*g_gastos | AK40: =IF(7=0,personal_liquidoInicial,DR39) | AL40: =IF(7=0,0,BB39) | AM40: =CHOOSE(sel_cfgIdx,loc_precio_duplex,loc_precio_inlaw,loc_precio_dosCasas,loc_precio_casaAdu,loc_precio_multi) | AN40: =AM40*(1+g_appr)^(A40-2026) | AO40: =IF(AND(M40=1,vivienda_prestamoMedico=1),1,0) | AP40: =IF(AO40=1,0.05,vivienda_enganchePct) | AQ40: =AN40*(1-AP40) | AR40: =PMT(g_mortRate/12,vivienda_plazoHipoteca*12,-AQ40) | AS40: =INDEX(cfg_units,sel_cfgIdx) | AT40: =AS40*loc_rentaUnidad*(1+g_inf)^(A40-2026)*(1-vivienda_vacancia) | AU40: =AR40+AN40*loc_impuestoPropPct/12+AM40*loc_seguroPct*(1+vivienda_inflacionSeguro)^(A40-2026)/12+IF(AND(AO40=0,AP40<0.2),AQ40*vivienda_pmiTasa/12,0) | AV40: =AN40*AP40+AN40*vivienda_cierrePct+general_reservaMeses/12*AJ40 | AW40: =(IF(7=0,MIN(personal_irsSaldo,personal_irsPagoMensual*12),MIN(CD39,personal_irsPagoMensual*12))+IF(CE40>0,PMT(CF40,MAX(1,prestamos_plazoAnios-CG40),-CE40),0)+IF(CR40>0,PMT(CS40,MAX(1,prestamos_plazoAnios-CT40),-CR40),0))/12 | AX40: =IF(OR(sel_cfg="duplex",sel_cfg="multi",sel_cfg="dosCasas"),0.75*personal_aporteFamiliaMensual,0) | AY40: =AU40-0.75*AT40-AX40+AW40 | AZ40: =(D40+G40+H40+0.5*F40)/12 | BA40: =IF(AND(AL40=0,A40>=vivienda_anioMinCompra,J40<0.5,AI40>0,AK40>=AV40,AY40<=vivienda_dtiMax*AZ40),1,0) | BB40: =MAX(AL40,BA40) | BC40: =IF(BA40=1,A40,IF(7=0,"",BC39)) | BD40: =AK40-IF(BA40=1,AN40*AP40+AN40*vivienda_cierrePct,0) | BE40: =IF(BA40=1,AN40,IF(7=0,0,BE39)) | BF40: =IF(BA40=1,AR40,IF(7=0,0,BF39)) | BG40: =IF(BA40=1,IF(AND(AO40=0,AP40<0.2),1,0),IF(7=0,0,BY39)) | BH40: =IF(sel_cfg="casaAdu",1,0) | BI40: =IF(AND(BB40=1,BH40=1,IF(7=0,0,BJ39)=0,A40>=IF(BC40="",9999,BC40)+vivienda_aduRetrasoAnios),1,0) | BJ40: =MAX(IF(7=0,0,BJ39),BI40) | BK40: =IF(BI40=1,PMT((g_mortRate+0.005)/12,180,-loc_precio_aduCosto*C40),IF(7=0,0,BK39)) | BL40: =IF(BA40=1,AN40,IF(7=0,0,DT39))+IF(BI40=1,loc_precio_aduCosto*C40,0) | BM40: =IF(BA40=1,AQ40,IF(7=0,0,DU39)) | BN40: =IF(BM40<=0,0,FV(g_mortRate/12,12,BF40,-BM40)) | BO40: =IF(BM40<=0,0,12*BF40+MIN(0,BN40)) | BP40: =MAX(0,BN40) | BQ40: =IF(BI40=1,loc_precio_aduCosto*C40,IF(7=0,0,DV39)) | BR40: =IF(BQ40<=0,0,FV((g_mortRate+0.005)/12,12,BK40,-BQ40)) | BS40: =IF(BQ40<=0,0,12*BK40+MIN(0,BR40)) | BT40: =MAX(0,BR40) | BU40: =IF(BB40=1,AM40*loc_seguroPct*(1+vivienda_inflacionSeguro)^(A40-2026)*IF(BJ40=1,1+loc_precio_aduCosto/AM40,1),0) | BV40: =BL40*loc_impuestoPropPct | BW40: =BL40*vivienda_mantenimientoPct | BX40: =IF(AND(BG40=1,BP40>0.8*BE40),BE40*(1-vivienda_enganchePct)*vivienda_pmiTasa,0) | BY40: =IF(AND(BG40=1,BP40>0.8*BE40),1,0) | BZ40: =IF(BB40=1,AS40*loc_rentaUnidad*12*C40*(1-vivienda_vacancia)*(1-vivienda_gestionPct),0) | CA40: =IF(BB40=1,BO40+BS40+BU40+BV40+BW40+BX40,loc_rentaMensual*12*C40) | CB40: =IF(BB40=1,personal_aporteFamiliaMensual*12,0) | CC40: =MIN(IF(7=0,personal_irsSaldo,CD39),personal_irsPagoMensual*12) | CD40: =IF(7=0,personal_irsSaldo,CD39)-CC40 | CE40: =IF(7=0,IF(personal_deudaEsFederal=1,personal_deudaEstudiantil,0),DW39) | CF40: =IF(7=0,personal_tasaDeudaEstudiantil,DX39) | CG40: =IF(7=0,0,DY39) | CH40: =IF(J40>=0.5,1,0) | CI40: =IF(AND(CH40=0,prestamos_pslfActivo=1,K40>=0.5,CE40>0),1,0) | CJ40: =CE40*CF40 | CK40: =MAX(prestamos_rapPagoMinimoAnual,IF(Y40<10000,0,MIN(0.1,INT(Y40/10000)/100))*Y40) | CL40: =IF(CE40<=0,0,IF(CH40=1,0,IF(CI40=1,MIN(CE40+CJ40,CK40),PMT(CF40,MAX(1,prestamos_plazoAnios-CG40),-CE40)))) | CM40: =IF(CE40<=0,0,IF(CH40=1,CE40+CJ40,IF(CI40=1,MAX(0,CE40-MAX(CL40-CJ40,MIN(600,CL40))),MAX(0,CE40*(1+CF40)-CL40)))) | CN40: =IF(7=0,0,CN39)+IF(CI40=1,12*MIN(1,K40),0) | CO40: =IF(AND(CI40=1,CN40>=prestamos_pslfPagos,CM40>0),CM40,0) | CP40: =CM40-CO40 | CQ40: =IF(AND(CE40>0,CH40=0,CI40=0),CG40+1,CG40) | CR40: =IF(7=0,IF(personal_deudaEsFederal=1,0,personal_deudaEstudiantil),EA39) | CS40: =IF(7=0,IF(personal_deudaEsFederal=1,prestamos_tasaPrivada,personal_tasaDeudaEstudiantil),EB39) | CT40: =IF(7=0,0,EC39) | CU40: =IF(OR(CR40<=0,CH40=1),0,PMT(CS40,MAX(1,prestamos_plazoAnios-CT40),-CR40)) | CV40: =IF(CR40<=0,0,IF(CH40=1,CR40*(1+CS40),MAX(0,CR40*(1+CS40)-CU40))) | CW40: =IF(AND(CR40>0,CH40=0),CT40+1,CT40) | CX40: =IF(7=0,0,ED39)*(1+general_tasaDeudaConsumo) | CY40: =L40*12*tiempos_travelGastoExtraMes*C40 | CZ40: =AJ40+CY40+CA40+CC40+CL40+CU40+I40+N40-BZ40-CB40 | DA40: =AH40-CZ40 | DB40: =IF(7=0,0,DB39)+DA40 | DC40: =AN40*vivienda_enganchePct+AN40*vivienda_cierrePct+general_reservaMeses/12*AJ40 | DD40: =IF(BB40=1,g_ret,IF(BD40>0,MIN(1,DC40/BD40),1)*g_cash+(1-IF(BD40>0,MIN(1,DC40/BD40),1))*g_ret) | DE40: =IF(DA40>=0,MIN(CX40,DA40),0) | DF40: =IF(DA40>=0,(1-general_tasaAhorro)*(DA40-DE40),0) | DG40: =IF(DA40>=0,DA40-DE40-DF40,0) | DH40: =MIN(personal_rothAnual,DG40) | DI40: =IF(AND(DA40>=0,BB40=1,BP40+BT40>0),MIN(vivienda_prepagoPct*(DG40-DH40),BP40+BT40),0) | DJ40: =MIN(DI40,BP40) | DK40: =IF(DA40<0,MIN(MAX(0,BD40),-DA40),0) | DL40: =IF(DA40<0,-DA40-DK40,0) | DM40: =IF(7=0,0,DZ39) | DN40: =IF(AND(DL40>0,J40>0),MIN(DL40,MIN(prestamos_topeAnualPosgrado*MIN(1,J40),MAX(0,prestamos_topeTotalPosgrado-DM40))),0) | DO40: =IF(AND(DL40>0,J40>0),DL40-DN40,0) | DP40: =IF(AND(DL40>0,J40<=0),DL40,0) | DQ40: =IF(DA40>=0,DG40-DH40-DI40,-DK40) | DR40: =BD40*(1+DD40)+DQ40*(1+DD40/2) | DS40: =IF(7=0,personal_retiroInicial,DS39)*(1+g_ret)+(O40+P40+DH40)*(1+g_ret/2) | DT40: =IF(BB40=1,BL40*(1+g_appr),0) | DU40: =BP40-DJ40 | DV40: =BT40-(DI40-DJ40) | DW40: =CP40+DN40 | DX40: =IF(DN40>0,(CP40*CF40+DN40*prestamos_tasaFederalPosgrado)/(CP40+DN40),CF40) | DY40: =IF(DN40>0,0,CQ40) | DZ40: =DM40+DN40 | EA40: =CV40+DO40 | EB40: =IF(DO40>0,(CV40*CS40+DO40*prestamos_tasaPrivada)/(CV40+DO40),CS40) | EC40: =IF(DO40>0,0,CW40) | ED40: =CX40-DE40+DP40 | EE40: =IF(IF(7=0,"",EE39)<>"",EE39,IF(AND(BB40=1,DU40<=0.5,DV40<=0.5,OR(BH40=0,BJ40=1)),A40,"")) | EF40: =DU40+DV40+DW40+EA40+ED40+CD40 | EG40: =DR40+DS40+DT40-EF40 | EH40: =EG40/(1+g_inf)^(A40+1-2026)
A41: 2035 | B41: 8 | C41: =(1+g_inf)^(A41-2026) | D41: =SUMPRODUCT($AB$5:$AB$29,$E$5:$E$29*(1+$F$5:$F$29)^(A41-2026)*$G$5:$G$29*$H$5:$H$29*(1-$N$5:$N$29*$O$5:$O$29))*g_salMult+SUMPRODUCT(($B$5:$B$29>=A41)*($B$5:$B$29<A41+1)*$I$5:$I$29)*g_salMult | E41: =SUMPRODUCT($AB$5:$AB$29,$E$5:$E$29*(1+$F$5:$F$29)^(A41-2026)*$G$5:$G$29*$H$5:$H$29*$M$5:$M$29)*g_salMult | F41: =SUMPRODUCT($AB$5:$AB$29,$E$5:$E$29*(1+$F$5:$F$29)^(A41-2026)*$G$5:$G$29*$H$5:$H$29*$N$5:$N$29*$O$5:$O$29)*g_salMult | G41: =SUMPRODUCT($AB$5:$AB$29,$P$5:$P$29*(1+$F$5:$F$29)^(A41-2026)) | H41: =SUMPRODUCT($AB$5:$AB$29,$Q$5:$Q$29*(1+$F$5:$F$29)^(A41-2026))+IF(personal_llcActivo=1,personal_llcNeto*(1+personal_llcCrecimiento)^8,0) | I41: =SUMPRODUCT($AB$5:$AB$29,$J$5:$J$29/($C$5:$C$29-$B$5:$B$29+($C$5:$C$29=$B$5:$B$29)))*C41 | J41: =SUMPRODUCT($AB$5:$AB$29,$K$5:$K$29) | K41: =SUMPRODUCT($AB$5:$AB$29,$L$5:$L$29) | L41: =SUMPRODUCT($AB$5:$AB$29,$N$5:$N$29) | M41: =IF(SUMPRODUCT($AB$5:$AB$29,$R$5:$R$29)>0,1,0) | N41: =SUMPRODUCT(($AO$5:$AO$24>=A41)*($AO$5:$AO$24<A41+1)*$AP$5:$AP$24)*C41+IF(8=0,IF(sel_loc<>"miami",personal_costoMudanzaInicial,0),0) | O41: =MIN(personal_aporte403bPct*D41,retiro_limite403b*C41) | P41: =MIN(personal_aporte403bPct,personal_match403bPct)*E41 | Q41: =IF(G41>0,MAX(0,G41-impuestos_scorpCostoAnual*C41),0) | R41: =Q41*impuestos_scorpSalarioPct/(1+impuestos_ssTasa+impuestos_medicareTasa) | S41: =impuestos_ssTasa*MIN(R41,MAX(0,impuestos_ssTope*C41-D41))+impuestos_medicareTasa*R41 | T41: =Q41-R41-S41 | U41: =D41+R41 | V41: =H41*0.9235 | W41: =IF(H41>0,2*impuestos_ssTasa*MIN(V41,MAX(0,impuestos_ssTope*C41-U41))+2*impuestos_medicareTasa*V41,0) | X41: =impuestos_ssTasa*MIN(U41,impuestos_ssTope*C41)+impuestos_medicareTasa*U41+impuestos_medicareAdicional*MAX(0,U41+H41*0.9235-impuestos_medicareUmbral) | Y41: =MAX(0,D41-O41+R41+T41+H41-W41/2) | Z41: =MAX(0,Y41-impuestos_deduccionEstandar*C41) | AA41: =MIN(0.2*MAX(0,T41+H41-W41/2)*MAX(0,MIN(1,1-(Z41-impuestos_qbiUmbral*C41)/(impuestos_qbiRango*C41))),0.2*Z41) | AB41: =MAX(0,Z41-AA41) | AC41: =SUMPRODUCT((AB41>tb_federalBrackets_lo*C41)*(AB41-tb_federalBrackets_lo*C41)*tb_federalBrackets_dr) | AD41: =MAX(0,Y41-impuestos_nyDeduccion*C41) | AE41: =CHOOSE(loc_taxcode,0,impuestos_ohTasa*MAX(0,Y41-impuestos_ohExento*C41)+impuestos_ohMunicipal*U41,SUMPRODUCT((AD41>tb_nyBrackets_lo*C41)*(AD41-tb_nyBrackets_lo*C41)*tb_nyBrackets_dr)+loc_nyc*SUMPRODUCT((AD41>tb_nycBrackets_lo*C41)*(AD41-tb_nycBrackets_lo*C41)*tb_nycBrackets_dr)) | AF41: =AC41+AE41+X41+W41 | AG41: =D41+F41+R41+T41+H41 | AH41: =AG41-AF41-O41 | AI41: =D41+F41+G41+H41 | AJ41: =loc_gastosVida*C41*g_gastos | AK41: =IF(8=0,personal_liquidoInicial,DR40) | AL41: =IF(8=0,0,BB40) | AM41: =CHOOSE(sel_cfgIdx,loc_precio_duplex,loc_precio_inlaw,loc_precio_dosCasas,loc_precio_casaAdu,loc_precio_multi) | AN41: =AM41*(1+g_appr)^(A41-2026) | AO41: =IF(AND(M41=1,vivienda_prestamoMedico=1),1,0) | AP41: =IF(AO41=1,0.05,vivienda_enganchePct) | AQ41: =AN41*(1-AP41) | AR41: =PMT(g_mortRate/12,vivienda_plazoHipoteca*12,-AQ41) | AS41: =INDEX(cfg_units,sel_cfgIdx) | AT41: =AS41*loc_rentaUnidad*(1+g_inf)^(A41-2026)*(1-vivienda_vacancia) | AU41: =AR41+AN41*loc_impuestoPropPct/12+AM41*loc_seguroPct*(1+vivienda_inflacionSeguro)^(A41-2026)/12+IF(AND(AO41=0,AP41<0.2),AQ41*vivienda_pmiTasa/12,0) | AV41: =AN41*AP41+AN41*vivienda_cierrePct+general_reservaMeses/12*AJ41 | AW41: =(IF(8=0,MIN(personal_irsSaldo,personal_irsPagoMensual*12),MIN(CD40,personal_irsPagoMensual*12))+IF(CE41>0,PMT(CF41,MAX(1,prestamos_plazoAnios-CG41),-CE41),0)+IF(CR41>0,PMT(CS41,MAX(1,prestamos_plazoAnios-CT41),-CR41),0))/12 | AX41: =IF(OR(sel_cfg="duplex",sel_cfg="multi",sel_cfg="dosCasas"),0.75*personal_aporteFamiliaMensual,0) | AY41: =AU41-0.75*AT41-AX41+AW41 | AZ41: =(D41+G41+H41+0.5*F41)/12 | BA41: =IF(AND(AL41=0,A41>=vivienda_anioMinCompra,J41<0.5,AI41>0,AK41>=AV41,AY41<=vivienda_dtiMax*AZ41),1,0) | BB41: =MAX(AL41,BA41) | BC41: =IF(BA41=1,A41,IF(8=0,"",BC40)) | BD41: =AK41-IF(BA41=1,AN41*AP41+AN41*vivienda_cierrePct,0) | BE41: =IF(BA41=1,AN41,IF(8=0,0,BE40)) | BF41: =IF(BA41=1,AR41,IF(8=0,0,BF40)) | BG41: =IF(BA41=1,IF(AND(AO41=0,AP41<0.2),1,0),IF(8=0,0,BY40)) | BH41: =IF(sel_cfg="casaAdu",1,0) | BI41: =IF(AND(BB41=1,BH41=1,IF(8=0,0,BJ40)=0,A41>=IF(BC41="",9999,BC41)+vivienda_aduRetrasoAnios),1,0) | BJ41: =MAX(IF(8=0,0,BJ40),BI41) | BK41: =IF(BI41=1,PMT((g_mortRate+0.005)/12,180,-loc_precio_aduCosto*C41),IF(8=0,0,BK40)) | BL41: =IF(BA41=1,AN41,IF(8=0,0,DT40))+IF(BI41=1,loc_precio_aduCosto*C41,0) | BM41: =IF(BA41=1,AQ41,IF(8=0,0,DU40)) | BN41: =IF(BM41<=0,0,FV(g_mortRate/12,12,BF41,-BM41)) | BO41: =IF(BM41<=0,0,12*BF41+MIN(0,BN41)) | BP41: =MAX(0,BN41) | BQ41: =IF(BI41=1,loc_precio_aduCosto*C41,IF(8=0,0,DV40)) | BR41: =IF(BQ41<=0,0,FV((g_mortRate+0.005)/12,12,BK41,-BQ41)) | BS41: =IF(BQ41<=0,0,12*BK41+MIN(0,BR41)) | BT41: =MAX(0,BR41) | BU41: =IF(BB41=1,AM41*loc_seguroPct*(1+vivienda_inflacionSeguro)^(A41-2026)*IF(BJ41=1,1+loc_precio_aduCosto/AM41,1),0) | BV41: =BL41*loc_impuestoPropPct | BW41: =BL41*vivienda_mantenimientoPct | BX41: =IF(AND(BG41=1,BP41>0.8*BE41),BE41*(1-vivienda_enganchePct)*vivienda_pmiTasa,0) | BY41: =IF(AND(BG41=1,BP41>0.8*BE41),1,0) | BZ41: =IF(BB41=1,AS41*loc_rentaUnidad*12*C41*(1-vivienda_vacancia)*(1-vivienda_gestionPct),0) | CA41: =IF(BB41=1,BO41+BS41+BU41+BV41+BW41+BX41,loc_rentaMensual*12*C41) | CB41: =IF(BB41=1,personal_aporteFamiliaMensual*12,0) | CC41: =MIN(IF(8=0,personal_irsSaldo,CD40),personal_irsPagoMensual*12) | CD41: =IF(8=0,personal_irsSaldo,CD40)-CC41 | CE41: =IF(8=0,IF(personal_deudaEsFederal=1,personal_deudaEstudiantil,0),DW40) | CF41: =IF(8=0,personal_tasaDeudaEstudiantil,DX40) | CG41: =IF(8=0,0,DY40) | CH41: =IF(J41>=0.5,1,0) | CI41: =IF(AND(CH41=0,prestamos_pslfActivo=1,K41>=0.5,CE41>0),1,0) | CJ41: =CE41*CF41 | CK41: =MAX(prestamos_rapPagoMinimoAnual,IF(Y41<10000,0,MIN(0.1,INT(Y41/10000)/100))*Y41) | CL41: =IF(CE41<=0,0,IF(CH41=1,0,IF(CI41=1,MIN(CE41+CJ41,CK41),PMT(CF41,MAX(1,prestamos_plazoAnios-CG41),-CE41)))) | CM41: =IF(CE41<=0,0,IF(CH41=1,CE41+CJ41,IF(CI41=1,MAX(0,CE41-MAX(CL41-CJ41,MIN(600,CL41))),MAX(0,CE41*(1+CF41)-CL41)))) | CN41: =IF(8=0,0,CN40)+IF(CI41=1,12*MIN(1,K41),0) | CO41: =IF(AND(CI41=1,CN41>=prestamos_pslfPagos,CM41>0),CM41,0) | CP41: =CM41-CO41 | CQ41: =IF(AND(CE41>0,CH41=0,CI41=0),CG41+1,CG41) | CR41: =IF(8=0,IF(personal_deudaEsFederal=1,0,personal_deudaEstudiantil),EA40) | CS41: =IF(8=0,IF(personal_deudaEsFederal=1,prestamos_tasaPrivada,personal_tasaDeudaEstudiantil),EB40) | CT41: =IF(8=0,0,EC40) | CU41: =IF(OR(CR41<=0,CH41=1),0,PMT(CS41,MAX(1,prestamos_plazoAnios-CT41),-CR41)) | CV41: =IF(CR41<=0,0,IF(CH41=1,CR41*(1+CS41),MAX(0,CR41*(1+CS41)-CU41))) | CW41: =IF(AND(CR41>0,CH41=0),CT41+1,CT41) | CX41: =IF(8=0,0,ED40)*(1+general_tasaDeudaConsumo) | CY41: =L41*12*tiempos_travelGastoExtraMes*C41 | CZ41: =AJ41+CY41+CA41+CC41+CL41+CU41+I41+N41-BZ41-CB41 | DA41: =AH41-CZ41 | DB41: =IF(8=0,0,DB40)+DA41 | DC41: =AN41*vivienda_enganchePct+AN41*vivienda_cierrePct+general_reservaMeses/12*AJ41 | DD41: =IF(BB41=1,g_ret,IF(BD41>0,MIN(1,DC41/BD41),1)*g_cash+(1-IF(BD41>0,MIN(1,DC41/BD41),1))*g_ret) | DE41: =IF(DA41>=0,MIN(CX41,DA41),0) | DF41: =IF(DA41>=0,(1-general_tasaAhorro)*(DA41-DE41),0) | DG41: =IF(DA41>=0,DA41-DE41-DF41,0) | DH41: =MIN(personal_rothAnual,DG41) | DI41: =IF(AND(DA41>=0,BB41=1,BP41+BT41>0),MIN(vivienda_prepagoPct*(DG41-DH41),BP41+BT41),0) | DJ41: =MIN(DI41,BP41) | DK41: =IF(DA41<0,MIN(MAX(0,BD41),-DA41),0) | DL41: =IF(DA41<0,-DA41-DK41,0) | DM41: =IF(8=0,0,DZ40) | DN41: =IF(AND(DL41>0,J41>0),MIN(DL41,MIN(prestamos_topeAnualPosgrado*MIN(1,J41),MAX(0,prestamos_topeTotalPosgrado-DM41))),0) | DO41: =IF(AND(DL41>0,J41>0),DL41-DN41,0) | DP41: =IF(AND(DL41>0,J41<=0),DL41,0) | DQ41: =IF(DA41>=0,DG41-DH41-DI41,-DK41) | DR41: =BD41*(1+DD41)+DQ41*(1+DD41/2) | DS41: =IF(8=0,personal_retiroInicial,DS40)*(1+g_ret)+(O41+P41+DH41)*(1+g_ret/2) | DT41: =IF(BB41=1,BL41*(1+g_appr),0) | DU41: =BP41-DJ41 | DV41: =BT41-(DI41-DJ41) | DW41: =CP41+DN41 | DX41: =IF(DN41>0,(CP41*CF41+DN41*prestamos_tasaFederalPosgrado)/(CP41+DN41),CF41) | DY41: =IF(DN41>0,0,CQ41) | DZ41: =DM41+DN41 | EA41: =CV41+DO41 | EB41: =IF(DO41>0,(CV41*CS41+DO41*prestamos_tasaPrivada)/(CV41+DO41),CS41) | EC41: =IF(DO41>0,0,CW41) | ED41: =CX41-DE41+DP41 | EE41: =IF(IF(8=0,"",EE40)<>"",EE40,IF(AND(BB41=1,DU41<=0.5,DV41<=0.5,OR(BH41=0,BJ41=1)),A41,"")) | EF41: =DU41+DV41+DW41+EA41+ED41+CD41 | EG41: =DR41+DS41+DT41-EF41 | EH41: =EG41/(1+g_inf)^(A41+1-2026)
A42: 2036 | B42: 9 | C42: =(1+g_inf)^(A42-2026) | D42: =SUMPRODUCT($AC$5:$AC$29,$E$5:$E$29*(1+$F$5:$F$29)^(A42-2026)*$G$5:$G$29*$H$5:$H$29*(1-$N$5:$N$29*$O$5:$O$29))*g_salMult+SUMPRODUCT(($B$5:$B$29>=A42)*($B$5:$B$29<A42+1)*$I$5:$I$29)*g_salMult | E42: =SUMPRODUCT($AC$5:$AC$29,$E$5:$E$29*(1+$F$5:$F$29)^(A42-2026)*$G$5:$G$29*$H$5:$H$29*$M$5:$M$29)*g_salMult | F42: =SUMPRODUCT($AC$5:$AC$29,$E$5:$E$29*(1+$F$5:$F$29)^(A42-2026)*$G$5:$G$29*$H$5:$H$29*$N$5:$N$29*$O$5:$O$29)*g_salMult | G42: =SUMPRODUCT($AC$5:$AC$29,$P$5:$P$29*(1+$F$5:$F$29)^(A42-2026)) | H42: =SUMPRODUCT($AC$5:$AC$29,$Q$5:$Q$29*(1+$F$5:$F$29)^(A42-2026))+IF(personal_llcActivo=1,personal_llcNeto*(1+personal_llcCrecimiento)^9,0) | I42: =SUMPRODUCT($AC$5:$AC$29,$J$5:$J$29/($C$5:$C$29-$B$5:$B$29+($C$5:$C$29=$B$5:$B$29)))*C42 | J42: =SUMPRODUCT($AC$5:$AC$29,$K$5:$K$29) | K42: =SUMPRODUCT($AC$5:$AC$29,$L$5:$L$29) | L42: =SUMPRODUCT($AC$5:$AC$29,$N$5:$N$29) | M42: =IF(SUMPRODUCT($AC$5:$AC$29,$R$5:$R$29)>0,1,0) | N42: =SUMPRODUCT(($AO$5:$AO$24>=A42)*($AO$5:$AO$24<A42+1)*$AP$5:$AP$24)*C42+IF(9=0,IF(sel_loc<>"miami",personal_costoMudanzaInicial,0),0) | O42: =MIN(personal_aporte403bPct*D42,retiro_limite403b*C42) | P42: =MIN(personal_aporte403bPct,personal_match403bPct)*E42 | Q42: =IF(G42>0,MAX(0,G42-impuestos_scorpCostoAnual*C42),0) | R42: =Q42*impuestos_scorpSalarioPct/(1+impuestos_ssTasa+impuestos_medicareTasa) | S42: =impuestos_ssTasa*MIN(R42,MAX(0,impuestos_ssTope*C42-D42))+impuestos_medicareTasa*R42 | T42: =Q42-R42-S42 | U42: =D42+R42 | V42: =H42*0.9235 | W42: =IF(H42>0,2*impuestos_ssTasa*MIN(V42,MAX(0,impuestos_ssTope*C42-U42))+2*impuestos_medicareTasa*V42,0) | X42: =impuestos_ssTasa*MIN(U42,impuestos_ssTope*C42)+impuestos_medicareTasa*U42+impuestos_medicareAdicional*MAX(0,U42+H42*0.9235-impuestos_medicareUmbral) | Y42: =MAX(0,D42-O42+R42+T42+H42-W42/2) | Z42: =MAX(0,Y42-impuestos_deduccionEstandar*C42) | AA42: =MIN(0.2*MAX(0,T42+H42-W42/2)*MAX(0,MIN(1,1-(Z42-impuestos_qbiUmbral*C42)/(impuestos_qbiRango*C42))),0.2*Z42) | AB42: =MAX(0,Z42-AA42) | AC42: =SUMPRODUCT((AB42>tb_federalBrackets_lo*C42)*(AB42-tb_federalBrackets_lo*C42)*tb_federalBrackets_dr) | AD42: =MAX(0,Y42-impuestos_nyDeduccion*C42) | AE42: =CHOOSE(loc_taxcode,0,impuestos_ohTasa*MAX(0,Y42-impuestos_ohExento*C42)+impuestos_ohMunicipal*U42,SUMPRODUCT((AD42>tb_nyBrackets_lo*C42)*(AD42-tb_nyBrackets_lo*C42)*tb_nyBrackets_dr)+loc_nyc*SUMPRODUCT((AD42>tb_nycBrackets_lo*C42)*(AD42-tb_nycBrackets_lo*C42)*tb_nycBrackets_dr)) | AF42: =AC42+AE42+X42+W42 | AG42: =D42+F42+R42+T42+H42 | AH42: =AG42-AF42-O42 | AI42: =D42+F42+G42+H42 | AJ42: =loc_gastosVida*C42*g_gastos | AK42: =IF(9=0,personal_liquidoInicial,DR41) | AL42: =IF(9=0,0,BB41) | AM42: =CHOOSE(sel_cfgIdx,loc_precio_duplex,loc_precio_inlaw,loc_precio_dosCasas,loc_precio_casaAdu,loc_precio_multi) | AN42: =AM42*(1+g_appr)^(A42-2026) | AO42: =IF(AND(M42=1,vivienda_prestamoMedico=1),1,0) | AP42: =IF(AO42=1,0.05,vivienda_enganchePct) | AQ42: =AN42*(1-AP42) | AR42: =PMT(g_mortRate/12,vivienda_plazoHipoteca*12,-AQ42) | AS42: =INDEX(cfg_units,sel_cfgIdx) | AT42: =AS42*loc_rentaUnidad*(1+g_inf)^(A42-2026)*(1-vivienda_vacancia) | AU42: =AR42+AN42*loc_impuestoPropPct/12+AM42*loc_seguroPct*(1+vivienda_inflacionSeguro)^(A42-2026)/12+IF(AND(AO42=0,AP42<0.2),AQ42*vivienda_pmiTasa/12,0) | AV42: =AN42*AP42+AN42*vivienda_cierrePct+general_reservaMeses/12*AJ42 | AW42: =(IF(9=0,MIN(personal_irsSaldo,personal_irsPagoMensual*12),MIN(CD41,personal_irsPagoMensual*12))+IF(CE42>0,PMT(CF42,MAX(1,prestamos_plazoAnios-CG42),-CE42),0)+IF(CR42>0,PMT(CS42,MAX(1,prestamos_plazoAnios-CT42),-CR42),0))/12 | AX42: =IF(OR(sel_cfg="duplex",sel_cfg="multi",sel_cfg="dosCasas"),0.75*personal_aporteFamiliaMensual,0) | AY42: =AU42-0.75*AT42-AX42+AW42 | AZ42: =(D42+G42+H42+0.5*F42)/12 | BA42: =IF(AND(AL42=0,A42>=vivienda_anioMinCompra,J42<0.5,AI42>0,AK42>=AV42,AY42<=vivienda_dtiMax*AZ42),1,0) | BB42: =MAX(AL42,BA42) | BC42: =IF(BA42=1,A42,IF(9=0,"",BC41)) | BD42: =AK42-IF(BA42=1,AN42*AP42+AN42*vivienda_cierrePct,0) | BE42: =IF(BA42=1,AN42,IF(9=0,0,BE41)) | BF42: =IF(BA42=1,AR42,IF(9=0,0,BF41)) | BG42: =IF(BA42=1,IF(AND(AO42=0,AP42<0.2),1,0),IF(9=0,0,BY41)) | BH42: =IF(sel_cfg="casaAdu",1,0) | BI42: =IF(AND(BB42=1,BH42=1,IF(9=0,0,BJ41)=0,A42>=IF(BC42="",9999,BC42)+vivienda_aduRetrasoAnios),1,0) | BJ42: =MAX(IF(9=0,0,BJ41),BI42) | BK42: =IF(BI42=1,PMT((g_mortRate+0.005)/12,180,-loc_precio_aduCosto*C42),IF(9=0,0,BK41)) | BL42: =IF(BA42=1,AN42,IF(9=0,0,DT41))+IF(BI42=1,loc_precio_aduCosto*C42,0) | BM42: =IF(BA42=1,AQ42,IF(9=0,0,DU41)) | BN42: =IF(BM42<=0,0,FV(g_mortRate/12,12,BF42,-BM42)) | BO42: =IF(BM42<=0,0,12*BF42+MIN(0,BN42)) | BP42: =MAX(0,BN42) | BQ42: =IF(BI42=1,loc_precio_aduCosto*C42,IF(9=0,0,DV41)) | BR42: =IF(BQ42<=0,0,FV((g_mortRate+0.005)/12,12,BK42,-BQ42)) | BS42: =IF(BQ42<=0,0,12*BK42+MIN(0,BR42)) | BT42: =MAX(0,BR42) | BU42: =IF(BB42=1,AM42*loc_seguroPct*(1+vivienda_inflacionSeguro)^(A42-2026)*IF(BJ42=1,1+loc_precio_aduCosto/AM42,1),0) | BV42: =BL42*loc_impuestoPropPct | BW42: =BL42*vivienda_mantenimientoPct | BX42: =IF(AND(BG42=1,BP42>0.8*BE42),BE42*(1-vivienda_enganchePct)*vivienda_pmiTasa,0) | BY42: =IF(AND(BG42=1,BP42>0.8*BE42),1,0) | BZ42: =IF(BB42=1,AS42*loc_rentaUnidad*12*C42*(1-vivienda_vacancia)*(1-vivienda_gestionPct),0) | CA42: =IF(BB42=1,BO42+BS42+BU42+BV42+BW42+BX42,loc_rentaMensual*12*C42) | CB42: =IF(BB42=1,personal_aporteFamiliaMensual*12,0) | CC42: =MIN(IF(9=0,personal_irsSaldo,CD41),personal_irsPagoMensual*12) | CD42: =IF(9=0,personal_irsSaldo,CD41)-CC42 | CE42: =IF(9=0,IF(personal_deudaEsFederal=1,personal_deudaEstudiantil,0),DW41) | CF42: =IF(9=0,personal_tasaDeudaEstudiantil,DX41) | CG42: =IF(9=0,0,DY41) | CH42: =IF(J42>=0.5,1,0) | CI42: =IF(AND(CH42=0,prestamos_pslfActivo=1,K42>=0.5,CE42>0),1,0) | CJ42: =CE42*CF42 | CK42: =MAX(prestamos_rapPagoMinimoAnual,IF(Y42<10000,0,MIN(0.1,INT(Y42/10000)/100))*Y42) | CL42: =IF(CE42<=0,0,IF(CH42=1,0,IF(CI42=1,MIN(CE42+CJ42,CK42),PMT(CF42,MAX(1,prestamos_plazoAnios-CG42),-CE42)))) | CM42: =IF(CE42<=0,0,IF(CH42=1,CE42+CJ42,IF(CI42=1,MAX(0,CE42-MAX(CL42-CJ42,MIN(600,CL42))),MAX(0,CE42*(1+CF42)-CL42)))) | CN42: =IF(9=0,0,CN41)+IF(CI42=1,12*MIN(1,K42),0) | CO42: =IF(AND(CI42=1,CN42>=prestamos_pslfPagos,CM42>0),CM42,0) | CP42: =CM42-CO42 | CQ42: =IF(AND(CE42>0,CH42=0,CI42=0),CG42+1,CG42) | CR42: =IF(9=0,IF(personal_deudaEsFederal=1,0,personal_deudaEstudiantil),EA41) | CS42: =IF(9=0,IF(personal_deudaEsFederal=1,prestamos_tasaPrivada,personal_tasaDeudaEstudiantil),EB41) | CT42: =IF(9=0,0,EC41) | CU42: =IF(OR(CR42<=0,CH42=1),0,PMT(CS42,MAX(1,prestamos_plazoAnios-CT42),-CR42)) | CV42: =IF(CR42<=0,0,IF(CH42=1,CR42*(1+CS42),MAX(0,CR42*(1+CS42)-CU42))) | CW42: =IF(AND(CR42>0,CH42=0),CT42+1,CT42) | CX42: =IF(9=0,0,ED41)*(1+general_tasaDeudaConsumo) | CY42: =L42*12*tiempos_travelGastoExtraMes*C42 | CZ42: =AJ42+CY42+CA42+CC42+CL42+CU42+I42+N42-BZ42-CB42 | DA42: =AH42-CZ42 | DB42: =IF(9=0,0,DB41)+DA42 | DC42: =AN42*vivienda_enganchePct+AN42*vivienda_cierrePct+general_reservaMeses/12*AJ42 | DD42: =IF(BB42=1,g_ret,IF(BD42>0,MIN(1,DC42/BD42),1)*g_cash+(1-IF(BD42>0,MIN(1,DC42/BD42),1))*g_ret) | DE42: =IF(DA42>=0,MIN(CX42,DA42),0) | DF42: =IF(DA42>=0,(1-general_tasaAhorro)*(DA42-DE42),0) | DG42: =IF(DA42>=0,DA42-DE42-DF42,0) | DH42: =MIN(personal_rothAnual,DG42) | DI42: =IF(AND(DA42>=0,BB42=1,BP42+BT42>0),MIN(vivienda_prepagoPct*(DG42-DH42),BP42+BT42),0) | DJ42: =MIN(DI42,BP42) | DK42: =IF(DA42<0,MIN(MAX(0,BD42),-DA42),0) | DL42: =IF(DA42<0,-DA42-DK42,0) | DM42: =IF(9=0,0,DZ41) | DN42: =IF(AND(DL42>0,J42>0),MIN(DL42,MIN(prestamos_topeAnualPosgrado*MIN(1,J42),MAX(0,prestamos_topeTotalPosgrado-DM42))),0) | DO42: =IF(AND(DL42>0,J42>0),DL42-DN42,0) | DP42: =IF(AND(DL42>0,J42<=0),DL42,0) | DQ42: =IF(DA42>=0,DG42-DH42-DI42,-DK42) | DR42: =BD42*(1+DD42)+DQ42*(1+DD42/2) | DS42: =IF(9=0,personal_retiroInicial,DS41)*(1+g_ret)+(O42+P42+DH42)*(1+g_ret/2) | DT42: =IF(BB42=1,BL42*(1+g_appr),0) | DU42: =BP42-DJ42 | DV42: =BT42-(DI42-DJ42) | DW42: =CP42+DN42 | DX42: =IF(DN42>0,(CP42*CF42+DN42*prestamos_tasaFederalPosgrado)/(CP42+DN42),CF42) | DY42: =IF(DN42>0,0,CQ42) | DZ42: =DM42+DN42 | EA42: =CV42+DO42 | EB42: =IF(DO42>0,(CV42*CS42+DO42*prestamos_tasaPrivada)/(CV42+DO42),CS42) | EC42: =IF(DO42>0,0,CW42) | ED42: =CX42-DE42+DP42 | EE42: =IF(IF(9=0,"",EE41)<>"",EE41,IF(AND(BB42=1,DU42<=0.5,DV42<=0.5,OR(BH42=0,BJ42=1)),A42,"")) | EF42: =DU42+DV42+DW42+EA42+ED42+CD42 | EG42: =DR42+DS42+DT42-EF42 | EH42: =EG42/(1+g_inf)^(A42+1-2026)
